Workbook

Sheet IT
C2: DIVISI/DEPARTEMEN | D2: : Divisi Information Technology
C3: TUGAS UTAMA | D3: :
D4: - Menyediakan solusi aplikasi untuk mendukung efisiensi kegiatan operasional dan bisnis guna mencapai profitabilitas yang tinggi.
D5: - Memastikan tersedianya infrastruktur teknologi informasi guna mendukung kegiatan dan bisnis di perusahaan.
D6: - Memastikan tersedianya data yang terverifikasi agar dapat digunakan dalam pengambilan keputusan management.
C7: NAMA PENANGGUNG JAWAB RISIKO | D7: : Endiaz Ludia Arsanto (Head of IT DevSecOps)
C8: PERIODE | D8: : Triwulan 1 2026
A10: Identifikasi | I10: Analisis | AA10: Rencana Tindak Lanjut
A11: Kode/No | C11: Penjabaran Risiko | D11: Nama Aset | E11: Kategori Aset | F11: Kategori Risiko | G11: Internal/ Eksternal | H11: Kode (R/P) | I11: Akar Masalah | K11: Ancaman | L11: Kerentanan | M11: Pengendalian Saat Ini | N11: Kerahasiaan/ Keutuhan/ Ketersediaan | O11: Referensi Pengendalian | Q11: Tingkat Dampak | R11: Tingkat Probabilitas | S11: Nilai Risiko | T11: Tingkat Risiko | U11: Risk Appetite | V11: Risk Tolerance | W11: Respon Paska Kejadian | X11: Pencegahan | Y11: Risk Owner | Z11: Risk Owner | AA11: Rencana Penanganan Risiko | AD11: Tinjauan Q1 | AF11: Tinjauan Q2 | AH11: Tinjauan Q3 | AJ11: Tinjauan Q3 | AL11: Analisis Risiko | AO11: Tingkat Risiko | AP11: Status | AQ11: Sign off
I12: Penyebab | J12: Akibat | O12: Clause | P12: Annex | AA12: Aktivitas | AB12: PIC | AC12: Target Waktu | AD12: Rencana Tinjauan Q1 | AE12: Hasil | AF12: Rencana Tinjauan Q2 | AG12: Hasil | AH12: Rencana Tinjauan Q3 | AI12: Hasil | AJ12: Rencana Tinjauan Q4 | AK12: Hasil | AL12: Dampak | AM12: Probabilitas | AN12: Nilai Risiko Baru | AS12: - In Progress - 1 Maret 2026 | AT12: DONE | AU12: DONE Maret 2026
C13: Penjabaran Risiko | D13: Nama Aset | E13: Kategori Aset | F13: Kategori Risiko | G13: INT/EX | H13: R / P | I13: Penyebab / Faktor Pendorong | J13: Akibat / Manfaat | K13: Ancaman / Pendorong Eksternal | L13: Kerentanan / Hambatan Realisasi | M13: Pengendalian Saat Ini | N13: CIA | O13: Clause | P13: Annex | Q13: Dampak | R13: Probabilitas | S13: Nilai | T13: Tingkat | U13: Appetite | V13: Tolerance | W13: Respon Kejadian | X13: Pencegahan / Peluang | Y13: Owner 1 | Z13: Owner 2 | AA13: Aktivitas | AB13: PIC | AC13: Target | AD13: Q1 Review | AE13: Q1 Hasil | AF13: Q2 Review | AG13: Q2 Hasil | AH13: Q3 Review | AI13: Q3 Hasil | AJ13: Q4 Review | AK13: Q4 Hasil | AL13: Dampak | AM13: Probabilitas | AN13: Nilai | AO13: Tingkat | AP13: Status | AQ13: Sign off
A14: 1 | B14: =A14+1 -> 2 | C14: =B14+1 -> 3 | D14: =C14+1 -> 4 | E14: =D14+1 -> 5 | F14: =E14+1 -> 6 | G14: =F14+1 -> 7 | H14: =G14+1 -> 8 | I14: =H14+1 -> 9 | ... X14: =W14+1 -> 24 | Y14: =W14+1 -> 24 | Z14: =X14+1 -> 25 | AA14: =Z14+1 -> 26 | AB14: =AA14+1 -> 27 | AC14: =AB14+1 -> 28 | AD14: =AC14+1 -> 29 | AE14: =AD14+1 -> 30 | AF14: =AE14+1 -> 31 | AG14: =AF14+1 -> 32 | AH14: =AG14+1 -> 33 | ... AQ14: =AP14+1 -> 42
A15: IT | B15: =ROW()-ROW($B$14) -> 1 | C15: Penyalahgunaan endpoint API melalui serangan brute force, credential stuffing, dan enumerasi resource berpotensi terjadi tanpa hambatan teknis — akibat belum diimplementasikannya rate limiting pada API Gateway yang meninggalkan celah penyalahgunaan berbasis volume. | D15: API Endpoint | E15: Information | F15: Operasional | G15: External | H15: Risiko | I15: Rate limiting belum diimplementasikan akibat keterbatasan waktu eksplorasi dan anggaran untuk solusi yang proper; belum ada kebijakan yang menetapkan standar minimum keamanan API termasuk kewajiban rate limiting; validasi otorisasi level resource (BOLA - Broken Object Level Authorization/IDOR - Insecure Direct Object Reference) belum terdokumentasikan sebagai requirement yang wajib diverifikasi | J15: Endpoint API rentan terhadap serangan brute force dan credential stuffing yang memanfaatkan ketiadaan pembatasan jumlah request; enumerasi resource yang memungkinkan penyerang memetakan seluruh data yang dapat diakses; potensi Distributed Denial of Service pada level API yang mengganggu ketersediaan layanan; eksploitasi BOLA/IDOR yang memungkinkan akses data nasabah lain secara tidak terotorisasi | K15: Brute force dan credential stuffing pada endpoint autentikasi tanpa pembatasan percobaan; enumerasi resource melalui BOLA/IDOR yang mengekspos data nasabah lintas akun; API abuse yang membebani infrastruktur hingga mengganggu ketersediaan layanan; scraping data massal melalui endpoint yang tidak dibatasi frekuensinya | L15: Rate limiting belum diimplementasikan pada API Gateway Kong; validasi otorisasi level resource belum dikonfirmasi mencakup perlindungan BOLA/IDOR; tidak ada kebijakan standar minimum keamanan API yang mewajibkan rate limiting sebagai komponen wajib | M15: Mekanisme autentikasi JWT dengan symmetric dan asymmetric key telah diimplementasikan; WAF Coraza open-source telah aktif sebagai lapisan perlindungan aplikasi; API Gateway Kong telah digunakan sebagai titik kontrol terpusat; namun rate limiting belum diimplementasikan sehingga endpoint masih rentan terhadap serangan berbasis volume | N15: Semua (C - I - A) | O15: 8.1 – Perencanaan dan pengendalian operasional; 9.1 – Pemantauan, pengukuran, analisis dan evaluasi | P15: A.8.20 – Keamanan jaringan; A.8.25 – Siklus hidup pengembangan yang aman; A.8.26 – Persyaratan keamanan aplikasi; A.8.6 – Manajemen kapasitas | Q15: 4 | R15: 3 | S15: =Q15*R15 -> 12 | T15: =_xlfn.IFNA(VLOOKUP(S15,Parameter!$D$53:$E$77,2),"") -> SEDANG | U15: Rendah — perusahaan tidak bersedia membiarkan endpoint API beroperasi tanpa rate limiting mengingat ketiadaannya secara langsung membuka celah penyalahgunaan berbasis volume yang dapat berdampak pada kerahasiaan data nasabah dan ketersediaan layanan | V15: Sedang — perusahaan masih dapat beroperasi selama nilai risiko residual ≤ 9; jika residual masih >9, wajib eskalasi ke manajemen. Sebagai syarat minimum toleransi, organisasi wajib memastikan telah tersedia: (1) konfigurasi rate limiting aktif pada API Gateway Kong untuk seluruh endpoint yang menghadap publik, dan (2) validasi otorisasi level resource yang terkonfirmasi mencakup perlindungan terhadap BOLA/IDOR pada endpoint yang menangani data nasabah | W15: (1) Identifikasi dan blokir segera IP address atau token yang terdeteksi melakukan pola request abnormal melalui rule WAF Coraza yang sudah aktif sebagai tindakan pembatasan dampak darurat; (2) lakukan review log API Gateway Kong untuk memetakan scope abuse yang sudah terjadi — identifikasi endpoint yang menjadi target, volume request abnormal, dan data yang berpotensi terekspos atau dienumerasi; (3) perkuat rule WAF Coraza secara ad-hoc untuk memblokir pola serangan spesifik yang teridentifikasi dalam log sebagai mitigasi sementara selama rate limiting belum tersedia; (4) eskalasi insiden kepada manajemen, dokumentasikan scope dampak dan data yang berpotensi terdampak, serta jadwalkan implementasi rate limiting sebagai respons korektif dengan prioritas tertinggi. | X15: Implementasi rate limiting pada API Gateway Kong menggunakan fitur plugin yang tersedia; lakukan validasi dan dokumentasi perlindungan BOLA/IDOR pada seluruh endpoint yang menangani data nasabah; susun kebijakan standar minimum keamanan API yang mewajibkan rate limiting sebagai komponen wajib | Y15: Digital Application Development | AA15: - Implementasi rate limiting pada API Gateway Kong — aktifkan dan konfigurasi plugin rate limiting Kong untuk seluruh endpoint yang menghadap publik; tetapkan threshold yang sesuai per IP, per token, dan per endpoint berdasarkan pola traffic normal; manfaatkan fitur yang sudah tersedia dalam Kong sebelum mempertimbangkan solusi berbayar - Validasi dan dokumentasikan perlindungan BOLA/IDOR — lakukan review menyeluruh terhadap seluruh endpoint yang menangani data spesifik nasabah untuk memastikan validasi otorisasi level resource sudah diimplementasikan; dokumentasikan hasilnya sebagai bukti kepatuhan dan identifikasi endpoint yang masih memerlukan perbaikan - Susun kebijakan standar minimum keamanan API — definisikan standar wajib yang harus dipenuhi setiap endpoint API sebelum dapat di-deploy ke production, mencakup autentikasi, otorisasi, rate limiting, dan logging; jadikan sebagai gate wajib dalam proses deployment pipeline - Lakukan API security assessment menyeluruh — laksanakan pengujian keamanan berbasis OWASP API Security Top 10 terhadap seluruh endpoint aktif untuk mengidentifikasi kerentanan yang belum tertangani; gunakan temuan sebagai dasar prioritas perbaikan dan penguatan konfigurasi WAF Coraza | AB15: - | AC15: 46387 | AD15: 46102 | AE15: JWT, WAF Coraza, dan API Gateway Kong sudah berjalan sebagai lapisan perlindungan autentikasi yang memadai, namun rate limiting belum diimplementasikan sehingga celah penyalahgunaan berbasis volume masih terbuka, risiko mengalami penurunan parsial, status In Progress dan menjadi prioritas untuk segera diaktifkan rate limiting pada API Gateway | AL15: =Q15 -> 4 | AM15: =R15 -> 3 | AN15: =AL15*AM15 -> 12 | AO15: =_xlfn.IFNA(VLOOKUP(AN15,Parameter!$D$53:$E$77,2),"") -> SEDANG | AP15: New - Open
A16: IT | B16: =ROW()-ROW($B$14) -> 2 | C16: Eksposur detail arsitektur sistem dan pemetaan endpoint kepada pihak tidak berwenang yang dapat memfasilitasi threat modeling dan pengembangan eksploitasi berpotensi terjadi — akibat dokumentasi teknis API yang dapat diakses tanpa autentikasi dari seluruh jaringan internal dan tidak adanya requirement keamanan yang mengatur proteksi dokumentasi | D16: API Endpoint | E16: Information | F16: Operasional | G16: External | H16: Risiko | I16: Tidak adanya mekanisme autentikasi dan otorisasi yang diterapkan langsung pada dokumentasi API; tidak ada requirement yang mendefinisikan standar keamanan akses dokumentasi teknis; keterbatasan waktu yang menghambat implementasi kontrol akses pada dokumentasi; tidak ada awareness terhadap risiko eksposur dokumentasi API di jaringan internal | J16: Threat actor yang berhasil masuk ke jaringan internal melalui lateral movement atau insider threat dapat mengakses seluruh detail arsitektur API; informasi yang diperoleh memfasilitasi threat modeling yang lebih akurat dan pengembangan eksploitasi yang lebih terarah; peningkatan efektivitas serangan berbasis pengetahuan arsitektur yang menurunkan waktu dan effort yang dibutuhkan attacker; eksposur struktur data internal yang dapat mengungkap cara pengelolaan data nasabah | K16: Insider threat yang memanfaatkan akses dokumentasi API untuk memetakan celah eksploitasi; attacker yang sudah berada di jaringan internal melalui lateral movement menggunakan dokumentasi untuk merancang serangan lanjutan; eksposur endpoint dan parameter schema yang memfasilitasi serangan BOLA/IDOR yang lebih terarah | L16: Dokumentasi API tidak memiliki mekanisme autentikasi dan otorisasi tersendiri; akses hanya dikontrol di level perimeter firewall tanpa granularitas per pengguna; tidak ada requirement yang mewajibkan proteksi dokumentasi teknis sebagai aset sensitif; tidak ada klasifikasi dokumen yang menandai API specification sebagai informasi yang memerlukan perlindungan akses | M16: Akses terhadap dokumentasi teknis API telah dibatasi pada jaringan internal melalui konfigurasi firewall sebagai kontrol perimeter; namun belum terdapat mekanisme autentikasi dan otorisasi yang diterapkan langsung pada dokumentasi API, sehingga seluruh personil di jaringan internal dapat mengakses detail arsitektur tanpa verifikasi identitas dan kewenangan | N16: Kerahasiaan [C] | O16: 8.1 – Perencanaan dan pengendalian operasional; 5.15 – Manajemen akses | P16: A.5.15 – Manajemen akses; A.8.3 – Pembatasan akses informasi; A.8.26 – Persyaratan keamanan aplikasi; A.5.12 – Klasifikasi informasi | Q16: 3 | R16: 3 | S16: =Q16*R16 -> 9 | T16: =_xlfn.IFNA(VLOOKUP(S16,Parameter!$D$53:$E$77,2),"") -> SEDANG-RENDAH | U16: Rendah — perusahaan tidak bersedia membiarkan dokumentasi teknis API yang mengandung detail arsitektur sistem dapat diakses tanpa verifikasi identitas dan kewenangan, mengingat informasi tersebut secara langsung memfasilitasi pengembangan eksploitasi yang lebih terarah terhadap sistem | V16: Sedang — perusahaan masih dapat beroperasi selama nilai risiko residual ≤ 6; jika residual masih >6, wajib eskalasi ke manajemen. Sebagai syarat minimum toleransi, organisasi wajib memastikan telah tersedia: (1) mekanisme autentikasi yang membatasi akses dokumentasi API hanya kepada personil yang memiliki kebutuhan bisnis yang terdefinisi, dan (2) klasifikasi dokumentasi API sebagai aset informasi sensitif yang memerlukan kontrol akses berbasis identitas | W16: (1) Nonaktifkan sementara akses publik dokumentasi API pada jaringan internal hingga mekanisme autentikasi dapat diimplementasikan; distribusikan dokumentasi hanya melalui channel yang terproteksi kepada personil yang membutuhkan; (2) audit log akses untuk mengidentifikasi siapa saja yang sudah mengakses dokumentasi API dalam periode tertentu dan apakah ada pola akses yang tidak wajar; (3) lakukan review terhadap seluruh endpoint yang terdokumentasi untuk mengidentifikasi apakah ada yang sudah dieksploitasi berdasarkan pola akses pada log API Gateway; (4) eskalasi temuan kepada manajemen dan dokumentasikan scope eksposur sebagai dasar prioritas implementasi kontrol akses | X16: Implementasi mekanisme autentikasi pada akses dokumentasi API; klasifikasikan API specification sebagai aset informasi sensitif; tetapkan requirement keamanan akses dokumentasi teknis sebagai standar wajib; batasi akses hanya kepada personil dengan kebutuhan bisnis yang terdefinisi | Y16: Digital Application Development | AA16: - Implementasi mekanisme autentikasi pada akses dokumentasi API — terapkan kontrol akses berbasis identitas pada seluruh dokumentasi teknis API (Swagger UI, Postman collections, OpenAPI spec) sehingga hanya personil dengan identitas terverifikasi dan kewenangan terdefinisi yang dapat mengaksesnya; manfaatkan IAM yang sudah tersedia sebagai mekanisme autentikasi - Klasifikasikan API documentation sebagai aset informasi sensitif — tandai seluruh dokumentasi teknis API sebagai aset dengan klasifikasi confidential yang memerlukan kontrol akses berbasis identitas; integrasikan ke dalam kebijakan klasifikasi informasi yang berlaku dan pastikan penanganannya mengikuti standar perlindungan yang sesuai - Tetapkan requirement keamanan akses dokumentasi teknis sebagai standar wajib — definisikan secara formal bahwa seluruh dokumentasi teknis yang mengandung detail arsitektur sistem wajib dilindungi dengan autentikasi; integrasikan sebagai requirement wajib dalam proses pengembangan dan deployment dokumentasi API ke depannya - Evaluasi penerapan API documentation portal dengan kontrol akses granular — kaji solusi portal dokumentasi API yang mendukung autentikasi terpusat, kontrol akses berbasis role, dan audit trail akses; pertimbangkan sebagai investasi jangka menengah untuk mengelola akses dokumentasi secara lebih terstruktur dan teraudit | AB16: Personel Digital Application Development berkoordinasi dengan Personel Security Analyst dan Personel IT Governance | AC16: 46387 | AD16: 46102 | AE16: Pembatasan firewall internal sudah berjalan sebagai kontrol perimeter yang memberikan perlindungan dasar, namun tidak adanya autentikasi pada dokumentasi API membuat insider threat dan attacker yang sudah berada di jaringan internal dapat mengakses seluruh detail arsitektur tanpa hambatan, risiko belum mengalami penurunan signifikan, status In Progress dan menjadi prioritas untuk segera diimplementasikan autentikasi pada akses dokumentasi API | AL16: =Q16 -> 3 | AM16: =R16 -> 3 | AN16: =AL16*AM16 -> 9 | AO16: =_xlfn.IFNA(VLOOKUP(AN16,Parameter!$D$53:$E$77,2),"") -> SEDANG-RENDAH | AP16: New - Open
A17: IT | B17: =ROW()-ROW($B$14) -> 3 | C17: Gangguan layanan pada sistem dependen dan inkonsistensi data akibat perubahan API contract yang tidak terkomunikasi berpotensi terjadi — akibat tidak tersedianya dokumentasi API specification sebagai referensi formal contract bagi consumer internal maupun eksternal meskipun versioning sudah berjalan | D17: API Endpoint | E17: Information | F17: Strategis | G17: External | H17: Risiko | I17: Dokumentasi API specification belum tersedia akibat keterbatasan waktu dan resources untuk penyusunannya; tidak adanya prosedur formal notifikasi perubahan API contract kepada consumer; consumer tidak memiliki referensi formal untuk memvalidasi dan mengantisipasi perubahan yang terjadi pada API yang mereka konsumsi | J17: Gangguan layanan pada sistem dependen akibat perubahan field, tipe data, atau validation rule yang tidak diantisipasi; inkonsistensi data pada consumer yang belum melakukan adaptasi terhadap perubahan contract; peningkatan effort debugging dan troubleshooting akibat tidak adanya referensi API spec yang dapat digunakan untuk mengidentifikasi akar masalah; potensi data corruption pada sistem yang memproses response dengan format yang sudah berubah | K17: Breaking change yang tidak terdeteksi consumer akibat tidak adanya dokumentasi contract formal; inkonsistensi data yang terakumulasi pada sistem downstream; gangguan layanan yang berdampak pada operasional bisnis akibat integrasi yang gagal setelah perubahan API | L17: API specification belum terdokumentasi dan tidak dapat dibagikan kepada consumer; tidak ada prosedur notifikasi perubahan API yang formal; consumer tidak memiliki referensi untuk melakukan contract testing secara mandiri; keterbatasan waktu dan resources yang menghalangi penyusunan dokumentasi API | M17: Semantic versioning telah diimplementasikan pada API sebagai mekanisme dasar pengelolaan perubahan; namun dokumentasi API specification yang dapat dibagikan kepada pengguna internal maupun eksternal belum tersedia, sehingga consumer tidak memiliki referensi formal terhadap contract yang berlaku dan tidak dapat menerima notifikasi perubahan secara terstruktur | N17: Keutuhan [I] + Ketersediaan [A] | O17: 8.1 – Perencanaan dan pengendalian operasional; 7.5 – Informasi terdokumentasi | P17: A.5.37 – Prosedur operasi yang terdokumentasi; A.8.25 – Siklus hidup pengembangan yang aman; A.5.19 – Keamanan informasi dalam hubungan pemasok | Q17: 3 | R17: 3 | S17: =Q17*R17 -> 9 | T17: =_xlfn.IFNA(VLOOKUP(S17,Parameter!$D$53:$E$77,2),"") -> SEDANG-RENDAH | U17: Sedang — perusahaan dapat mentolerir ketiadaan API spec dalam jangka pendek selama versioning masih berjalan sebagai kontrol dasar, namun tidak bersedia membiarkan consumer internal maupun eksternal beroperasi tanpa referensi formal contract API mengingat dampaknya pada keandalan integrasi dan konsistensi data | V17: Sedang — perusahaan masih dapat beroperasi selama nilai risiko residual ≤ 6; jika residual masih >6, wajib eskalasi ke manajemen. Sebagai syarat minimum toleransi, organisasi wajib memastikan telah tersedia: (1) dokumentasi API specification minimal untuk endpoint kritis yang dikonsumsi oleh sistem dependen yang paling berdampak pada operasional bisnis, dan (2) prosedur notifikasi perubahan API yang formal kepada seluruh consumer yang teridentifikasi sebelum perubahan diimplementasikan | W17: (1) Identifikasi segera sistem dependen yang mengalami gangguan dan koordinasikan dengan tim developer untuk melakukan rollback atau hotfix pada perubahan API yang menyebabkan disruption; (2) komunikasikan perubahan API yang telah terjadi kepada seluruh consumer yang teridentifikasi melalui channel komunikasi yang tersedia sebagai notifikasi darurat; (3) lakukan audit terhadap seluruh sistem dependen untuk mengidentifikasi scope dampak inkonsistensi data yang mungkin sudah terjadi; (4) eskalasi insiden kepada manajemen, dokumentasikan akar masalah, dan jadikan sebagai justifikasi urgensi penyusunan API specification formal | X17: Susun dokumentasi API specification minimal untuk endpoint kritis; implementasi prosedur notifikasi perubahan API formal kepada consumer; integrasikan penyusunan API spec sebagai komponen wajib dalam proses pengembangan API baru | Y17: Digital Application Development | AA17: - Susun dokumentasi API specification untuk endpoint kritis — prioritaskan dokumentasi OpenAPI/Swagger untuk endpoint yang dikonsumsi oleh sistem dependen paling kritis; manfaatkan tools auto-generation dari kode yang sudah ada untuk mempercepat proses tanpa memerlukan effort manual penuh dalam keterbatasan waktu dan resources - Tetapkan prosedur notifikasi perubahan API formal kepada consumer — definisikan mekanisme dan channel notifikasi wajib yang harus dijalankan sebelum setiap perubahan API diimplementasikan; sertakan changelog yang menjelaskan perubahan field, tipe data, dan validation rule beserta timeline adaptasi yang diberikan kepada consumer - Integrasikan penyusunan API spec sebagai komponen wajib dalam pengembangan API baru — tetapkan bahwa setiap API baru yang dikembangkan wajib disertai dokumentasi OpenAPI specification sebelum dapat di-deploy ke production; jadikan sebagai gate wajib dalam pipeline CI/CD untuk API endpoint baru - Implementasi consumer contract testing — eksplorasi tools contract testing seperti Pact atau Spring Cloud Contract yang memungkinkan consumer memvalidasi secara otomatis bahwa perubahan API tidak melanggar contract yang disepakati; jadikan sebagai investasi jangka menengah setelah dokumentasi API spec tersedia | AB17: Personel App Development berkoordinasi dengan Personel IT Core Development dan Personel IT Governance dan IT DevSecOps serta QA | AC17: 46387 | AD17: 46102 | AE17: Versioning sudah berjalan sebagai kontrol dasar yang memadai untuk mencegah breaking change langsung, namun ketiadaan API specification membuat consumer tidak memiliki referensi formal contract dan perubahan tidak dapat dikomunikasikan secara terstruktur, risiko belum mengalami penurunan signifikan, status In Progress dan menjadi prioritas untuk segera disusun API spec endpoint kritis dan ditetapkan prosedur notifikasi perubahan | AL17: =Q17 -> 3 | AM17: =R17 -> 3 | AN17: =AL17*AM17 -> 9 | AO17: =_xlfn.IFNA(VLOOKUP(AN17,Parameter!$D$53:$E$77,2),"") -> SEDANG-RENDAH | AP17: New - Open
A18: IT | B18: =ROW()-ROW($B$14) -> 4 | C18: Lateral movement dari kompromi integrasi pihak ketiga ke production environment dan akses tidak terotorisasi terhadap data nasabah berpotensi terjadi — akibat container Docker API yang berjalan dengan privilege root dan belum pernah dilaksanakannya penetration testing untuk memvalidasi efektivitas kontrol segmentasi jaringan yang ada | D18: API Endpoint | E18: Information | F18: Operasional | G18: External | H18: Risiko | I18: Container Docker API yang berpotensi berjalan dengan privilege root sehingga kompromi container dapat memberikan akses penuh ke host; penetration testing belum pernah dilaksanakan sehingga efektivitas kontrol segmentasi tidak tervalidasi; keterbatasan knowledge dan man power yang menghambat pelaksanaan uji keamanan internal secara mandiri | J18: Lateral movement dari environment integrasi pihak ketiga yang terkompromi ke production environment yang mengandung data nasabah dan transaction ledger; akses tidak terotorisasi terhadap data klaim, data medis, dan data transaksi nasabah; potensi manipulasi transaction ledger yang mengakibatkan kerugian finansial; pelanggaran kepatuhan regulasi akibat eksposur data nasabah melalui jalur integrasi pihak ketiga yang tidak tervalidasi keamanannya | K18: Lateral movement melalui kompromi TPA, healthcare provider portal, atau broker integration platform yang memiliki koneksi langsung ke core system; container escape dari Docker container yang berjalan sebagai root untuk mendapatkan akses ke host dan jaringan internal; eksploitasi celah segmentasi yang belum teridentifikasi akibat tidak adanya pentest | L18: Container Docker API berpotensi berjalan dengan privilege root yang memperbesar dampak kompromi; tidak ada penetration testing yang memvalidasi efektivitas kontrol segmentasi dan kemampuan mencegah lateral movement; keterbatasan knowledge internal untuk melakukan uji keamanan mandiri; efektivitas kontrol DMZ dan geolocation belum tervalidasi terhadap skenario serangan nyata | M18: Pembatasan akses berbasis kebijakan telah diterapkan pada titik integrasi pihak ketiga; segmentasi jaringan melalui DMZ telah diimplementasikan; pembatasan geolokasi aktif sebagai kontrol tambahan; namun container Docker API berpotensi berjalan sebagai root dan penetration testing belum pernah dilaksanakan untuk memvalidasi efektivitas kontrol yang ada | N18: Kerahasiaan [C] + Keutuhan [I] | O18: 8.1 – Perencanaan dan pengendalian operasional; 5.19 – Keamanan informasi dalam hubungan pemasok | P18: A.8.20 – Keamanan jaringan; A.8.22 – Segregasi jaringan; A.8.25 – Siklus hidup pengembangan yang aman; A.5.19 – Keamanan informasi dalam hubungan pemasok | Q18: 4 | R18: 3 | S18: =Q18*R18 -> 12 | T18: =_xlfn.IFNA(VLOOKUP(S18,Parameter!$D$53:$E$77,2),"") -> SEDANG | U18: Rendah — perusahaan tidak bersedia membiarkan jalur integrasi pihak ketiga yang memiliki koneksi langsung ke core system beroperasi tanpa validasi keamanan melalui penetration testing mengingat potensi lateral movement yang dapat mengekspos seluruh data nasabah dan transaction ledger | V18: Sedang — perusahaan masih dapat beroperasi selama nilai risiko residual ≤ 9; jika residual masih >9, wajib eskalasi ke manajemen. Sebagai syarat minimum toleransi, organisasi wajib memastikan telah tersedia: (1) seluruh container Docker API yang digunakan untuk integrasi pihak ketiga sudah dijalankan dengan non-root user sebagai hardening dasar, dan (2) penetration testing telah dilaksanakan minimal terhadap jalur integrasi pihak ketiga yang memiliki koneksi langsung ke core system untuk memvalidasi efektivitas kontrol segmentasi | W18: (1) Isolasi segera seluruh jalur integrasi pihak ketiga yang terindikasi terkompromi melalui pemutusan koneksi network pada firewall untuk mencegah lateral movement lebih lanjut ke core system; (2) lakukan audit log akses terhadap seluruh API endpoint yang terekspos ke pihak ketiga untuk mengidentifikasi scope data yang berpotensi terekspos dan timeline akses tidak terotorisasi; (3) koordinasikan dengan pihak ketiga yang terkompromi untuk asesmen scope kompromi dan langkah pemulihan di sisi mereka; (4) eskalasi insiden kepada manajemen dan Legal Counsel untuk asesmen kewajiban notifikasi regulasi jika data nasabah terdampak | X18: Hardening container Docker dengan menjalankan seluruh API sebagai non-root user; laksanakan penetration testing terhadap environment jaringan dan jalur integrasi pihak ketiga; validasi efektivitas kontrol DMZ terhadap skenario lateral movement | Y18: Digital Application Development | Z18: DevSecOps | AA18: - Hardening seluruh container Docker API ke non-root user — audit seluruh container yang digunakan untuk integrasi pihak ketiga; implementasikan non-root user pada seluruh Dockerfile dan docker-compose yang masih menggunakan root; terapkan prinsip least privilege pada level container untuk memastikan kompromi container tidak memberikan akses ke host - Jadwalkan dan laksanakan penetration testing terhadap jalur integrasi pihak ketiga — definisikan scope pentest yang mencakup seluruh titik integrasi TPA, healthcare provider portal, dan broker platform; gunakan vendor pentest eksternal mengingat keterbatasan kapabilitas internal; fokuskan pada skenario lateral movement dari environment pihak ketiga ke core system - Validasi dan perkuat efektivitas kontrol segmentasi DMZ — review konfigurasi DMZ dan firewall rules yang mengatur traffic antara environment integrasi pihak ketiga dengan core system; pastikan tidak ada jalur komunikasi yang tidak terotorisasi; terapkan whitelist komunikasi yang hanya mengizinkan traffic yang benar-benar diperlukan - Implementasi monitoring anomali pada jalur integrasi pihak ketiga — aktifkan logging dan monitoring terhadap seluruh traffic API dari integrasi pihak ketiga; konfigurasi alert untuk pola akses yang tidak wajar seperti volume request abnormal, akses di luar jam operasional, atau enumerasi endpoint; integrasikan ke Wazuh sebagai bagian dari monitoring terpusat | AB18: Personel App Dev berkoordinasi dengan Personel Security Analyst dan Personel IT Infra - Network, Personel IT Infra Sysadmin dan DevSecOps | AC18: 46387 | AD18: 46102 | AE18: Pembatasan akses, DMZ, dan geolocation sudah berjalan sebagai kontrol dasar yang memadai, namun container Docker berpotensi berjalan sebagai root dan penetration testing belum pernah dilaksanakan sehingga efektivitas kontrol tidak tervalidasi, risiko masih berada pada level Sedang, status In Progress dan menjadi prioritas untuk segera dilakukan hardening container dan dijadwalkan penetration testing | AL18: =Q18 -> 4 | AM18: =R18 -> 3 | AN18: =AL18*AM18 -> 12 | AO18: =_xlfn.IFNA(VLOOKUP(AN18,Parameter!$D$53:$E$77,2),"") -> SEDANG | AP18: New - Open
A19: IT | B19: =ROW()-ROW($B$14) -> 5 | C19: Pelanggaran prinsip pembatasan penyimpanan UU PDP dan perluasan permukaan risiko pelanggaran data berpotensi terjadi — akibat tidak terdefinisinya kebijakan retensi data digital yang dapat ditegakkan secara teknis sehingga data pribadi nasabah dari polis berakhir disimpan indefinitely tanpa batas waktu yang sesuai ketentuan regulasi | D19: Aplikasi Core System | E19: Information | F19: Operasional | G19: External | H19: Risiko | I19: Kebijakan retensi data digital belum terdefinisi dan hanya tersedia untuk arsip fisik; data owner belum ditetapkan sehingga tidak ada yang bertanggung jawab atas pengelolaan siklus hidup data digital; klasifikasi data belum tersedia sehingga tingkat sensitivitas dan ketentuan retensi per kategori data tidak dapat ditetapkan; tidak ada mekanisme teknis yang menegakkan batas waktu penyimpanan dan prosedur penghapusan data secara otomatis | J19: Data pribadi nasabah dari polis yang sudah berakhir disimpan indefinitely melampaui persyaratan retensi regulasi; pelanggaran prinsip storage limitation UU PDP yang mengakibatkan eksposur terhadap sanksi administratif; perluasan permukaan risiko pelanggaran data akibat volume data yang terus bertambah tanpa penghapusan; potensi tuntutan hukum dari nasabah atas penyimpanan data yang melampaui tujuan dan batas waktu yang diizinkan | K19: Sanksi administratif dari regulator atas pelanggaran prinsip storage limitation UU PDP; tuntutan hukum dari nasabah atas penyimpanan data pribadi yang melampaui batas waktu yang diizinkan; peningkatan dampak pelanggaran data akibat volume data yang tidak perlu tersimpan dalam sistem; audit regulasi yang mengungkap ketiadaan data retention policy digital sebagai temuan major non-conformity | L19: Tidak ada kebijakan retensi data digital yang terdefinisi dan dapat ditegakkan secara teknis; tidak ada data owner yang bertanggung jawab atas siklus hidup data; tidak ada klasifikasi data yang menjadi dasar penetapan ketentuan retensi per kategori; tidak ada mekanisme otomatis untuk penghapusan data yang melampaui batas waktu retensi | M19: Kebijakan retensi data telah tersedia untuk pengelolaan arsip fisik; namun kebijakan retensi data digital belum terdefinisi, data owner belum ditetapkan, dan klasifikasi data belum tersedia, sehingga tidak ada mekanisme yang mengatur batas waktu penyimpanan dan prosedur penghapusan data pribadi digital sesuai ketentuan UU PDP | N19: Kerahasiaan [C] + Keutuhan [I] | O19: 8.1 – Perencanaan dan pengendalian operasional; 5.1 – Kepemimpinan dan komitmen | P19: A.5.34 – Privasi dan perlindungan informasi pribadi; A.8.10 – Penghapusan informasi; A.5.12 – Klasifikasi informasi; A.5.31 – Persyaratan hukum, undang-undang, peraturan dan kontrak | Q19: 4 | R19: 5 | S19: =Q19*R19 -> 20 | T19: =_xlfn.IFNA(VLOOKUP(S19,Parameter!$D$53:$E$77,2),"") -> TINGGI | U19: Rendah — perusahaan tidak bersedia membiarkan data pribadi nasabah disimpan tanpa batas waktu yang jelas mengingat pelanggaran prinsip storage limitation UU PDP bersifat mandatory dan membawa konsekuensi sanksi administratif serta tuntutan hukum yang tidak dapat dihindari | V19: Sedang — perusahaan masih dapat beroperasi selama nilai risiko residual ≤ 9; jika residual masih >9, wajib eskalasi ke manajemen senior dan Legal Counsel. Sebagai syarat minimum toleransi, organisasi wajib memastikan telah tersedia: (1) kebijakan retensi data digital yang mendefinisikan batas waktu penyimpanan per kategori data sesuai ketentuan regulasi yang berlaku, dan (2) data owner yang ditetapkan secara formal dan bertanggung jawab atas kepatuhan siklus hidup data pada domain masing-masing | W19: (1) Lakukan inventarisasi segera terhadap kategori data digital yang paling berisiko — prioritaskan data nasabah dari polis berakhir yang sudah tersimpan melampaui perkiraan batas waktu yang seharusnya berlaku; (2) engajemen Legal Counsel untuk asesmen eksposur regulasi akibat penyimpanan data yang sudah terjadi dan opsi remediasi yang tersedia; (3) susun kebijakan retensi data digital darurat sebagai dokumen interim yang dapat segera diterapkan sambil proses formal penyusunan berlangsung; (4) eskalasi kepada manajemen senior dengan laporan scope data yang berpotensi melanggar prinsip storage limitation sebagai justifikasi urgensi implementasi | X19: Susun kebijakan retensi data digital yang mendefinisikan batas waktu penyimpanan per kategori data; tetapkan data owner per domain data; implementasi klasifikasi data sebagai fondasi penetapan ketentuan retensi; kembangkan mekanisme teknis penghapusan data otomatis pada core system | Y19: IT Core Development | AA19: - Tetapkan data owner secara formal per domain data — identifikasi dan tunjuk personil yang bertanggung jawab atas kepatuhan siklus hidup data untuk setiap domain data kritis; definisikan scope tanggung jawab, kewenangan, dan akuntabilitas data owner terhadap pemenuhan ketentuan retensi dan penghapusan data sesuai UU PDP - Susun kebijakan retensi data digital per kategori data — definisikan batas waktu penyimpanan untuk setiap kategori data digital berdasarkan persyaratan regulasi yang berlaku, termasuk data nasabah aktif, data polis berakhir, data klaim, dan data medis; koordinasikan dengan Legal Counsel untuk memastikan ketentuan retensi selaras dengan seluruh regulasi yang berlaku - Implementasi klasifikasi data sebagai fondasi penetapan retensi — kategorikan seluruh data digital berdasarkan tingkat sensitivitas dan ketentuan regulasi yang mengatur penyimpanannya; jadikan klasifikasi sebagai dasar penetapan kebijakan retensi dan prosedur penghapusan yang berbeda per kategori - Kembangkan mekanisme teknis penghapusan data otomatis pada core system — koordinasikan dengan tim DBA dan pengembangan untuk mengimplementasikan mekanisme yang secara otomatis mengidentifikasi dan menghapus atau mengarsip data yang telah melampaui batas waktu retensi; pastikan proses penghapusan terdokumentasi sebagai audit trail kepatuhan | AB19: Personel Pengembang Aplikasi Core berkoordinasi dengan Legal Counsel, Personel IT Governance, dan Personel DBA | AC19: 46387 | AD19: 46102 | AE19: Retensi data fisik sudah ada namun kebijakan retensi data digital, data owner, dan klasifikasi data belum ada sama sekali sehingga data pribadi nasabah disimpan indefinitely tanpa batas waktu yang sesuai regulasi, risiko masih terbuka penuh pada level Tinggi dengan probabilitas sangat tinggi, status New - Open dan menjadi prioritas utama untuk segera ditetapkan data owner dan disusun kebijakan retensi data digital | AL19: =Q19 -> 4 | AM19: =R19 -> 5 | AN19: =AL19*AM19 -> 20 | AO19: =_xlfn.IFNA(VLOOKUP(AN19,Parameter!$D$53:$E$77,2),"") -> TINGGI | AP19: New - Open
A20: IT | B20: =ROW()-ROW($B$14) -> 6 | C20: Eksposur kerentanan yang tidak dapat dimitigasi secara teknis pada sistem inti bisnis berpotensi berlangsung dalam jangka panjang — akibat seluruh core system yang sudah end-of-life tidak mendapat vendor security update dan tidak kompatibel dengan MFA, TLS terkini, dan enkripsi modern, sementara personil yang memahami sistem semakin berkurang | D20: Aplikasi Core System | E20: Software | F20: Strategis | G20: Internal | H20: Risiko | I20: Seluruh core system menggunakan teknologi yang sudah melampaui batas dukungan vendor sehingga tidak ada security update yang tersedia; arsitektur teknologi lama tidak kompatibel dengan implementasi modern security controls seperti MFA, TLS versi terkini, dan algoritma enkripsi modern; developer yang memahami sistem sudah pensiun atau resign sementara rekrutmen developer baru yang memahami teknologi legacy sangat sulit; revamp sistem membutuhkan waktu dan investasi yang signifikan sementara kebutuhan bisnis terus berlanjut | J20: Kerentanan keamanan pada core system tidak dapat diperbaiki melalui patch karena vendor sudah tidak memberikan dukungan; modern security controls tidak dapat diimplementasikan sehingga sistem tidak dapat memenuhi standar keamanan minimum yang ditetapkan regulasi; risiko eksploitasi kerentanan yang diketahui publik pada teknologi lama terus meningkat seiring waktu; ketergantungan pada personil yang semakin berkurang menciptakan risiko knowledge loss yang dapat menghentikan operasional sistem | K20: Eksploitasi kerentanan CVE publik pada teknologi legacy yang tidak dapat di-patch; serangan yang memanfaatkan ketidakmampuan sistem menerapkan MFA sehingga credential compromise lebih mudah terjadi; intersepsi komunikasi akibat TLS versi lama yang rentan terhadap known attack; knowledge loss permanen jika personil yang tersisa tidak lagi tersedia | L20: Tidak ada vendor security update untuk sistem EOL; arsitektur tidak kompatibel dengan modern security controls; personil yang memahami sistem semakin terbatas dan tidak ada backup yang memadai; tidak ada roadmap modernisasi yang terdefinisi dan disetujui sebagai solusi jangka panjang | M20: Core system vendor dikelola melalui keterlibatan vendor sebagai dukungan pemeliharaan; core system internal menjalankan program sharing knowledge yang terbatas cakupannya; namun tidak ada vendor security update dan modern security controls tidak dapat diimplementasikan akibat ketidakkompatibilan teknologi | N20: Semua (C - I - A) | O20: 8.1 – Perencanaan dan pengendalian operasional; 5.1 – Kepemimpinan dan komitmen; 6.1 – Tindakan untuk menangani risiko dan peluang | P20: A.8.8 – Manajemen kerentanan teknis; A.8.25 – Siklus hidup pengembangan yang aman; A.5.30 – Kesiapan ICT untuk keberlangsungan bisnis; A.6.3 – Kesadaran, pendidikan dan pelatihan keamanan informasi | Q20: 4 | R20: 4 | S20: =Q20*R20 -> 16 | T20: =_xlfn.IFNA(VLOOKUP(S20,Parameter!$D$53:$E$77,2),"") -> SEDANG-TINGGI | U20: Rendah — perusahaan tidak bersedia membiarkan sistem inti bisnis beroperasi dalam kondisi EOL tanpa security update dan tanpa kemampuan menerapkan modern security controls dalam jangka panjang mengingat eksposur kerentanan yang tidak dapat dimitigasi terus meningkat seiring waktu | V20: Sedang — perusahaan masih dapat beroperasi dengan core system legacy selama kompensasi kontrol pada lapisan perimeter masih efektif; jika eksploitasi aktif teridentifikasi atau kompensasi kontrol tidak lagi memadai, realisasi modernisasi wajib dieskalasi sebagai prioritas investasi segera. Sebagai syarat minimum toleransi, organisasi wajib memastikan telah tersedia: (1) kompensasi kontrol keamanan pada lapisan perimeter dan akses yang mengkompensasi ketidakmampuan sistem menerapkan modern security controls secara langsung, dan (2) roadmap modernisasi core system yang terdokumentasi dan mendapat persetujuan manajemen sebagai komitmen strategis jangka panjang | W20: (1) Isolasi segera modul atau komponen core system yang teridentifikasi tereksploitasi untuk membatasi dampak lateral movement ke komponen lain; (2) aktifkan kompensasi kontrol darurat pada lapisan perimeter seperti pengetatan firewall rules dan pembatasan akses untuk meminimalkan attack surface sementara perbaikan teknis diupayakan; (3) koordinasikan dengan vendor core system untuk asesmen opsi darurat yang tersedia termasuk hotfix atau workaround yang dapat diterapkan tanpa upgrade penuh; (4) eskalasi kepada manajemen senior dengan laporan bahwa insiden terjadi pada sistem EOL yang tidak dapat di-patch sebagai justifikasi urgensi percepatan roadmap modernisasi | X20: Implementasi kompensasi kontrol keamanan pada lapisan perimeter untuk mengkompensasi ketidakmampuan sistem menerapkan modern security controls; susun roadmap modernisasi core system bertahap; akselerasi program sharing knowledge untuk mencegah knowledge loss | Y20: Chief Technology & Information Officer | Z20: IT Core Development | AA20: - Implementasi kompensasi kontrol keamanan pada lapisan perimeter dan akses — terapkan kontrol yang mengkompensasi ketidakmampuan sistem menerapkan MFA, TLS terkini, dan enkripsi modern secara langsung; contoh: implementasi MFA pada lapisan VPN/gateway sebelum akses ke core system, enkripsi komunikasi pada level network melalui TLS termination di load balancer, dan pembatasan akses berbasis IP dan role yang ketat - Susun dan presentasikan roadmap modernisasi core system bertahap — dokumentasikan jalur modernisasi yang realistis dengan mempertimbangkan ketergantungan bisnis, ketersediaan developer, dan keterbatasan anggaran; pecah menjadi fase yang dapat dieksekusi secara inkremental tanpa menghentikan operasional; presentasikan kepada manajemen untuk mendapatkan komitmen strategis dan alokasi anggaran - Akselerasi program sharing knowledge untuk mencegah knowledge loss — tingkatkan intensitas dan cakupan sharing knowledge dengan target minimal 2 personil memahami setiap modul kritis; dokumentasikan seluruh pengetahuan teknis yang diekstrak dalam knowledge base yang dapat diakses; pertimbangkan keterlibatan konsultan eksternal yang memahami teknologi legacy sebagai bridging resource - Evaluasi opsi modernisasi bertahap berbasis strangler fig pattern — kaji pendekatan modernisasi inkremental yang mengganti komponen sistem legacy satu per satu tanpa menghentikan operasional; mulai dengan modul yang paling kritikal dari perspektif keamanan dan paling feasible untuk dimodernisasi; jadikan sebagai strategi jangka menengah yang dapat dimulai sambil roadmap penuh dipersiapkan | AB20: Personel CTIO berkoordinasi dengan Personel IT Core Development, Personel IT Governance, dan vendor core system | AC20: 46387 | AD20: 46102 | AE20: Dukungan vendor dan sharing knowledge sudah berjalan sebagai kontrol parsial yang terbatas, namun seluruh core system sudah EOL tanpa security update dan tidak kompatibel dengan modern security controls, risiko eksposur kerentanan tidak dapat dimitigasi secara teknis langsung, status In Progress dan menjadi prioritas strategis untuk segera disusun roadmap modernisasi dan diimplementasikan kompensasi kontrol pada lapisan perimeter | AL20: =Q20 -> 4 | AM20: =R20 -> 4 | AN20: =AL20*AM20 -> 16 | AO20: =_xlfn.IFNA(VLOOKUP(AN20,Parameter!$D$53:$E$77,2),"") -> SEDANG-TINGGI | AP20: New - Open
A21: IT | B21: =ROW()-ROW($B$14) -> 7 | C21: Meningkatnya serangan siber yang menargetkan identitas dan kredensial pengguna berpotensi mengekspos sistem kritis perusahaan — namun membuka peluang implementasi Zero Trust Architecture yang menggantikan paradigma perimeter security konvensional dengan model verifikasi berkelanjutan, meningkatkan postur keamanan secara menyeluruh sambil memfasilitasi fleksibilitas akses tenaga kerja digital | D21: Aplikasi Identity and Access Management (IAM) & PAM | E21: Information | F21: Strategis | G21: External | H21: Peluang | I21: Meningkatnya intensitas serangan siber berbasis identitas dan kredensial yang menargetkan industri asuransi; tekanan regulasi OJK yang mensyaratkan kontrol akses yang semakin granular; keterbatasan paradigma perimeter security konvensional dalam mengakomodasi model kerja hybrid dan akses multi-cloud | J21: Peningkatan postur keamanan secara menyeluruh melalui model verifikasi berkelanjutan yang tidak bergantung pada perimeter jaringan; pengurangan eksposur akibat serangan berbasis kredensial yang dicuri; fasilitasi fleksibilitas akses tenaga kerja digital yang mendukung produktivitas; potensi diferensiasi kompetitif di segmen nasabah korporat yang mensyaratkan standar keamanan tinggi | K21: Peningkatan serangan identity-based secara global yang memperkuat justifikasi bisnis; regulasi keamanan siber yang semakin ketat mendorong adopsi model zero trust; kompetitor yang mengadopsi ZTA lebih awal berpotensi memenangkan segmen nasabah korporat yang sensitif terhadap keamanan | L21: Keterbatasan anggaran untuk investasi solusi ZTA yang komprehensif; gap knowledge internal terkait arsitektur dan implementasi Zero Trust; infrastruktur existing yang memerlukan adaptasi bertahap untuk mendukung model ZTA; tidak adanya roadmap adopsi ZTA yang terdokumentasi | M21: Pembatasan akses ke server telah diterapkan sebagai kontrol dasar; implementasi DMZ sudah berjalan sebagai segmentasi jaringan awal; namun paradigma yang digunakan masih berbasis perimeter security konvensional yang belum mencerminkan prinsip Zero Trust | N21: Semua (C - I - A) | O21: 5.1 – Kepemimpinan dan komitmen; 6.1 – Tindakan untuk menangani risiko dan peluang; 8.1 – Perencanaan dan pengendalian operasional | P21: A.5.15 – Manajemen akses; A.8.2 – Hak akses istimewa; A.8.5 – Autentikasi aman; A.8.20 – Keamanan jaringan | Q21: 4 | R21: 3 | S21: =Q21*R21 -> 12 | T21: =_xlfn.IFNA(VLOOKUP(S21,Parameter!$D$53:$E$77,2),"") -> SEDANG | U21: Tinggi — perusahaan memiliki ambisi untuk mengkapitalisasi peluang ini secara aktif mengingat dampak strategisnya pada postur keamanan jangka panjang dan potensi diferensiasi kompetitif, meskipun realisasinya perlu dilakukan secara bertahap sesuai kapasitas anggaran dan knowledge yang tersedia | V21: Sedang — perusahaan masih dapat menunda realisasi penuh peluang ini selama nilai manfaat yang belum terealisasi ≤ dampak level Sedang; jika ancaman berbasis identitas sudah berdampak aktif pada sistem perusahaan, realisasi peluang ini wajib dieskalasi sebagai prioritas investasi. Sebagai syarat minimum untuk mulai mengkapitalisasi peluang, organisasi wajib memastikan telah tersedia: (1) roadmap adopsi ZTA bertahap yang terdokumentasi dan telah mendapat persetujuan manajemen sebagai arah strategis, dan (2) alokasi anggaran pilot project ZTA minimal untuk satu domain prioritas tinggi sebagai proof of concept | W21: (1) Manfaatkan setiap insiden keamanan berbasis identitas yang terjadi sebagai momentum untuk mempresentasikan justifikasi bisnis ZTA kepada manajemen senior dengan data dampak yang konkret; (2) segera dokumentasikan quick win yang dapat dicapai dari implementasi parsial ZTA pada domain prioritas sebagai bukti nilai untuk mendukung persetujuan anggaran lebih lanjut; (3) jalin komunikasi dengan vendor ZTA yang menawarkan model adopsi bertahap dan berbiaya rendah di awal untuk mengakomodasi keterbatasan anggaran; (4) eskalasi roadmap ZTA ke manajemen senior dengan framing investasi keamanan sebagai enabler bisnis bukan cost center | X21: (Peluang) Susun roadmap adopsi ZTA bertahap berbasis kapasitas anggaran dan knowledge internal; mulai dengan implementasi komponen ZTA bernilai tinggi seperti MFA universal dan PAM sebagai fondasi awal; bangun business case ZTA yang mengkuantifikasi potensi penghematan biaya insiden versus investasi | Y21: Chief Technology & Information Officer | AA21: - Implementasi kompensasi kontrol keamanan pada lapisan perimeter dan akses — terapkan kontrol yang mengkompensasi ketidakmampuan sistem menerapkan MFA, TLS terkini, dan enkripsi modern secara langsung; contoh: implementasi MFA pada lapisan VPN/gateway sebelum akses ke core system, enkripsi komunikasi pada level network melalui TLS termination di load balancer, dan pembatasan akses berbasis IP dan role yang ketat - Susun dan presentasikan roadmap modernisasi core system bertahap — dokumentasikan jalur modernisasi yang realistis dengan mempertimbangkan ketergantungan bisnis, ketersediaan developer, dan keterbatasan anggaran; pecah menjadi fase yang dapat dieksekusi secara inkremental tanpa menghentikan operasional; presentasikan kepada manajemen untuk mendapatkan komitmen strategis dan alokasi anggaran - Akselerasi program sharing knowledge untuk mencegah knowledge loss — tingkatkan intensitas dan cakupan sharing knowledge dengan target minimal 2 personil memahami setiap modul kritis; dokumentasikan seluruh pengetahuan teknis yang diekstrak dalam knowledge base yang dapat diakses; pertimbangkan keterlibatan konsultan eksternal yang memahami teknologi legacy sebagai bridging resource - Evaluasi opsi modernisasi bertahap berbasis strangler fig pattern — kaji pendekatan modernisasi inkremental yang mengganti komponen sistem legacy satu per satu tanpa menghentikan operasional; mulai dengan modul yang paling kritikal dari perspektif keamanan dan paling feasible untuk dimodernisasi; jadikan sebagai strategi jangka menengah yang dapat dimulai sambil roadmap penuh dipersiapkan | AB21: Personel CTIO berkoordinasi dengan Personel Security Analyst, Personel IT Governance, dan Personel IT Infra - Sysadmin | AC21: 46386 | AD21: 46102 | AE21: Pembatasan akses server dan DMZ sudah berjalan sebagai fondasi awal yang dapat menjadi titik start adopsi ZTA, namun keterbatasan anggaran dan knowledge masih menjadi hambatan utama realisasi, peluang belum dikapitalisasi, status New - Open dan menjadi prioritas strategis untuk segera disusun business case dan roadmap adopsi ZTA sebelum momentum justifikasi dari ancaman yang meningkat terlewatkan | AL21: =Q21 -> 4 | AM21: =R21 -> 3 | AN21: =AL21*AM21 -> 12 | AO21: =_xlfn.IFNA(VLOOKUP(AN21,Parameter!$D$53:$E$77,2),"") -> SEDANG | AP21: New - Open
A22: IT | B22: =ROW()-ROW($B$14) -> 8 | C22: Aktivitas tidak terotorisasi atau berbahaya oleh administrator yang tidak dapat dideteksi dan diinvestigasi berpotensi terjadi — akibat shared administrative credentials yang digunakan bergantian tanpa individual accountability, MFA enforcement, dan PAM system yang menghilangkan seluruh audit trail yang dapat diatribusikan per individu | D22: Aplikasi Identity and Access Management (IAM) & PAM | E22: Information | F22: Operasional | G22: Internal | H22: Risiko | I22: Shared administrative credentials digunakan bergantian oleh multiple personil tanpa individual accountability; PAM system belum diimplementasikan akibat keterbatasan investasi; MFA belum diterapkan pada akun administrator; password administrator yang standar dan hampir sama di seluruh environment meningkatkan risiko kompromi lateral jika satu environment terekspos | J22: Aktivitas administrator tidak dapat diatribusikan kepada individu yang bertanggung jawab akibat penggunaan shared credentials; audit trail yang bermakna tidak tersedia untuk keperluan investigasi forensik; insider threat melalui akses administrator tidak dapat terdeteksi dan dibuktikan; potensi kompromi seluruh environment jika satu set shared credentials terekspos akibat kesamaan password | K22: Insider threat yang memanfaatkan shared credentials untuk aktivitas berbahaya tanpa dapat diidentifikasi; kompromi seluruh environment akibat kesamaan password administrator yang memungkinkan lateral movement; penyalahgunaan akses administrator yang tidak dapat dibuktikan akibat tidak adanya individual audit trail; credential stuffing yang memanfaatkan password standar yang dapat ditebak | L22: Shared administrative credentials tanpa individual accountability; password administrator standar dan hampir sama di seluruh environment; PAM system belum ada; MFA belum diterapkan pada akun administrator; audit trail tidak dapat diatribusikan per individu | M22: Kebijakan pengelolaan akses istimewa telah tersedia; segregasi environment container dan non-container telah diterapkan; review hak akses istimewa dilaksanakan berkala; Guacamole tersedia sebagai platform remote access terpusat; namun PAM belum diimplementasikan, shared credentials masih digunakan, dan MFA belum diterapkan pada akun administrator | N22: Kerahasiaan [C] + Keutuhan [I] | O22: 8.1 – Perencanaan dan pengendalian operasional; 9.1 – Pemantauan, pengukuran, analisis dan evaluasi | P22: A.8.2 – Hak akses istimewa; A.5.17 – Informasi autentikasi; A.5.15 – Manajemen akses; A.8.15 – Logging | Q22: 4 | R22: 4 | S22: =Q22*R22 -> 16 | T22: =_xlfn.IFNA(VLOOKUP(S22,Parameter!$D$53:$E$77,2),"") -> SEDANG-TINGGI | U22: Rendah — perusahaan tidak bersedia membiarkan akses administrator dijalankan tanpa individual accountability dan audit trail mengingat ketiadaan atribusi individual secara langsung memungkinkan insider threat dan aktivitas berbahaya beroperasi tanpa dapat dideteksi maupun diinvestigasi | V22: Sedang — perusahaan masih dapat beroperasi selama nilai risiko residual ≤ 9; jika residual masih >9, wajib eskalasi ke manajemen senior. Sebagai syarat minimum toleransi, organisasi wajib memastikan telah tersedia: (1) akun administrator individual per personil yang menggantikan shared credentials minimal pada environment produksi yang paling kritis, dan (2) session recording melalui Guacamole yang aktif untuk seluruh sesi akses administrator sebagai audit trail sementara PAM belum tersedia | W22: (1) Lakukan rotasi segera seluruh shared administrative credentials di seluruh environment untuk memutus potensi akses tidak terotorisasi yang sedang berlangsung; (2) review manual log Guacamole dan log sistem yang tersedia untuk mengidentifikasi aktivitas administrator yang mencurigakan dalam periode teridentifikasi; (3) batasi akses administrator hanya melalui Guacamole sebagai satu-satunya jalur yang dapat di-log sementara investigasi berlangsung; (4) eskalasi insiden kepada manajemen senior dengan laporan ketidakmampuan mengidentifikasi pelaku akibat shared credentials sebagai justifikasi urgensi implementasi akun individual dan PAM | X22: Buat akun administrator individual per personil sebagai pengganti shared credentials; aktifkan session recording di Guacamole sebagai audit trail sementara; susun roadmap implementasi PAM bertahap; terapkan MFA pada seluruh akses administrator | Y22: IT Infra - Sysadmin | Z22: IT Security Analyst | AA22: - Buat akun administrator individual per personil dan nonaktifkan shared credentials — buat akun administrator terpisah untuk setiap personil yang memerlukan akses istimewa; mulai dari environment produksi kritis; nonaktifkan shared credentials secara bertahap setelah akun individual aktif; pastikan setiap akun individual memiliki level privilege minimum sesuai kebutuhan tugasnya - Aktifkan session recording di Guacamole untuk seluruh sesi administrator — konfigurasi Guacamole untuk merekam seluruh sesi remote access administrator sebagai audit trail yang dapat diatribusikan per individu; manfaatkan kapabilitas ini sebagai kompensasi kontrol sementara PAM belum tersedia; pastikan rekaman tersimpan dengan retensi yang memadai untuk keperluan investigasi - Terapkan MFA pada seluruh akun administrator — implementasikan MFA untuk seluruh akses administrator baik langsung maupun melalui Guacamole; manfaatkan FortiToken yang sudah tersedia sebagai mekanisme MFA; pastikan tidak ada jalur akses administrator yang dapat dilakukan tanpa MFA - Susun roadmap implementasi PAM bertahap berbasis kapasitas investasi — evaluasi solusi PAM open-source seperti Teleport atau solusi komersial yang dapat diadopsi secara bertahap; dokumentasikan roadmap implementasi yang dimulai dari environment paling kritis; jadikan sebagai justifikasi investasi kepada manajemen dengan kuantifikasi risiko shared credentials yang sedang berlangsung | AB22: Personel IT Infra - Sysadmin berkoordinasi dengan Personel Security Analyst dan Personel IT Governance | AC22: 46387 | AD22: 46102 | AE22: Kebijakan, segregasi environment, review hak akses, dan Guacamole sudah berjalan sebagai kontrol dasar yang memadai, namun shared credentials masih digunakan, PAM belum ada, dan MFA belum diterapkan sehingga individual accountability dan audit trail tidak tersedia, risiko masih terbuka pada level Tinggi, status In Progress dan menjadi prioritas utama untuk segera dibuat akun individual dan diaktifkan session recording Guacamole | AL22: =Q22 -> 4 | AM22: =R22 -> 4 | AN22: =AL22*AM22 -> 16 | AO22: =_xlfn.IFNA(VLOOKUP(AN22,Parameter!$D$53:$E$77,2),"") -> SEDANG-TINGGI | AP22: New - Open
A23: IT | B23: =ROW()-ROW($B$14) -> 9 | C23: Credential leakage via non-repository channels (Slack, email, Jira, Trello, Google Drive, public document sharing) beyond scope dari automated secret scanning automation memungkinkan threat actor memperoleh API keys, access tokens, database credentials untuk unauthorized API access dan cloud service abuse. | D23: Aplikasi Identity and Access Management (IAM) & PAM | E23: Information | F23: Operasional | G23: Internal | H23: Risiko | I23: Walaupun sudah ada Gitleaks pada CI/CD tapi cakupan Gitleaks terbatas pada repositori kode sehingga tidak dapat mendeteksi credential yang dibagikan melalui Slack, email, Jira, Trello, atau Google Drive; rendahnya awareness personil terhadap risiko keamanan credential sharing di platform komunikasi dan kolaborasi; tidak adanya kebijakan eksplisit yang melarang pembagian credential melalui channel yang tidak aman | J23: Credential yang terekspos dapat dimanfaatkan oleh threat actor untuk akses tidak terotorisasi ke sistem, API, dan layanan cloud; penyalahgunaan layanan cloud menggunakan API key yang bocor yang mengakibatkan kerugian finansial; kesulitan investigasi forensik karena credential exposure di channel kolaborasi tidak meninggalkan jejak audit yang memadai; potensi pelanggaran kepatuhan regulasi akibat akses tidak terotorisasi ke data nasabah | K23: Eksploitasi API key atau access token yang ditemukan di Slack, email, atau Google Drive untuk akses tidak terotorisasi; penyalahgunaan database credential untuk ekstrasi data nasabah; cloud service abuse menggunakan credential yang bocor yang mengakibatkan kerugian finansial; insider threat yang memanfaatkan credential yang dibagikan secara tidak aman | L23: Secret scanning tidak mencakup channel non-repositori; tidak ada kebijakan eksplisit yang melarang credential sharing di platform komunikasi; rendahnya awareness personil terhadap risiko credential exposure di luar konteks source code; tidak ada mekanisme rotasi credential otomatis jika terdeteksi bocor | M23: Secret scanning berbasis Gitleaks telah diintegrasikan ke dalam CI/CD pipeline untuk mendeteksi credential pada source code repositori; namun cakupan terbatas pada repositori kode dan tidak mencakup platform komunikasi, email korporat, platform manajemen proyek, dan layanan berbagi dokumen | N23: Kerahasiaan [C] + Keutuhan [I] | O23: 8.1 – Perencanaan dan pengendalian operasional; 9.1 – Pemantauan, pengukuran, analisis dan evaluasi | P23: A.5.17 – Informasi autentikasi; A.8.12 – Pencegahan kebocoran data; A.6.3 – Kesadaran, pendidikan dan pelatihan keamanan informasi; A.8.15 – Logging | Q23: 4 | R23: 4 | S23: =Q23*R23 -> 16 | T23: =_xlfn.IFNA(VLOOKUP(S23,Parameter!$D$53:$E$77,2),"") -> SEDANG-TINGGI | U23: Rendah — perusahaan tidak bersedia membiarkan credential terekspos melalui channel komunikasi yang tidak terpantau mengingat dampak langsung terhadap keamanan akses sistem kritis, integritas data nasabah, dan potensi kerugian finansial akibat penyalahgunaan layanan cloud | V23: Sedang — perusahaan masih dapat beroperasi selama nilai risiko residual ≤ 9; jika residual masih >9, wajib eskalasi ke manajemen. Sebagai syarat minimum toleransi, organisasi wajib memastikan telah tersedia: (1) kebijakan eksplisit yang melarang pembagian credential melalui channel yang tidak aman beserta panduan alternatif yang aman, dan (2) program awareness yang memastikan seluruh personil memahami risiko credential exposure di channel non-repositori dan cara penanganannya yang benar | W23: (1) Lakukan rotasi segera terhadap seluruh credential yang teridentifikasi telah dibagikan melalui channel tidak aman — revoke API key, reset password, dan regenerate access token yang terekspos; (2) audit seluruh log akses sistem dan layanan cloud untuk mengidentifikasi apakah credential yang bocor sudah dimanfaatkan oleh pihak tidak berwenang dalam periode teridentifikasi; (3) lakukan pencarian manual pada channel yang teridentifikasi menjadi medium kebocoran untuk memastikan tidak ada credential aktif lain yang masih terekspos; (4) eskalasi insiden kepada manajemen, dokumentasikan scope eksposur, dan tinjau kewajiban pelaporan regulasi jika sistem yang terekspos menangani data nasabah | X23: Susun dan sosialisasikan kebijakan eksplisit larangan credential sharing di channel tidak aman; implementasi program awareness credential security; eksplorasi tools DLP atau secret scanning yang dapat menjangkau channel non-repositori; implementasi secret manager sebagai alternatif aman pengganti credential sharing | Y23: DevSecOps | AA23: - Susun dan sosialisasikan kebijakan eksplisit larangan credential sharing di channel tidak aman — tetapkan larangan formal berbagi password, API key, access token, dan database credential melalui Slack, email, Jira, Trello, atau Google Drive; sertakan panduan alternatif yang aman seperti penggunaan secret manager; sosialisasikan kepada seluruh personil IT dengan bukti tanda tangan penerimaan kebijakan - Implementasi program awareness credential security — selenggarakan sesi edukasi yang mencakup risiko nyata credential exposure di channel komunikasi, contoh kasus eksploitasi credential yang bocor, dan praktik aman pengelolaan credential; wajibkan seluruh personil yang memiliki akses ke sistem kritis mengikuti program ini - Implementasi secret manager sebagai alternatif aman — deploy solusi secret manager seperti HashiCorp Vault atau solusi setara untuk mengelola dan mendistribusikan credential secara aman; eliminasi kebutuhan sharing credential manual dengan menyediakan mekanisme akses credential yang terkontrol dan teraudit - Evaluasi dan implementasi DLP atau secret scanning untuk channel non-repositori — kaji tools yang dapat mendeteksi pola credential di platform komunikasi dan kolaborasi yang digunakan; pertimbangkan solusi yang terintegrasi dengan platform yang sudah ada untuk memastikan deteksi otomatis credential exposure di luar scope Gitleaks | AB23: Personel DevSecOps berkoordinasi dengan Personel Security Analyst dan Personel IT Governance | AC23: 46387 | AD23: 46102 | AE23: Gitleaks sudah berjalan sebagai kontrol yang memadai untuk repositori kode namun tidak mencakup channel komunikasi dan kolaborasi, credential sharing di channel non-repositori sudah terbukti terjadi dan tidak terdeteksi, risiko masih terbuka pada level Tinggi, status In Progress dan menjadi prioritas untuk segera disusun kebijakan dan diselenggarakan awareness sebelum insiden eksploitasi terjadi | AL23: =Q23 -> 4 | AM23: =R23 -> 4 | AN23: =AL23*AM23 -> 16 | AO23: =_xlfn.IFNA(VLOOKUP(AN23,Parameter!$D$53:$E$77,2),"") -> SEDANG-TINGGI | AP23: New - Open
A24: IT | B24: =ROW()-ROW($B$14) -> 10 | C24: Development personnel granted direct read/write access terhadap production database containing real personal data tanpa data masking/anonymization, tanpa Just-In-Time (JIT) access mechanism, dan tanpa column-level restriction berdasarkan business necessity, violating principle of least privilege dan expanding insider threat risk. | D24: Aplikasi Identity and Access Management (IAM) & PAM | E24: Information | F24: Strategis | G24: External | H24: Risiko | N24: Semua (C - I - A) | Q24: 1 | R24: 1 | S24: =Q24*R24 -> 1 | T24: =_xlfn.IFNA(VLOOKUP(S24,Parameter!$D$53:$E$77,2),"") -> RENDAH | V24: - | W24: - | X24: - | Y24: IT Security Analyst | Z24: IT Infra - Sysadmin | AA24: - | AB24: - | AC24: 46387 | AD24: 46102 | AE24: - | AL24: =Q24 -> 1 | AM24: =R24 -> 1 | AN24: =AL24*AM24 -> 1 | AO24: =_xlfn.IFNA(VLOOKUP(AN24,Parameter!$D$53:$E$77,2),"") -> RENDAH | AP24: New - Open
A25: IT | B25: =ROW()-ROW($B$14) -> 11 | C25: Kerugian finansial dan pembocoran akses sistem berpotensi terjadi akibat personil yang tertipu permintaan tidak terotorisasi dari pihak yang menyamar sebagai pejabat senior atau nasabah menggunakan AI — akibat tidak adanya prosedur verifikasi identitas untuk permintaan mendadak melalui channel digital dan belum adanya awareness personil terhadap modus penipuan berbasis AI | D25: Aplikasi Identity and Access Management (IAM) & PAM | E25: Information | F25: Operasional | G25: External | H25: Risiko | I25: Tidak adanya prosedur out-of-band verification untuk permintaan mendadak yang diterima melalui channel digital; materi pelatihan security awareness belum mencakup modus penipuan berbasis AI seperti voice cloning dan deepfake video call; tidak adanya kebijakan yang mewajibkan verifikasi ulang untuk permintaan transfer dana, reset kredensial, atau pemberian akses yang diterima melalui telepon atau video call | J25: Transfer dana tidak terotorisasi yang disetujui berdasarkan instruksi dari pihak yang menyamar sebagai pejabat senior; akses sistem atau reset kredensial diberikan kepada pihak tidak berwenang yang menyamar sebagai personil IT; perubahan data nasabah atau polis yang tidak sah melalui proses verifikasi yang tertipu; kerugian finansial langsung dan potensi kebocoran data yang berdampak pada reputasi dan kepercayaan nasabah | K25: Telepon atau video call dari "direktur" atau "manajer senior" menggunakan suara atau wajah yang dimanipulasi AI yang meminta transfer dana mendadak atau persetujuan transaksi besar; telepon ke IT Helpdesk menggunakan suara mirip atasan yang meminta reset password atau pemberian akses darurat; pesan suara WhatsApp dari "pimpinan" yang meminta data sensitif atau tindakan segera tanpa prosedur formal | L25: Tidak ada prosedur verifikasi identitas untuk permintaan mendadak melalui channel digital; personil tidak memiliki awareness terhadap modus penipuan berbasis AI; tidak ada kebijakan yang mewajibkan konfirmasi melalui channel terpisah untuk permintaan sensitif; kepercayaan implisit terhadap suara atau wajah yang familiar tanpa verifikasi tambahan | M25: Program pelatihan security awareness telah dilaksanakan secara rutin kepada seluruh personil; namun materi belum mencakup modus penipuan berbasis AI seperti voice cloning dan deepfake, dan belum terdapat prosedur out-of-band verification untuk permintaan sensitif yang diterima melalui channel digital | N25: Kerahasiaan [C] + Keutuhan [I] | O25: 8.1 – Perencanaan dan pengendalian operasional; 6.1 – Tindakan untuk menangani risiko dan peluang | P25: A.8.5 – Autentikasi aman; A.5.15 – Manajemen akses; A.6.3 – Kesadaran, pendidikan dan pelatihan keamanan informasi; A.5.25 – Asesmen dan keputusan terkait peristiwa keamanan informasi | Q25: 4 | R25: 3 | S25: =Q25*R25 -> 12 | T25: =_xlfn.IFNA(VLOOKUP(S25,Parameter!$D$53:$E$77,2),"") -> SEDANG | U25: Rendah — perusahaan tidak bersedia membiarkan proses transfer dana, pemberian akses, dan verifikasi identitas bergantung pada kepercayaan implisit terhadap channel digital tanpa prosedur verifikasi tambahan, mengingat modus penipuan berbasis AI semakin mudah diakses dan semakin sulit dibedakan dari komunikasi asli | V25: Sedang — perusahaan masih dapat beroperasi selama nilai risiko residual ≤ 9; jika residual masih >9, wajib eskalasi ke manajemen. Sebagai syarat minimum toleransi, organisasi wajib memastikan telah tersedia: (1) materi pelatihan security awareness yang sudah diperbarui mencakup modus penipuan berbasis AI dengan contoh kasus konkret yang relevan bagi seluruh personil, dan (2) prosedur out-of-band verification yang terdokumentasi dan wajib dijalankan untuk setiap permintaan transfer dana, reset kredensial, dan pemberian akses yang diterima melalui telepon atau video call tanpa pengajuan formal | W25: (1) Bekukan segera transaksi, akses, atau perubahan yang terindikasi dilakukan berdasarkan instruksi dari pihak yang identitasnya diragukan; hubungi pihak yang diklaim sebagai pemberi instruksi melalui nomor resmi yang sudah terdaftar untuk konfirmasi; (2) kumpulkan dan amankan seluruh bukti komunikasi — rekaman telepon, video call, pesan — untuk keperluan investigasi forensik dan pelaporan; (3) laporkan insiden kepada manajemen senior segera dan koordinasikan dengan tim keamanan untuk analisis modus serangan yang digunakan; (4) eskalasi kepada Legal Counsel jika terjadi kerugian finansial dan dokumentasikan seluruh langkah penanganan sebagai bukti itikad baik kepada regulator | X25: Perbarui materi pelatihan security awareness dengan modul khusus modus penipuan berbasis AI; implementasi prosedur out-of-band verification wajib untuk permintaan sensitif; tetapkan kebijakan zero-trust untuk instruksi mendadak melalui channel digital | Y25: IT Security Analyst | AA25: - Perbarui materi pelatihan security awareness dengan modul modus penipuan berbasis AI — tambahkan contoh konkret seperti skenario "bos telepon minta transfer", "IT diminta reset password via telepon", dan "video call CEO palsu"; gunakan contoh kasus nyata dari industri keuangan dan asuransi global; wajibkan seluruh personil yang mengelola dana, akses sistem, dan data nasabah mengikuti pelatihan ini - Implementasi prosedur out-of-band verification wajib untuk permintaan sensitif — tetapkan kebijakan bahwa setiap permintaan transfer dana, reset kredensial, pemberian akses darurat, dan perubahan data nasabah yang diterima melalui telepon, video call, atau pesan digital wajib dikonfirmasi melalui nomor atau channel resmi yang sudah terdaftar sebelumnya — bukan melalui nomor yang menelepon - Tetapkan kebijakan zero-trust untuk instruksi mendadak melalui channel tidak resmi — tidak ada instruksi yang diterima melalui channel di luar prosedur formal yang dapat langsung dieksekusi tanpa verifikasi; sosialisasikan bahwa menolak instruksi mendadak tanpa verifikasi adalah tindakan yang benar dan didukung kebijakan perusahaan - Jadwalkan simulasi tabletop exercise skenario AI-based social engineering — simulasikan skenario nyata voice cloning dan deepfake video call yang menargetkan personil finance, IT helpdesk, dan unit bisnis; gunakan hasil simulasi untuk mengidentifikasi gap awareness dan memperkuat prosedur yang ada | AB25: Personel Security Analyst berkoordinasi dengan Personel IT Governance dan seluruh kepala unit yang menjalankan proses transfer dana, pengelolaan akses, dan verifikasi identitas | AC25: 46387 | AD25: 46102 | AE25: Pelatihan security awareness rutin sudah berjalan sebagai fondasi yang baik namun belum mencakup modus penipuan berbasis AI dan tidak ada prosedur out-of-band verification, personil rentan tertipu instruksi tidak terotorisasi melalui channel digital, status In Progress dan menjadi prioritas untuk segera diperbarui materi pelatihan dan ditetapkan prosedur verifikasi wajib | AL25: =Q25 -> 4 | AM25: =R25 -> 3 | AN25: =AL25*AM25 -> 12 | AO25: =_xlfn.IFNA(VLOOKUP(AN25,Parameter!$D$53:$E$77,2),"") -> SEDANG | AP25: New - Open
A26: IT | B26: =ROW()-ROW($B$14) -> 12 | C26: Remote access ke corporate systems via unencrypted public Wi-Fi networks tanpa mandatory VPN client enforcement memungkinkan Man-in-the-Middle (MitM) attack untuk credential interception, session hijacking, dan unauthorized access terhadap sensitive corporate information. | D26: Aplikasi Identity and Access Management (IAM) & PAM | E26: Information | F26: Strategis | G26: External | H26: Risiko | N26: Semua (C - I - A) | Q26: 1 | R26: 1 | S26: =Q26*R26 -> 1 | T26: =_xlfn.IFNA(VLOOKUP(S26,Parameter!$D$53:$E$77,2),"") -> RENDAH | V26: - | W26: - | X26: - | Y26: IT Security Analyst | AA26: - | AB26: - | AC26: 46387 | AD26: 46102 | AE26: - | AL26: =Q26 -> 1 | AM26: =R26 -> 1 | AN26: =AL26*AM26 -> 1 | AO26: =_xlfn.IFNA(VLOOKUP(AN26,Parameter!$D$53:$E$77,2),"") -> RENDAH | AP26: New - Open
A27: IT | B27: =ROW()-ROW($B$14) -> 13 | C27: Mobile application deployment tanpa code obfuscation, anti-debugging controls, root/jailbreak detection, dan hardcoded credential protection memungkinkan attacker untuk reverse-engineer aplikasi, extract embedded API keys, dan identify business logic vulnerabilities. | D27: Aplikasi Mobile | E27: Information | F27: Strategis | G27: External | H27: Risiko | N27: Semua (C - I - A) | Q27: 1 | R27: 1 | S27: =Q27*R27 -> 1 | T27: =_xlfn.IFNA(VLOOKUP(S27,Parameter!$D$53:$E$77,2),"") -> RENDAH | V27: - | W27: - | X27: - | Y27: Digital Application Development | Z27: IT Security Analyst | AA27: - | AB27: - | AC27: 46387 | AD27: 46102 | AE27: - | AL27: =Q27 -> 1 | AM27: =R27 -> 1 | AN27: =AL27*AM27 -> 1 | AO27: =_xlfn.IFNA(VLOOKUP(AN27,Parameter!$D$53:$E$77,2),"") -> RENDAH | AP27: New - Open
A28: IT | B28: =ROW()-ROW($B$14) -> 14 | C28: Project management tickets atau roadmap documentation yang mengungkapkan planned security control implementation timeline dan upcoming technology adoption memberikan threat actor information untuk timing attack execution sebelum mitigating controls menjadi operational. | D28: Aplikasi Ticketing | E28: Information | F28: Operasional | G28: Internal | H28: Risiko | Q28: 1 | R28: 1 | S28: =Q28*R28 -> 1 | T28: =_xlfn.IFNA(VLOOKUP(S28,Parameter!$D$53:$E$77,2),"") -> RENDAH | AC28: 46387 | AD28: 46102 | AL28: =Q28 -> 1 | AM28: =R28 -> 1 | AN28: =AL28*AM28 -> 1 | AO28: =_xlfn.IFNA(VLOOKUP(AN28,Parameter!$D$53:$E$77,2),"") -> RENDAH | AP28: New - Open
A29: IT | B29: =ROW()-ROW($B$14) -> 15 | C29: Celah keamanan tersembunyi dan dependency berbahaya berpotensi masuk ke aplikasi production tanpa terdeteksi — akibat tidak adanya review code yang terstruktur dan governance penggunaan AI tools dalam pengembangan sehingga kode yang dihasilkan AI tidak divalidasi keamanannya sebelum digunakan | D29: Aplikasi Web | E29: Software | F29: Operasional | G29: Internal | H29: Risiko | I29: Tidak adanya prosedur review code yang mewajibkan validasi keamanan terhadap kode yang dihasilkan AI sebelum digunakan dalam aplikasi; belum ada governance yang mengatur penggunaan AI code generation tools secara aman; tidak ada personil dedicated yang bertanggung jawab atas validasi keamanan kode; penanganan yang sepenuhnya reaktif tanpa mekanisme deteksi proaktif | J29: Dependency berbahaya atau typosquatting package masuk ke aplikasi tanpa terdeteksi; celah keamanan dalam logika kode yang dihasilkan AI dieksploitasi di production; supply chain attack melalui malicious package yang direkomendasikan AI; peningkatan technical debt keamanan akibat akumulasi kode tidak tervalidasi yang semakin sulit diaudit | K29: Typosquatting package yang direkomendasikan AI code generation tools yang mengandung malware; hidden security flaws dalam logika kode yang dihasilkan AI yang dapat dieksploitasi; insecure library recommendations yang membawa kerentanan ke aplikasi production; supply chain attack melalui dependency yang tidak tervalidasi | L29: Tidak ada review code yang mewajibkan validasi keamanan kode AI-generated; tidak ada governance penggunaan AI tools dalam pengembangan; tidak ada personil dedicated untuk security code review; tidak ada dependency scanning yang mendeteksi typosquatting dan malicious package secara proaktif; penanganan sepenuhnya reaktif tanpa mekanisme deteksi dini | M29: Penanganan permasalahan kode dilaksanakan secara reaktif berdasarkan kendala yang ditemukan saat operasional; belum terdapat prosedur review code terstruktur, governance AI tools, personil dedicated validasi keamanan, maupun mekanisme proaktif untuk mendeteksi dependency berbahaya sebelum masuk ke production | N29: Kerahasiaan [C] + Keutuhan [I] | O29: 8.1 – Perencanaan dan pengendalian operasional; 7.2 – Kompetensi | P29: A.8.25 – Siklus hidup pengembangan yang aman; A.8.26 – Persyaratan keamanan aplikasi; A.8.8 – Manajemen kerentanan teknis; A.5.19 – Keamanan informasi dalam hubungan pemasok | Q29: 4 | R29: 4 | S29: =Q29*R29 -> 16 | T29: =_xlfn.IFNA(VLOOKUP(S29,Parameter!$D$53:$E$77,2),"") -> SEDANG-TINGGI | U29: Rendah — perusahaan tidak bersedia membiarkan kode yang dihasilkan AI masuk ke aplikasi production tanpa validasi keamanan mengingat potensi hidden security flaws dan dependency berbahaya yang tidak terdeteksi dapat dieksploitasi secara aktif dan sulit diidentifikasi setelah terakumulasi | V29: Sedang — perusahaan masih dapat beroperasi selama nilai risiko residual ≤ 9; jika residual masih >9, wajib eskalasi ke manajemen. Sebagai syarat minimum toleransi, organisasi wajib memastikan telah tersedia: (1) prosedur review code yang mewajibkan validasi keamanan terhadap kode AI-generated sebelum dapat di-merge ke branch utama, dan (2) dependency scanning otomatis yang aktif dalam CI/CD pipeline untuk mendeteksi typosquatting dan malicious package sebelum deployment | W29: (1) Lakukan audit segera terhadap seluruh dependency yang ditambahkan dalam periode penggunaan AI code generation untuk mengidentifikasi package yang mencurigakan atau tidak dikenal; (2) jalankan dependency scanning manual terhadap seluruh aplikasi yang aktif untuk mengidentifikasi typosquatting package atau malicious library yang mungkin sudah masuk ke production; (3) isolasi dan rollback komponen yang teridentifikasi mengandung dependency berbahaya atau celah keamanan kritis; (4) eskalasi temuan kepada manajemen dan dokumentasikan scope potensi eksposur sebagai justifikasi urgensi implementasi governance AI dan review code yang terstruktur | X29: Susun kebijakan governance penggunaan AI code generation tools; implementasi prosedur review code wajib untuk kode AI-generated; aktifkan dependency scanning otomatis dalam CI/CD pipeline; tingkatkan awareness developer terhadap risiko AI-generated code | Y29: IT Governance | AA29: - Susun kebijakan governance penggunaan AI code generation tools — tetapkan tools AI yang diizinkan secara resmi, batasan penggunaannya, kewajiban review sebelum kode digunakan, dan larangan penggunaan AI untuk komponen yang menangani data nasabah sensitif tanpa review keamanan; sosialisasikan kepada seluruh developer sebagai kebijakan yang mengikat - Implementasi prosedur review code wajib untuk kode AI-generated — tetapkan bahwa seluruh kode yang dihasilkan AI wajib melalui security-focused code review oleh personil yang kompeten sebelum dapat di-merge; gunakan checklist review yang mencakup validasi dependency, logika akses data, dan potensi injection vulnerability - Aktifkan dependency scanning otomatis dalam CI/CD pipeline — implementasikan tools seperti OWASP Dependency-Check atau Dependabot untuk mendeteksi typosquatting package, malicious library, dan dependency dengan CVE yang diketahui secara otomatis sebelum deployment; jadikan sebagai gate wajib yang memblokir build jika dependency berbahaya terdeteksi - Selenggarakan awareness training untuk developer tentang risiko AI-generated code — edukasi developer mengenai risiko spesifik penggunaan AI code generation seperti typosquatting, hidden logic flaws, dan insecure library recommendations; sertakan panduan cara memvalidasi kode dan dependency yang dihasilkan AI sebelum digunakan | AB29: Personel DevSecOps berkoordinasi dengan Personel IT Core Development dan Personel IT Governance dan Personel IT Digital Development dan Personel IT Security Analyst | AC29: 46387 | AD29: 46102 | AE29: Penanganan masih sepenuhnya reaktif tanpa review code, governance AI, dan dependency scanning proaktif, kode AI-generated masuk ke aplikasi tanpa validasi keamanan, risiko masih terbuka penuh pada level Tinggi, status New - Open dan menjadi prioritas untuk segera disusun governance AI dan diaktifkan dependency scanning dalam CI/CD pipeline | AL29: =Q29 -> 4 | AM29: =R29 -> 4 | AN29: =AL29*AM29 -> 16 | AO29: =_xlfn.IFNA(VLOOKUP(AN29,Parameter!$D$53:$E$77,2),"") -> SEDANG-TINGGI | AP29: New - Open
A30: IT | B30: =ROW()-ROW($B$14) -> 16 | C30: Critical application dependencies terhadap abandoned open-source libraries (no active maintenance, no security updates, no community support) memungkinkan unmitigated vulnerability exploitation tanpa remediation path atau alternative mitigation options available. | D30: Aplikasi Web | E30: Information | F30: Strategis | G30: External | H30: Risiko | N30: Semua (C - I - A) | Q30: 1 | R30: 1 | S30: =Q30*R30 -> 1 | T30: =_xlfn.IFNA(VLOOKUP(S30,Parameter!$D$53:$E$77,2),"") -> RENDAH | V30: - | W30: - | X30: - | Y30: IT Security Analyst | AA30: - | AB30: - | AC30: 46387 | AD30: 46102 | AE30: - | AL30: =Q30 -> 1 | AM30: =R30 -> 1 | AN30: =AL30*AM30 -> 1 | AO30: =_xlfn.IFNA(VLOOKUP(AN30,Parameter!$D$53:$E$77,2),"") -> RENDAH | AP30: New - Open
A31: IT | B31: =ROW()-ROW($B$14) -> 17 | C31: Inadequate logging dan distributed tracing implementation across microservices architecture tanpa centralized correlation ID dan log aggregation memungkinkan delayed incident detection, difficult forensic investigation, dan inability untuk trace attack progression across system components. | D31: Arsitektur Aplikasi | E31: Information | F31: Strategis | G31: External | H31: Risiko | N31: Semua (C - I - A) | Q31: 1 | R31: 1 | S31: =Q31*R31 -> 1 | T31: =_xlfn.IFNA(VLOOKUP(S31,Parameter!$D$53:$E$77,2),"") -> RENDAH | V31: - | W31: - | X31: - | Y31: Digital Application Development | Z31: DevSecOps | AA31: - | AB31: - | AC31: 46387 | AD31: 46102 | AE31: - | AL31: =Q31 -> 1 | AM31: =R31 -> 1 | AN31: =AL31*AM31 -> 1 | AO31: =_xlfn.IFNA(VLOOKUP(AN31,Parameter!$D$53:$E$77,2),"") -> RENDAH | AP31: New - Open
A32: IT | B32: =ROW()-ROW($B$14) -> 18 | C32: Absence dari Circuit Breaker pattern, timeout enforcement, dan graceful degradation logic dalam microservices communication menyebabkan cascading failures dimana single service outage menyebabkan resource exhaustion dan service unavailability terhadap dependent critical systems. | D32: Arsitektur Aplikasi | E32: Information | F32: Strategis | G32: External | H32: Risiko | N32: Semua (C - I - A) | Q32: 1 | R32: 1 | S32: =Q32*R32 -> 1 | T32: =_xlfn.IFNA(VLOOKUP(S32,Parameter!$D$53:$E$77,2),"") -> RENDAH | V32: - | W32: - | X32: - | Y32: Digital Application Development | Z32: DevSecOps | AA32: - | AB32: - | AC32: 46387 | AD32: 46102 | AE32: - | AL32: =Q32 -> 1 | AM32: =R32 -> 1 | AN32: =AL32*AM32 -> 1 | AO32: =_xlfn.IFNA(VLOOKUP(AN32,Parameter!$D$53:$E$77,2),"") -> RENDAH | AP32: New - Open
A33: IT | B33: =ROW()-ROW($B$14) -> 19 | C33: Microservices architecture dengan excessive inter-service dependency dan synchronous request chaining mengakibatkan performance degradation, cascading latency amplification, dan increased vulnerability window terhadap request-level attacks seperti timing attacks atau request smuggling. | D33: Arsitektur Aplikasi | E33: Information | F33: Strategis | G33: External | H33: Risiko | N33: Semua (C - I - A) | Q33: 1 | R33: 1 | S33: =Q33*R33 -> 1 | T33: =_xlfn.IFNA(VLOOKUP(S33,Parameter!$D$53:$E$77,2),"") -> RENDAH | V33: - | W33: - | X33: - | Y33: Digital Application Development | Z33: DevSecOps | AA33: - | AB33: - | AC33: 46387 | AD33: 46102 | AE33: - | AL33: =Q33 -> 1 | AM33: =R33 -> 1 | AN33: =AL33*AM33 -> 1 | AO33: =_xlfn.IFNA(VLOOKUP(AN33,Parameter!$D$53:$E$77,2),"") -> RENDAH | AP33: New - Open
A34: IT | B34: =ROW()-ROW($B$14) -> 20 | C34: Over-reliance pada asynchronous event-driven architecture (Kafka, RabbitMQ, message queues) tanpa documented data flow diagram, event schema definition, atau dead-letter queue handling memungkinkan data loss, race condition, dan difficult incident investigation. | D34: Arsitektur Aplikasi | E34: Information | F34: Strategis | G34: External | H34: Risiko | N34: Semua (C - I - A) | Q34: 1 | R34: 1 | S34: =Q34*R34 -> 1 | T34: =_xlfn.IFNA(VLOOKUP(S34,Parameter!$D$53:$E$77,2),"") -> RENDAH | V34: - | W34: - | X34: - | Y34: Digital Application Development | Z34: DevSecOps | AA34: - | AB34: - | AC34: 46387 | AD34: 46102 | AE34: - | AL34: =Q34 -> 1 | AM34: =R34 -> 1 | AN34: =AL34*AM34 -> 1 | AO34: =_xlfn.IFNA(VLOOKUP(AN34,Parameter!$D$53:$E$77,2),"") -> RENDAH | AP34: New - Open
A35: IT | B35: =ROW()-ROW($B$14) -> 21 | C35: Orphaned microservices yang tetap operational tanpa assigned team ownership, security patch management, atau incident response capability menyebabkan unmitigated vulnerability accumulation dan undetected service compromise. | D35: Arsitektur Aplikasi | E35: Information | F35: Strategis | G35: External | H35: Risiko | N35: Semua (C - I - A) | Q35: 1 | R35: 1 | S35: =Q35*R35 -> 1 | T35: =_xlfn.IFNA(VLOOKUP(S35,Parameter!$D$53:$E$77,2),"") -> RENDAH | V35: - | W35: - | X35: - | Y35: Digital Application Development | Z35: DevSecOps | AA35: - | AB35: - | AC35: 46387 | AD35: 46102 | AE35: - | AL35: =Q35 -> 1 | AM35: =R35 -> 1 | AN35: =AL35*AM35 -> 1 | AO35: =_xlfn.IFNA(VLOOKUP(AN35,Parameter!$D$53:$E$77,2),"") -> RENDAH | AP35: New - Open
A36: IT | B36: =ROW()-ROW($B$14) -> 22 | C36: Microservices decomposition menciptakan dramatically expanded attack surface melalui numerous internal API endpoints tanpa mutual TLS (mTLS) enforcement, Zero Trust architecture, atau service-to-service authentication, memungkinkan lateral movement tanpa credential validation. | D36: Arsitektur Aplikasi | E36: Information | F36: Strategis | G36: External | H36: Risiko | N36: Semua (C - I - A) | Q36: 1 | R36: 1 | S36: =Q36*R36 -> 1 | T36: =_xlfn.IFNA(VLOOKUP(S36,Parameter!$D$53:$E$77,2),"") -> RENDAH | V36: - | W36: - | X36: - | Y36: Digital Application Development | Z36: IT Security Analyst | AA36: - | AB36: - | AC36: 46387 | AD36: 46102 | AE36: - | AL36: =Q36 -> 1 | AM36: =R36 -> 1 | AN36: =AL36*AM36 -> 1 | AO36: =_xlfn.IFNA(VLOOKUP(AN36,Parameter!$D$53:$E$77,2),"") -> RENDAH | AP36: New - Open
A37: IT | B37: =ROW()-ROW($B$14) -> 23 | C37: Configuration Management Database (CMDB) tidak maintained dengan accurate current state information menyebabkan incomplete asset visibility, inability untuk determine service dependency mapping, dan inability untuk perform comprehensive impact analysis selama incident atau change management. | D37: Arsitektur Aplikasi | E37: Information | F37: Strategis | G37: External | H37: Risiko | N37: Semua (C - I - A) | Q37: 1 | R37: 1 | S37: =Q37*R37 -> 1 | T37: =_xlfn.IFNA(VLOOKUP(S37,Parameter!$D$53:$E$77,2),"") -> RENDAH | V37: - | W37: - | X37: - | Y37: Digital Application Development | AA37: - | AB37: - | AC37: 46387 | AD37: 46102 | AE37: - | AL37: =Q37 -> 1 | AM37: =R37 -> 1 | AN37: =AL37*AM37 -> 1 | AO37: =_xlfn.IFNA(VLOOKUP(AN37,Parameter!$D$53:$E$77,2),"") -> RENDAH | AP37: New - Open
A38: IT | B38: =ROW()-ROW($B$14) -> 24 | C38: Microservices dengan tightly coupled dependencies dan shared state management menciptakan operasional complexity similar dengan monolithic application, preventing independent deployment dan requiring coordinated downtime across multiple service untuk complete update cycle. | D38: Arsitektur Aplikasi | E38: Information | F38: Strategis | G38: External | H38: Risiko | N38: Semua (C - I - A) | Q38: 1 | R38: 1 | S38: =Q38*R38 -> 1 | T38: =_xlfn.IFNA(VLOOKUP(S38,Parameter!$D$53:$E$77,2),"") -> RENDAH | V38: - | W38: - | X38: - | Y38: Digital Application Development | AA38: - | AB38: - | AC38: 46387 | AD38: 46102 | AE38: - | AL38: =Q38 -> 1 | AM38: =R38 -> 1 | AN38: =AL38*AM38 -> 1 | AO38: =_xlfn.IFNA(VLOOKUP(AN38,Parameter!$D$53:$E$77,2),"") -> RENDAH | AP38: New - Open
A39: IT | B39: =ROW()-ROW($B$14) -> 25 | C39: Ketiadaan dari distributed transaction management pattern (Saga, Two-Phase Commit) di microservices architecture menyebabkan data inconsistency, orphaned records, dan inability untuk guarantee ACID properties terhadap multi-service transactions. | D39: Arsitektur Aplikasi | E39: Information | F39: Strategis | G39: External | H39: Risiko | N39: Semua (C - I - A) | Q39: 1 | R39: 1 | S39: =Q39*R39 -> 1 | T39: =_xlfn.IFNA(VLOOKUP(S39,Parameter!$D$53:$E$77,2),"") -> RENDAH | V39: - | W39: - | X39: - | Y39: Digital Application Development | AA39: - | AB39: - | AC39: 46387 | AD39: 46102 | AE39: - | AL39: =Q39 -> 1 | AM39: =R39 -> 1 | AN39: =AL39*AM39 -> 1 | AO39: =_xlfn.IFNA(VLOOKUP(AN39,Parameter!$D$53:$E$77,2),"") -> RENDAH | AP39: New - Open
A40: IT | B40: =ROW()-ROW($B$14) -> 26 | C40: Polyglot microservices architecture dengan shared single database backend eliminates database-level isolation benefit, preventing independent scaling, creating schema coupling, dan enabling unauthorized data access across service boundaries. | D40: Arsitektur Aplikasi | E40: Information | F40: Strategis | G40: External | H40: Risiko | N40: Semua (C - I - A) | Q40: 1 | R40: 1 | S40: =Q40*R40 -> 1 | T40: =_xlfn.IFNA(VLOOKUP(S40,Parameter!$D$53:$E$77,2),"") -> RENDAH | V40: - | W40: - | X40: - | Y40: Digital Application Development | AA40: - | AB40: - | AC40: 46387 | AD40: 46102 | AE40: - | AL40: =Q40 -> 1 | AM40: =R40 -> 1 | AN40: =AL40*AM40 -> 1 | AO40: =_xlfn.IFNA(VLOOKUP(AN40,Parameter!$D$53:$E$77,2),"") -> RENDAH | AP40: New - Open
A41: IT | B41: =ROW()-ROW($B$14) -> 27 | C41: Unrestricted technology choice (programming language, database, framework) across development teams tanpa standardization atau architectural governance menciptakan operational complexity, fragmented security posture, dan difficult knowledge transfer untuk incident response dan maintenance. | D41: Arsitektur Aplikasi | E41: Information | F41: Strategis | G41: External | H41: Risiko | N41: Semua (C - I - A) | Q41: 1 | R41: 1 | S41: =Q41*R41 -> 1 | T41: =_xlfn.IFNA(VLOOKUP(S41,Parameter!$D$53:$E$77,2),"") -> RENDAH | V41: - | W41: - | X41: - | Y41: Digital Application Development | AA41: - | AB41: - | AC41: 46387 | AD41: 46102 | AE41: - | AL41: =Q41 -> 1 | AM41: =R41 -> 1 | AN41: =AL41*AM41 -> 1 | AO41: =_xlfn.IFNA(VLOOKUP(AN41,Parameter!$D$53:$E$77,2),"") -> RENDAH | AP41: New - Open
A42: IT | B42: =ROW()-ROW($B$14) -> 28 | C42: Peningkatan efisiensi operasional IT yang signifikan dan eliminasi human error secara sistematis berpotensi terwujud — melalui perluasan kapabilitas otomatisasi yang sudah terbukti berjalan ke seluruh proses operasional yang teridentifikasi belum diotomatisasi melalui gap analisis yang terstruktur | D42: Automation Testing | E42: Software | F42: Strategis | G42: Internal | H42: Peluang | I42: Keterbatasan personil yang mendorong kebutuhan otomatisasi sebagai solusi efisiensi kapasitas; fondasi otomatisasi yang sudah terbukti berjalan pada beberapa domain memberikan kepercayaan teknis untuk perluasan; meningkatnya kompleksitas operasional IT yang tidak dapat diselesaikan dengan penambahan personil semata | J42: Pengurangan beban kerja manual yang membebaskan kapasitas personil untuk fokus pada tugas bernilai lebih tinggi; eliminasi human error pada proses repetitif yang meningkatkan keandalan operasional; percepatan eksekusi proses operasional yang meningkatkan kecepatan delivery layanan IT; pengurangan biaya operasional jangka panjang yang dapat dialokasikan ke inisiatif strategis bisnis | K42: Pertumbuhan kompleksitas operasional IT yang melebihi kapasitas penambahan personil; tekanan efisiensi biaya yang mendorong optimasi proses sebagai prioritas; perkembangan tools otomatisasi open-source yang semakin matang dan dapat diadopsi tanpa investasi lisensi signifikan | L42: Belum ada gap analisis menyeluruh yang memetakan seluruh proses yang berpotensi diotomatisasi; keterbatasan personil yang mengerjakan otomatisasi sambil menjalankan operasional harian; prioritas anggaran IT yang lebih diarahkan ke kebutuhan bisnis daripada efisiensi internal; tidak adanya roadmap otomatisasi yang terstruktur sebagai panduan perluasan bertahap | M42: Otomatisasi proses telah diimplementasikan pada beberapa domain operasional IT meliputi deployment melalui Jenkins CI/CD pipeline, penjadwalan background scheduler pada aplikasi, dan eksekusi tugas terjadwal melalui cronjob pada sistem administrasi; namun belum terdapat gap analisis menyeluruh yang memetakan potensi perluasan otomatisasi secara strategis | N42: Keutuhan [I] + Ketersediaan [A] | O42: 8.1 – Perencanaan dan pengendalian operasional; 9.1 – Pemantauan, pengukuran, analisis dan evaluasi | P42: A.5.37 – Prosedur operasi yang terdokumentasi; A.8.6 – Manajemen kapasitas; A.8.25 – Siklus hidup pengembangan yang aman | Q42: 3 | R42: 4 | S42: =Q42*R42 -> 12 | T42: =_xlfn.IFNA(VLOOKUP(S42,Parameter!$D$53:$E$77,2),"") -> SEDANG | U42: Tinggi — perusahaan memiliki ambisi untuk mengkapitalisasi peluang ini secara aktif mengingat fondasi otomatisasi yang sudah terbukti berjalan membuat perluasan dapat dilakukan secara inkremental dengan risiko implementasi yang rendah dan dampak efisiensi yang langsung terukur | V42: Sedang — perusahaan masih dapat beroperasi dengan level otomatisasi saat ini selama beban operasional manual masih dapat ditangani oleh personil yang ada; jika volume operasional manual sudah secara konsisten melampaui kapasitas tim, realisasi peluang ini wajib dieskalasi sebagai prioritas. Sebagai syarat minimum untuk mulai mengkapitalisasi peluang, organisasi wajib memastikan telah tersedia: (1) gap analisis proses operasional IT yang mengidentifikasi dan memprioritaskan seluruh proses berpotensi diotomatisasi berdasarkan nilai efisiensi dan kompleksitas implementasi, dan (2) roadmap otomatisasi bertahap yang terdokumentasi sebagai panduan perluasan yang terstruktur | W42: (1) Dokumentasikan setiap insiden human error atau bottleneck operasional yang terjadi sebagai justifikasi konkret untuk memprioritaskan otomatisasi proses terdampak; (2) identifikasi quick win otomatisasi yang dapat diimplementasikan dalam waktu singkat menggunakan tools yang sudah tersedia seperti Jenkins atau cronjob untuk membuktikan nilai tambah secara cepat; (3) presentasikan hasil quick win kepada manajemen sebagai bukti ROI otomatisasi untuk mendapatkan alokasi kapasitas personil atau anggaran yang lebih besar; (4) eskalasi roadmap otomatisasi kepada manajemen dengan framing pengurangan biaya operasional jangka panjang dan peningkatan keandalan layanan IT | X42: Lakukan gap analisis menyeluruh untuk mengidentifikasi proses yang belum diotomatisasi; susun roadmap otomatisasi bertahap berbasis prioritas nilai efisiensi; mulai dengan quick win pada proses berulang dan bernilai tinggi menggunakan tools yang sudah tersedia | Y42: DevSecOps | AA42: - Lakukan gap analisis menyeluruh proses operasional IT — identifikasi dan inventarisasi seluruh proses repetitif yang masih dilakukan secara manual; kategorikan berdasarkan frekuensi eksekusi, potensi human error, dan kompleksitas implementasi otomatisasi; urutkan prioritas berdasarkan rasio nilai efisiensi terhadap effort implementasi - Susun roadmap otomatisasi bertahap dan presentasikan ke manajemen — dokumentasikan jalur perluasan otomatisasi yang dapat dieksekusi secara inkremental menggunakan tools yang sudah tersedia; kuantifikasi estimasi penghematan waktu dan pengurangan error per proses sebagai justifikasi bisnis yang terukur - Implementasi quick win otomatisasi pada proses prioritas — mulai dengan mengotomatisasi proses yang paling sering dikerjakan manual, bervolume tinggi, dan dapat diselesaikan menggunakan Jenkins atau cronjob yang sudah tersedia; dokumentasikan hasil penghematan sebagai bukti ROI yang konkret - Eksplorasi RPA dan low-code automation untuk proses bisnis lintas sistem — evaluasi tools Robotic Process Automation open-source atau low-code yang dapat mengotomatisasi proses yang melibatkan multiple sistem tanpa memerlukan integrasi API penuh; jadikan sebagai investasi jangka menengah setelah quick win pertama berhasil dibuktikan | AB42: Personel DevSecOps berkoordinasi dengan Personel IT Infra - Sysadmin, Personel IT Governance, dan Personel IT Prod-Support | AC42: 46387 | AD42: 46102 | AE42: Jenkins, background scheduler, dan cronjob sudah berjalan sebagai fondasi otomatisasi yang terbukti kuat, namun gap analisis menyeluruh dan roadmap perluasan belum ada sehingga potensi efisiensi yang lebih besar belum dikapitalisasi, status New - Open dan menjadi prioritas strategis untuk segera dilakukan gap analisis dan disusun roadmap otomatisasi bertahap | AL42: =Q42 -> 3 | AM42: =R42 -> 4 | AN42: =AL42*AM42 -> 12 | AO42: =_xlfn.IFNA(VLOOKUP(AN42,Parameter!$D$53:$E$77,2),"") -> SEDANG | AP42: New - Open
A43: IT | B43: =ROW()-ROW($B$14) -> 29 | C43: Persistent security warnings dan SAST/SCA findings dalam CI/CD pipeline yang consistently diabaikan atau suppressed tanpa justification menyebabkan normalization dari security deviation, reduced security control effectiveness, dan cultural acceptance terhadap security non-compliance. | D43: Automation Testing | E43: Information | F43: Strategis | G43: External | H43: Risiko | N43: Semua (C - I - A) | Q43: 1 | R43: 1 | S43: =Q43*R43 -> 1 | T43: =_xlfn.IFNA(VLOOKUP(S43,Parameter!$D$53:$E$77,2),"") -> RENDAH | V43: - | W43: - | X43: - | Y43: IT Security Analyst | AA43: - | AB43: - | AC43: 46387 | AD43: 46102 | AE43: - | AL43: =Q43 -> 1 | AM43: =R43 -> 1 | AN43: =AL43*AM43 -> 1 | AO43: =_xlfn.IFNA(VLOOKUP(AN43,Parameter!$D$53:$E$77,2),"") -> RENDAH | AP43: New - Open
A44: IT | B44: =ROW()-ROW($B$14) -> 30 | C44: Business Intelligence dashboard dengan unrestricted "Export to Excel/CSV" functionality memungkinkan bulk sensitive data exfiltration tanpa data loss prevention (DLP) control, audit trail, atau export audit requirement. | D44: Dasboard Business Intelligence | E44: Information | F44: Strategis | G44: External | H44: Risiko | N44: Semua (C - I - A) | Q44: 1 | R44: 1 | S44: =Q44*R44 -> 1 | T44: =_xlfn.IFNA(VLOOKUP(S44,Parameter!$D$53:$E$77,2),"") -> RENDAH | V44: - | W44: - | X44: - | Y44: Data Analytics | AA44: - | AB44: - | AC44: 46387 | AD44: 46102 | AE44: - | AL44: =Q44 -> 1 | AM44: =R44 -> 1 | AN44: =AL44*AM44 -> 1 | AO44: =_xlfn.IFNA(VLOOKUP(AN44,Parameter!$D$53:$E$77,2),"") -> RENDAH | AP44: New - Open
A45: IT | B45: =ROW()-ROW($B$14) -> 31 | C45: Orphaned BI dashboard dan automated reporting artifacts yang tetap operational tanpa assigned owner, regular access review, atau decommissioning procedure menyebabkan unnecessarily expensive resource consumption, stale data distribution, dan potential security gap dari unreviewed data access. | D45: Dasboard Business Intelligence | E45: Information | F45: Strategis | G45: External | H45: Risiko | N45: Semua (C - I - A) | Q45: 1 | R45: 1 | S45: =Q45*R45 -> 1 | T45: =_xlfn.IFNA(VLOOKUP(S45,Parameter!$D$53:$E$77,2),"") -> RENDAH | V45: - | W45: - | X45: - | Y45: Data Analytics | AA45: - | AB45: - | AC45: 46387 | AD45: 46102 | AE45: - | AL45: =Q45 -> 1 | AM45: =R45 -> 1 | AN45: =AL45*AM45 -> 1 | AO45: =_xlfn.IFNA(VLOOKUP(AN45,Parameter!$D$53:$E$77,2),"") -> RENDAH | AP45: New - Open
A46: IT | B46: =ROW()-ROW($B$14) -> 32 | C46: Predictive analytics model atau reporting logic development tanpa rigorous validation terhadap underlying data quality assumptions, seasonal anomaly detection, atau statistical significance testing menghasilkan inaccurate business decision support dan potential fraud detection bypass. | D46: Dasboard Business Intelligence | E46: Information | F46: Strategis | G46: Internal | H46: Risiko | N46: Semua (C - I - A) | Q46: 1 | R46: 1 | S46: =Q46*R46 -> 1 | T46: =_xlfn.IFNA(VLOOKUP(S46,Parameter!$D$53:$E$77,2),"") -> RENDAH | V46: - | W46: - | X46: - | Y46: Data Analytics | AA46: - | AB46: - | AC46: 46387 | AD46: 46102 | AE46: - | AL46: =Q46 -> 1 | AM46: =R46 -> 1 | AN46: =AL46*AM46 -> 1 | AO46: =_xlfn.IFNA(VLOOKUP(AN46,Parameter!$D$53:$E$77,2),"") -> RENDAH | AP46: New - Open
A47: IT | B47: =ROW()-ROW($B$14) -> 33 | C47: Multiple authoritative data sources atau reporting systems yang menghasilkan conflicting metrics untuk same business entity menciptakan data integrity doubt, enabling manipulation, dan preventing consensus pada business-critical metrics untuk decision-making. | D47: Dasboard Business Intelligence | E47: Information | F47: Strategis | G47: External | H47: Risiko | N47: Semua (C - I - A) | Q47: 1 | R47: 1 | S47: =Q47*R47 -> 1 | T47: =_xlfn.IFNA(VLOOKUP(S47,Parameter!$D$53:$E$77,2),"") -> RENDAH | V47: - | W47: - | X47: - | Y47: Data Management | AA47: - | AB47: - | AC47: 46387 | AD47: 46102 | AE47: - | AL47: =Q47 -> 1 | AM47: =R47 -> 1 | AN47: =AL47*AM47 -> 1 | AO47: =_xlfn.IFNA(VLOOKUP(AN47,Parameter!$D$53:$E$77,2),"") -> RENDAH | AP47: New - Open
A48: IT | B48: =ROW()-ROW($B$14) -> 34 | C48: Publicly disclosed atau easily inferred security monitoring alert thresholds memungkinkan threat actor merancang low-intensity attack strategy yang maintain persistence di bawah detection threshold, extending dwell time dan enabling stealthy data exfiltration. | D48: Dashboard Monitoring Tool | E48: Information | F48: Operasional | G48: Internal | H48: Risiko | Q48: 1 | R48: 1 | S48: =Q48*R48 -> 1 | T48: =_xlfn.IFNA(VLOOKUP(S48,Parameter!$D$53:$E$77,2),"") -> RENDAH | AC48: 46387 | AD48: 46102 | AL48: =Q48 -> 1 | AM48: =R48 -> 1 | AN48: =AL48*AM48 -> 1 | AO48: =_xlfn.IFNA(VLOOKUP(AN48,Parameter!$D$53:$E$77,2),"") -> RENDAH | AP48: New - Open
A49: IT | B49: =ROW()-ROW($B$14) -> 35 | C49: Monitoring dashboard configuration exposure mengidentifikasi unmonitored systems atau low-fidelity monitoring areas yang menjadi ideal lateral movement vector untuk attacker untuk bergerak tanpa deteksi. | D49: Dashboard Monitoring Tool | E49: Information | F49: Operasional | G49: Internal | H49: Risiko | Q49: 1 | R49: 1 | S49: =Q49*R49 -> 1 | T49: =_xlfn.IFNA(VLOOKUP(S49,Parameter!$D$53:$E$77,2),"") -> RENDAH | AC49: 46387 | AD49: 46102 | AL49: =Q49 -> 1 | AM49: =R49 -> 1 | AN49: =AL49*AM49 -> 1 | AO49: =_xlfn.IFNA(VLOOKUP(AN49,Parameter!$D$53:$E$77,2),"") -> RENDAH | AP49: New - Open
A50: IT | B50: =ROW()-ROW($B$14) -> 36 | C50: Server Downtime & Data Loss – Keterbatasan infrastruktur backup, belum optimalnya cakupan DR untuk proses bisnis kritis, dan tidak adanya pengujian restore end-to-end meningkatkan risiko business interruption dan data loss yang berdampak pada operasional bisnis asuransi | D50: Data Backup & Restore Point | E50: Information | F50: Operasional | G50: Internal | H50: Risiko | I50: Keterbatasan kapasitas storage dan performa server backup; cakupan backup ke DR belum mencakup seluruh proses bisnis kritis; pengujian restore end-to-end belum dilaksanakan akibat keterbatasan sumber daya; tidak adanya validasi berkala terhadap integritas dan kelengkapan backup | J50: Keterbatasan kapasitas storage dan performa server backup; cakupan backup ke DR belum mencakup seluruh proses bisnis kritis; pengujian restore end-to-end belum dilaksanakan akibat keterbatasan sumber daya; tidak adanya validasi berkala terhadap integritas dan kelengkapan backup | K50: Kegagalan hardware server yang tidak dapat dipulihkan tepat waktu; ransomware yang mengenkripsi data produksi dan backup; bencana alam atau insiden yang memaksa aktivasi DR; corruption data yang tidak terdeteksi pada backup | L50: Storage backup terbatas sehingga tidak semua data kritis ter-backup penuh; performa server backup lambat berpotensi menyebabkan backup tidak selesai dalam window yang ditentukan; cakupan DR belum 100% mencakup proses bisnis kritis; restore end-to-end belum pernah diuji secara menyeluruh | M50: Veeam aktif dengan metode backup 3-2-1; backup rutin sudah berjalan; replikasi otomatis ke DR sudah aktif; SOP restore sudah tersedia dan restore parsial sudah pernah dijalankan | N50: Keutuhan [I] + Ketersediaan [A] | O50: 8.1 – Perencanaan dan pengendalian operasional; 9.1 – Pemantauan, pengukuran, analisis dan evaluasi | P50: A.8.13 – Backup informasi; A.5.29 – Keamanan informasi selama gangguan; A.5.30 – Kesiapan ICT untuk keberlangsungan bisnis | Q50: 4 | R50: 4 | S50: =Q50*R50 -> 16 | T50: =_xlfn.IFNA(VLOOKUP(S50,Parameter!$D$53:$E$77,2),"") -> SEDANG-TINGGI | U50: Rendah — perusahaan tidak bersedia menanggung risiko kegagalan pemulihan data pada saat bencana nyata mengingat dampaknya langsung pada keberlangsungan operasional bisnis asuransi, kepercayaan nasabah, dan pemenuhan kewajiban regulasi | V50: Sedang — perusahaan masih dapat beroperasi selama nilai risiko residual ≤ 9; jika residual masih >9, wajib eskalasi ke manajemen untuk penanganan segera dalam perencanaan anggaran infrastruktur | W50: Aktivasi prosedur DR dan eskalasi ke manajemen; jalankan restore dari backup terakhir yang valid; koordinasi dengan vendor Veeam untuk dukungan teknis darurat; dokumentasikan timeline insiden dan dampak bisnis untuk keperluan pelaporan regulasi | X50: Ekspansi kapasitas storage backup; optimasi konfigurasi Veeam untuk peningkatan performa; perluas cakupan DR untuk mencakup seluruh proses bisnis kritis; jadwalkan dan laksanakan DR drill dan restore end-to-end secara berkala | Y50: IT Infra - Sysadmin | AA50: - Inventarisasi proses bisnis kritis — identifikasi dan dokumentasikan seluruh proses bisnis kritis yang belum tercakup dalam replikasi DR, prioritaskan berdasarkan dampak bisnis - Perluas cakupan backup DR hingga 100% proses kritis — pastikan seluruh sistem dan data yang mendukung proses bisnis kritis masuk dalam scope replikasi otomatis ke DR - Ekspansi kapasitas storage backup — tambah kapasitas storage atau implementasi tiered storage untuk mengatasi keterbatasan yang menyebabkan backup tidak optimal - Tetapkan dan dokumentasikan RTO & RPO — definisikan target Recovery Time Objective dan Recovery Point Objective untuk setiap sistem kritis sebagai acuan pengujian dan perencanaan DR - Jadwalkan DR drill berkala — laksanakan pengujian restore end-to-end minimal setahun sekali atau setiap ada perubahan infrastruktur signifikan, dengan hasil terdokumentasi - Update BCDRP sesuai hasil DR drill — setiap temuan dari hasil DR drill wajib ditindaklanjuti dan didokumentasikan sebagai penyempurnaan dokumen BCDRP | AB50: Head of IT Operation - Infrastructure | AC50: 46387 | AD50: 46102 | AE50: (Belum seluruhnya dijalankan) | AL50: =Q50 -> 4 | AM50: =R50 -> 4 | AN50: =AL50*AM50 -> 16 | AO50: =_xlfn.IFNA(VLOOKUP(AN50,Parameter!$D$53:$E$77,2),"") -> SEDANG-TINGGI | AP50: New - Open
A51: IT | B51: =ROW()-ROW($B$14) -> 37 | C51: Disaster recovery backup strategy tanpa periodic testing terhadap actual restore capability pada alternative infrastructure mengakibatkan unvalidated recovery assumptions, potential backup corruption, dan unknown recovery time objective (RTO) achievement. | D51: Data Backup & Restore Point | E51: Information | F51: Strategis | G51: External | H51: Risiko | N51: Semua (C - I - A) | Q51: 1 | R51: 1 | S51: =Q51*R51 -> 1 | T51: =_xlfn.IFNA(VLOOKUP(S51,Parameter!$D$53:$E$77,2),"") -> RENDAH | V51: - | W51: - | X51: - | Y51: Data Management | AA51: - | AB51: - | AC51: 46387 | AD51: 46102 | AE51: - | AL51: =Q51 -> 1 | AM51: =R51 -> 1 | AN51: =AL51*AM51 -> 1 | AO51: =_xlfn.IFNA(VLOOKUP(AN51,Parameter!$D$53:$E$77,2),"") -> RENDAH | AP51: New - Open
A52: IT | B52: =ROW()-ROW($B$14) -> 38 | C52: Production data dump ke non-production environments (Development, UAT, SIT) tanpa data anonymization/masking exposing real personally identifiable information ke development personnel, expandingunnecessary data breach surface dan violating data minimization principle. | D52: Data Backup & Restore Point | E52: Information | F52: Strategis | G52: External | H52: Risiko | N52: Semua (C - I - A) | Q52: 1 | R52: 1 | S52: =Q52*R52 -> 1 | T52: =_xlfn.IFNA(VLOOKUP(S52,Parameter!$D$53:$E$77,2),"") -> RENDAH | V52: - | W52: - | X52: - | Y52: Data Management | AA52: - | AB52: - | AC52: 46387 | AD52: 46102 | AE52: - | AL52: =Q52 -> 1 | AM52: =R52 -> 1 | AN52: =AL52*AM52 -> 1 | AO52: =_xlfn.IFNA(VLOOKUP(AN52,Parameter!$D$53:$E$77,2),"") -> RENDAH | AP52: New - Open
A53: IT | B53: =ROW()-ROW($B$14) -> 39 | C53: Inadequate physical security controls memungkinkan unauthorized individuals melakukan piggybacking (mengekor personnel dengan valid access credential) untuk masuk ke critical infrastructure areas tanpa independent identity verification atau electronic access log. | D53: Data Center | E53: Information | F53: Strategis | G53: External | H53: Risiko | N53: Semua (C - I - A) | Q53: 1 | R53: 1 | S53: =Q53*R53 -> 1 | T53: =_xlfn.IFNA(VLOOKUP(S53,Parameter!$D$53:$E$77,2),"") -> RENDAH | V53: - | W53: - | X53: - | Y53: IT Infra - Sysadmin | Z53: DevSecOps | AA53: - | AB53: - | AC53: 46387 | AD53: 46102 | AE53: - | AL53: =Q53 -> 1 | AM53: =R53 -> 1 | AN53: =AL53*AM53 -> 1 | AO53: =_xlfn.IFNA(VLOOKUP(AN53,Parameter!$D$53:$E$77,2),"") -> RENDAH | AP53: New - Open
A54: IT | B54: =ROW()-ROW($B$14) -> 40 | C54: Physical data center infrastructure deficiencies (inadequate backup power (UPS), expired fire suppression system, failed environmental cooling, insufficient redundancy) menciptakan unmitigated vulnerability terhadap environmental hazards dan facility-level availability risk. | D54: Data Center | E54: Information | F54: Strategis | G54: External | H54: Risiko | N54: Semua (C - I - A) | Q54: 1 | R54: 1 | S54: =Q54*R54 -> 1 | T54: =_xlfn.IFNA(VLOOKUP(S54,Parameter!$D$53:$E$77,2),"") -> RENDAH | V54: - | W54: - | X54: - | Y54: IT Infra - Sysadmin | Z54: IT Infra - Network | AA54: - | AB54: - | AC54: 46387 | AD54: 46102 | AE54: - | AL54: =Q54 -> 1 | AM54: =R54 -> 1 | AN54: =AL54*AM54 -> 1 | AO54: =_xlfn.IFNA(VLOOKUP(AN54,Parameter!$D$53:$E$77,2),"") -> RENDAH | AP54: New - Open
A55: IT | B55: =ROW()-ROW($B$14) -> 41 | C55: Disaster Recovery Plan dan Business Continuity Plan existence tanpa periodic testing implementation menghasilkan unvalidated recovery assumptions, unknown actual recovery capability, dan undocumented failure modes dalam recovery procedure. | D55: Data Center | E55: Information | F55: Strategis | G55: External | H55: Risiko | N55: Semua (C - I - A) | Q55: 1 | R55: 1 | S55: =Q55*R55 -> 1 | T55: =_xlfn.IFNA(VLOOKUP(S55,Parameter!$D$53:$E$77,2),"") -> RENDAH | V55: - | W55: - | X55: - | Y55: IT Infrastructure (Head) | AA55: - | AB55: - | AC55: 46387 | AD55: 46102 | AE55: - | AL55: =Q55 -> 1 | AM55: =R55 -> 1 | AN55: =AL55*AM55 -> 1 | AO55: =_xlfn.IFNA(VLOOKUP(AN55,Parameter!$D$53:$E$77,2),"") -> RENDAH | AP55: New - Open
A56: IT | B56: =ROW()-ROW($B$14) -> 42 | C56: Excessive dependency terhadap vendor-specific security controls atau cloud-native security tools (AWS native security, GCP security services) tanpa multi-vendor redundancy atau portable security architecture menciptakan operational continuity risk jika cloud provider experiences outage atau policy change. | D56: Data Center | E56: Information | F56: Strategis | G56: External | H56: Risiko | N56: Semua (C - I - A) | Q56: 1 | R56: 1 | S56: =Q56*R56 -> 1 | T56: =_xlfn.IFNA(VLOOKUP(S56,Parameter!$D$53:$E$77,2),"") -> RENDAH | V56: - | W56: - | X56: - | Y56: IT Security Analyst | AA56: - | AB56: - | AC56: 46387 | AD56: 46102 | AE56: - | AL56: =Q56 -> 1 | AM56: =R56 -> 1 | AN56: =AL56*AM56 -> 1 | AO56: =_xlfn.IFNA(VLOOKUP(AN56,Parameter!$D$53:$E$77,2),"") -> RENDAH | AP56: New - Open
A57: IT | B57: =ROW()-ROW($B$14) -> 43 | C57: Ketiadaan dari independent third-party penetration testing dan red team exercise reliance solely pada internal security assessment menciptakan false confidence, missed external perspective terhadap attack vectors, dan lack dari adversarial thinking dalam security posture validation. | D57: Data Center | E57: Information | F57: Strategis | G57: External | H57: Risiko | N57: Semua (C - I - A) | Q57: 1 | R57: 1 | S57: =Q57*R57 -> 1 | T57: =_xlfn.IFNA(VLOOKUP(S57,Parameter!$D$53:$E$77,2),"") -> RENDAH | V57: - | W57: - | X57: - | Y57: IT Security Analyst | AA57: - | AB57: - | AC57: 46387 | AD57: 46102 | AE57: - | AL57: =Q57 -> 1 | AM57: =R57 -> 1 | AN57: =AL57*AM57 -> 1 | AO57: =_xlfn.IFNA(VLOOKUP(AN57,Parameter!$D$53:$E$77,2),"") -> RENDAH | AP57: New - Open
A58: IT | B58: =ROW()-ROW($B$14) -> 44 | C58: Triple extortion attack scenario dimana threat actor melakukan encryption ransom, organizational extortion, dan direct victim extortion (menghubungi high-value customers dengan direct threat terhadap sensitive personal medical data exposure) mengakibatkan compounded financial loss, reputational damage, dan customer trust erosion. | D58: Data Center | E58: Information | F58: Strategis | G58: External | H58: Risiko | N58: Semua (C - I - A) | Q58: 1 | R58: 1 | S58: =Q58*R58 -> 1 | T58: =_xlfn.IFNA(VLOOKUP(S58,Parameter!$D$53:$E$77,2),"") -> RENDAH | V58: - | W58: - | X58: - | Y58: IT Security Analyst | AA58: - | AB58: - | AC58: 46387 | AD58: 46102 | AE58: - | AL58: =Q58 -> 1 | AM58: =R58 -> 1 | AN58: =AL58*AM58 -> 1 | AO58: =_xlfn.IFNA(VLOOKUP(AN58,Parameter!$D$53:$E$77,2),"") -> RENDAH | AP58: New - Open
A59: IT | B59: =ROW()-ROW($B$14) -> 45 | C59: Data center maintenance report exposure mengungkapkan detailed infrastructure architecture, network device configuration, security system design, dan physical security controls yang dapat diexploitasi oleh threat actor untuk detailed facility reconnaissance dan identification dari security control weaknesses. | D59: Data Center | E59: Information | F59: Operasional | G59: Internal | H59: Risiko | Q59: 1 | R59: 1 | S59: =Q59*R59 -> 1 | T59: =_xlfn.IFNA(VLOOKUP(S59,Parameter!$D$53:$E$77,2),"") -> RENDAH | AC59: 46387 | AD59: 46102 | AL59: =Q59 -> 1 | AM59: =R59 -> 1 | AN59: =AL59*AM59 -> 1 | AO59: =_xlfn.IFNA(VLOOKUP(AN59,Parameter!$D$53:$E$77,2),"") -> RENDAH | AP59: New - Open
A60: IT | B60: =ROW()-ROW($B$14) -> 46 | C60: Infrastruktur IT on-premise yang sudah mendekati end-of-life berpotensi menimbulkan biaya pemeliharaan tinggi dan risiko kegagalan sistem — namun membuka peluang migrasi ke cloud yang meningkatkan skalabilitas, fleksibilitas, dan efisiensi biaya infrastruktur jangka panjang | D60: Data Center | E60: Information | F60: Operasional | G60: Internal | H60: Peluang | Q60: 1 | R60: 1 | S60: =Q60*R60 -> 1 | T60: =_xlfn.IFNA(VLOOKUP(S60,Parameter!$D$53:$E$77,2),"") -> RENDAH | AC60: 46387 | AD60: 46102 | AL60: =Q60 -> 1 | AM60: =R60 -> 1 | AN60: =AL60*AM60 -> 1 | AO60: =_xlfn.IFNA(VLOOKUP(AN60,Parameter!$D$53:$E$77,2),"") -> RENDAH | AP60: New - Open
A61: IT | B61: =ROW()-ROW($B$14) -> 47 | C61: Quality Assurance testing conduct menggunakan unmasked production data containing personally identifiable information (NIK, bank account, health data) dalam non-production environment tanpa data anonymization memungkinkan unauthorized PII exposure ke QA personnel dan test environment infrastructure. | D61: Data Dummy | E61: Information | F61: Strategis | G61: External | H61: Risiko | N61: Semua (C - I - A) | Q61: 1 | R61: 1 | S61: =Q61*R61 -> 1 | T61: =_xlfn.IFNA(VLOOKUP(S61,Parameter!$D$53:$E$77,2),"") -> RENDAH | V61: - | W61: - | X61: - | Y61: Quality Assurance | AA61: - | AB61: - | AC61: 46387 | AD61: 46102 | AE61: - | AL61: =Q61 -> 1 | AM61: =R61 -> 1 | AN61: =AL61*AM61 -> 1 | AO61: =_xlfn.IFNA(VLOOKUP(AN61,Parameter!$D$53:$E$77,2),"") -> RENDAH | AP61: New - Open
A62: IT | B62: =ROW()-ROW($B$14) -> 48 | C62: Penggunaan perangkat mobile pribadi oleh agen lapangan untuk menangkap dokumen sensitif pelanggan (Kartu Identitas Nasional, kartu kredit, hasil pemeriksaan medis) dengan konfigurasi automatic backup ke layanan cloud pribadi (Google Photos, iCloud) tanpa enkripsi atau kontrol akses memungkinkan eksposur data tidak sah terhadap infrastruktur penyimpanan cloud pihak ketiga. | D62: Data Internal Perusahaan | E62: Information | F62: Strategis | G62: External | H62: Risiko | N62: Semua (C - I - A) | Q62: 1 | R62: 1 | S62: =Q62*R62 -> 1 | T62: =_xlfn.IFNA(VLOOKUP(S62,Parameter!$D$53:$E$77,2),"") -> RENDAH | V62: - | W62: - | X62: - | Y62: IT Governance | AA62: - | AB62: - | AC62: 46387 | AD62: 46102 | AE62: - | AL62: =Q62 -> 1 | AM62: =R62 -> 1 | AN62: =AL62*AM62 -> 1 | AO62: =_xlfn.IFNA(VLOOKUP(AN62,Parameter!$D$53:$E$77,2),"") -> RENDAH | AP62: New - Open
A63: IT | B63: =ROW()-ROW($B$14) -> 49 | C63: Pengungkapan karyawan yang keluar dari organisasi terhadap aset intelektual proprietary (algoritma penetapan harga asuransi, formula underwriting, logika bisnis inti, kode sumber aplikasi) ke platform publik (GitHub, Kaggle) untuk keperluan portofolio pencarian kerja mengakibatkan kebocoran kekayaan intelektual dan eksposur intelijen kompetitif. | D63: Data Internal Perusahaan | E63: Information | F63: Strategis | G63: External | H63: Risiko | N63: Semua (C - I - A) | Q63: 1 | R63: 1 | S63: =Q63*R63 -> 1 | T63: =_xlfn.IFNA(VLOOKUP(S63,Parameter!$D$53:$E$77,2),"") -> RENDAH | V63: - | W63: - | X63: - | Y63: IT Governance | AA63: - | AB63: - | AC63: 46387 | AD63: 46102 | AE63: - | AL63: =Q63 -> 1 | AM63: =R63 -> 1 | AN63: =AL63*AM63 -> 1 | AO63: =_xlfn.IFNA(VLOOKUP(AN63,Parameter!$D$53:$E$77,2),"") -> RENDAH | AP63: New - Open
A64: IT | B64: =ROW()-ROW($B$14) -> 50 | C64: Penyalinan data klaim kesehatan nasabah yang berisi informasi kesehatan pribadi terhadap Model Bahasa Besar publik (ChatGPT versi gratis, Claude, Gemini) untuk keperluan ringkasan atau pembuatan rumus mengakibatkan transmisi data tidak terkontrol kepada penyedia layanan pihak ketiga tanpa perjanjian pemrosesan data. | D64: Data Internal Perusahaan | E64: Information | F64: Strategis | G64: External | H64: Risiko | N64: Semua (C - I - A) | Q64: 1 | R64: 1 | S64: =Q64*R64 -> 1 | T64: =_xlfn.IFNA(VLOOKUP(S64,Parameter!$D$53:$E$77,2),"") -> RENDAH | V64: - | W64: - | X64: - | Y64: IT Security Analyst | Z64: IT Governance | AA64: - | AB64: - | AC64: 46387 | AD64: 46102 | AE64: - | AL64: =Q64 -> 1 | AM64: =R64 -> 1 | AN64: =AL64*AM64 -> 1 | AO64: =_xlfn.IFNA(VLOOKUP(AN64,Parameter!$D$53:$E$77,2),"") -> RENDAH | AP64: New - Open
A65: IT | B65: =ROW()-ROW($B$14) -> 51 | C65: Unduhan data dalam jumlah besar yang berisi database prospek atau daftar nasabah oleh karyawan yang hendak keluar dari organisasi terhadap perangkat penyimpanan pribadi (USB flashdisk, hard drive eksternal) dengan tujuan untuk digunakan pada organisasi kompetitor mengakibatkan realisasi ancaman insider dan kehilangan aset intelektual. | D65: Data Internal Perusahaan | E65: Information | F65: Strategis | G65: External | H65: Risiko | N65: Semua (C - I - A) | Q65: 1 | R65: 1 | S65: =Q65*R65 -> 1 | T65: =_xlfn.IFNA(VLOOKUP(S65,Parameter!$D$53:$E$77,2),"") -> RENDAH | V65: - | W65: - | X65: - | Y65: IT Security Analyst | AA65: - | AB65: - | AC65: 46387 | AD65: 46102 | AE65: - | AL65: =Q65 -> 1 | AM65: =R65 -> 1 | AN65: =AL65*AM65 -> 1 | AO65: =_xlfn.IFNA(VLOOKUP(AN65,Parameter!$D$53:$E$77,2),"") -> RENDAH | AP65: New - Open
A66: IT | B66: =ROW()-ROW($B$14) -> 52 | C66: Penggunaan staf operasional terhadap alat shadow IT (aplikasi perpesanan pribadi WhatsApp, alat AI publik gratis) untuk memproses data rekam medis sensitif nasabah karena persepsi keterlambatan sistem internal mengakibatkan pemrosesan data yang tidak terkontrol melalui alat pihak ketiga yang tidak teruji. | D66: Data Internal Perusahaan | E66: Information | F66: Strategis | G66: External | H66: Risiko | N66: Semua (C - I - A) | Q66: 1 | R66: 1 | S66: =Q66*R66 -> 1 | T66: =_xlfn.IFNA(VLOOKUP(S66,Parameter!$D$53:$E$77,2),"") -> RENDAH | V66: - | W66: - | X66: - | Y66: IT Security Analyst | AA66: - | AB66: - | AC66: 46387 | AD66: 46102 | AE66: - | AL66: =Q66 -> 1 | AM66: =R66 -> 1 | AN66: =AL66*AM66 -> 1 | AO66: =_xlfn.IFNA(VLOOKUP(AN66,Parameter!$D$53:$E$77,2),"") -> RENDAH | AP66: New - Open
A67: IT | B67: =ROW()-ROW($B$14) -> 53 | C67: Non-kepatuhan terhadap kebijakan meja bersih dan prosedur kunci layar mengakibatkan dokumen sensitif terkait klaim bernilai tinggi tertinggal di area kerja yang tidak diawasi, atau perangkat laptop tetap menyala tanpa penguncian selama waktu istirahat karyawan, memungkinkan akses dan pengambilan dokumen oleh pihak tidak sah. | D67: Data Internal Perusahaan | E67: Information | F67: Strategis | G67: External | H67: Risiko | N67: Semua (C - I - A) | Q67: 1 | R67: 1 | S67: =Q67*R67 -> 1 | T67: =_xlfn.IFNA(VLOOKUP(S67,Parameter!$D$53:$E$77,2),"") -> RENDAH | V67: - | W67: - | X67: - | Y67: IT Security Analyst | AA67: - | AB67: - | AC67: 46387 | AD67: 46102 | AE67: - | AL67: =Q67 -> 1 | AM67: =R67 -> 1 | AN67: =AL67*AM67 -> 1 | AO67: =_xlfn.IFNA(VLOOKUP(AN67,Parameter!$D$53:$E$77,2),"") -> RENDAH | AP67: New - Open
A68: IT | B68: =ROW()-ROW($B$14) -> 54 | C68: Ketiadaan kontrol Data Loss Prevention (DLP) pada perangkat endpoint memungkinkan eksfiltrasi data tidak sah melalui salin-tempel data ke aplikasi berbasis web (WhatsApp Web, email pribadi), penyimpanan cloud pribadi, atau perangkat penyimpanan portable (USB flashdisk) tanpa deteksi atau pemblokiran sistem. | D68: Data Internal Perusahaan | E68: Information | F68: Strategis | G68: External | H68: Risiko | N68: Semua (C - I - A) | Q68: 1 | R68: 1 | S68: =Q68*R68 -> 1 | T68: =_xlfn.IFNA(VLOOKUP(S68,Parameter!$D$53:$E$77,2),"") -> RENDAH | V68: - | W68: - | X68: - | Y68: IT Security Analyst | AA68: - | AB68: - | AC68: 46387 | AD68: 46102 | AE68: - | AL68: =Q68 -> 1 | AM68: =R68 -> 1 | AN68: =AL68*AM68 -> 1 | AO68: =_xlfn.IFNA(VLOOKUP(AN68,Parameter!$D$53:$E$77,2),"") -> RENDAH | AP68: New - Open
A69: IT | B69: =ROW()-ROW($B$14) -> 55 | C69: Pertukaran data nasabah dalam skala besar terhadap pihak eksternal menggunakan protokol yang tidak aman atau usang (FTP tanpa enkripsi, SFTP tanpa verifikasi kunci, lampiran email dengan format terkompresi .zip dan kata sandi standar) tanpa mekanisme enkripsi komprehensif atau verifikasi integritas data. | D69: Data Internal Perusahaan | E69: Information | F69: Strategis | G69: External | H69: Risiko | N69: Semua (C - I - A) | Q69: 1 | R69: 1 | S69: =Q69*R69 -> 1 | T69: =_xlfn.IFNA(VLOOKUP(S69,Parameter!$D$53:$E$77,2),"") -> RENDAH | V69: - | W69: - | X69: - | Y69: IT Security Analyst | AA69: - | AB69: - | AC69: 46387 | AD69: 46102 | AE69: - | AL69: =Q69 -> 1 | AM69: =R69 -> 1 | AN69: =AL69*AM69 -> 1 | AO69: =_xlfn.IFNA(VLOOKUP(AN69,Parameter!$D$53:$E$77,2),"") -> RENDAH | AP69: New - Open
A70: IT | B70: =ROW()-ROW($B$14) -> 56 | C70: Akses agen asuransi terhadap sistem perusahaan kritis (portal penjualan, alat underwriting, database pelanggan) melalui perangkat mobile pribadi (smartphone, tablet) dengan kebijakan Bring Your Own Device (BYOD) tanpa mandat instalasi Mobile Device Management (MDM), enkripsi perangkat, atau mekanisme penghapusan data jarak jauh. | D70: Data Internal Perusahaan | E70: Information | F70: Strategis | G70: External | H70: Risiko | N70: Semua (C - I - A) | Q70: 1 | R70: 1 | S70: =Q70*R70 -> 1 | T70: =_xlfn.IFNA(VLOOKUP(S70,Parameter!$D$53:$E$77,2),"") -> RENDAH | V70: - | W70: - | X70: - | Y70: IT Security Analyst | AA70: - | AB70: - | AC70: 46387 | AD70: 46102 | AE70: - | AL70: =Q70 -> 1 | AM70: =R70 -> 1 | AN70: =AL70*AM70 -> 1 | AO70: =_xlfn.IFNA(VLOOKUP(AN70,Parameter!$D$53:$E$77,2),"") -> RENDAH | AP70: New - Open
A71: IT | B71: =ROW()-ROW($B$14) -> 57 | C71: Pelaksanaan rapat jarak jauh yang membahas informasi bisnis sensitif dan data kesehatan pribadi pelanggan bernilai tinggi (pejabat, selebriti) di ruang publik (kafe, ruang kerja bersama) tanpa perlengkapan privasi (headset untuk audio pribadi, privacy screen untuk layar perangkat) memungkinkan pendengar yang tidak sah (shoulder-surfing, eavesdropping) untuk mengakses informasi rahasia. | D71: Data Internal Perusahaan | E71: Information | F71: Strategis | G71: External | H71: Risiko | N71: Semua (C - I - A) | Q71: 1 | R71: 1 | S71: =Q71*R71 -> 1 | T71: =_xlfn.IFNA(VLOOKUP(S71,Parameter!$D$53:$E$77,2),"") -> RENDAH | V71: - | W71: - | X71: - | Y71: IT Security Analyst | AA71: - | AB71: - | AC71: 46387 | AD71: 46102 | AE71: - | AL71: =Q71 -> 1 | AM71: =R71 -> 1 | AN71: =AL71*AM71 -> 1 | AO71: =_xlfn.IFNA(VLOOKUP(AN71,Parameter!$D$53:$E$77,2),"") -> RENDAH | AP71: New - Open
A72: IT | B72: =ROW()-ROW($B$14) -> 58 | C72: Perjanjian kontrak dengan vendor penyedia layanan cloud atau administrator pihak ketiga (TPA rumah sakit) yang tidak mencakup klausul hak audit menghalangi organisasi untuk melakukan penilaian keamanan independen terhadap vendor, sehingga mengandalkan pernyataan keamanan vendor yang tidak terverifikasi. | D72: Data Internal Perusahaan | E72: Information | F72: Strategis | G72: External | H72: Risiko | N72: Semua (C - I - A) | Q72: 1 | R72: 1 | S72: =Q72*R72 -> 1 | T72: =_xlfn.IFNA(VLOOKUP(S72,Parameter!$D$53:$E$77,2),"") -> RENDAH | V72: - | W72: - | X72: - | Y72: IT Vendor/Supplier Management | Z72: IT Security Analyst | AA72: - | AB72: - | AC72: 46387 | AD72: 46102 | AE72: - | AL72: =Q72 -> 1 | AM72: =R72 -> 1 | AN72: =AL72*AM72 -> 1 | AO72: =_xlfn.IFNA(VLOOKUP(AN72,Parameter!$D$53:$E$77,2),"") -> RENDAH | AP72: New - Open
A73: IT | B73: =ROW()-ROW($B$14) -> 59 | C73: Berbagi data kesehatan pribadi nasabah terhadap mitra penyedia layanan (rumah sakit jaringan, administrator pihak ketiga, vendor percetakan polis) tanpa kesepakatan pemrosesan data (Data Processing Agreement) yang komprehensif sesuai persyaratan GDPR Pasal 28 atau Undang-Undang Perlindungan Data Pribadi menghasilkan kejelasan alokasi tanggung jawab yang tidak jelas dan perlindungan data kontraktual yang tidak memadai jika mitra mengalami pelanggaran keamanan. | D73: Data Internal Perusahaan | E73: Information | F73: Strategis | G73: External | H73: Risiko | N73: Semua (C - I - A) | Q73: 1 | R73: 1 | S73: =Q73*R73 -> 1 | T73: =_xlfn.IFNA(VLOOKUP(S73,Parameter!$D$53:$E$77,2),"") -> RENDAH | V73: - | W73: - | X73: - | Y73: IT Vendor/Supplier Management | AA73: - | AB73: - | AC73: 46387 | AD73: 46102 | AE73: - | AL73: =Q73 -> 1 | AM73: =R73 -> 1 | AN73: =AL73*AM73 -> 1 | AO73: =_xlfn.IFNA(VLOOKUP(AN73,Parameter!$D$53:$E$77,2),"") -> RENDAH | AP73: New - Open
A74: IT | B74: =ROW()-ROW($B$14) -> 60 | C74: Berbagi data kesehatan pribadi nasabah terhadap mitra penyedia layanan (rumah sakit jaringan, administrator pihak ketiga, vendor percetakan polis) tanpa kesepakatan pemrosesan data (Data Processing Agreement) yang komprehensif sesuai Undang-Undang Perlindungan Data Pribadi menghasilkan kejelasan alokasi tanggung jawab yang tidak jelas dan perlindungan data kontraktual yang tidak memadai jika mitra mengalami pelanggaran keamanan. | D74: Data Internal Perusahaan | E74: Information | F74: Strategis | G74: External | H74: Risiko | N74: Semua (C - I - A) | Q74: 1 | R74: 1 | S74: =Q74*R74 -> 1 | T74: =_xlfn.IFNA(VLOOKUP(S74,Parameter!$D$53:$E$77,2),"") -> RENDAH | V74: - | W74: - | X74: - | Y74: IT Vendor/Supplier Management | AA74: - | AB74: - | AC74: 46387 | AD74: 46102 | AE74: - | AL74: =Q74 -> 1 | AM74: =R74 -> 1 | AN74: =AL74*AM74 -> 1 | AO74: =_xlfn.IFNA(VLOOKUP(AN74,Parameter!$D$53:$E$77,2),"") -> RENDAH | AP74: New - Open
A75: IT | B75: =ROW()-ROW($B$14) -> 61 | C75: Container Image Rentan: Menggunakan base image Docker yang usang atau sudah disusupi malware sebelum di-deploy ke Environment Testing dan production. | D75: Data list environment (Container Images) | E75: Software | F75: Operasional | G75: Internal | H75: Risiko | I75: Tidak adanya kebijakan wajib penggunaan base image yang terverifikasi dan up-to-date; | J75: Deployment malware ke environment production, eksploitasi kerentanan pada container, lateral movement antar container, gangguan layanan, hingga kebocoran data | K75: Supply chain attack melalui base image berbahaya, eksploitasi CVE pada image usang, malware yang sudah tertanam sebelum image digunakan | L75: Tidak ada kebijakan minimum standard base image; image usang masih bisa di-deploy tanpa hambatan otomatis | M75: Trivy sudah terinstalasi dan terintegrasi di CI/CD pipeline, namun hasil scanning tidak memblokir pipeline secara otomatis | N75: Semua (C - I - A) | O75: 8.1 – Perencanaan dan pengendalian operasional | P75: A.8.8 – Manajemen kerentanan teknis; A.8.25 – Siklus hidup pengembangan yang aman | Q75: 4 | R75: 4 | S75: =Q75*R75 -> 16 | T75: =_xlfn.IFNA(VLOOKUP(S75,Parameter!$D$53:$E$77,2),"") -> SEDANG-TINGGI | U75: Rendah — organisasi tidak bersedia men-deploy container image yang mengandung kerentanan atau malware ke environment manapun, karena dapat mengkompromi seluruh infrastruktur production | V75: Sedang — organisasi masih dapat beroperasi selama nilai risiko residual ≤ 12; jika residual masih >12, wajib eskalasi segera | W75: Isolasi container terdampak segera; rollback ke image versi bersih; forensik untuk identifikasi apakah malware sudah aktif; audit seluruh container yang menggunakan image yang sama; notifikasi jika ada data terdampak | X75: Jadikan Trivy sebagai gatekeeper wajib (pipeline gagal otomatis jika ditemukan CVE Critical/High); kebijakan penggunaan base image resmi dan terverifikasi; image registry internal dengan whitelist base image yang diizinkan; update base image secara berkala | Y75: DevSecOps | AA75: - Jadikan Trivy sebagai gatekeeper — pipeline otomatis gagal dan tidak bisa naik production jika ditemukan CVE severity Critical atau High - Buat internal image registry — simpan dan kelola base image yang sudah diverifikasi secara terpusat, developer wajib menarik dari sini - Implementasi image signing (Cosign/Notary) — hanya image yang sudah ditandatangani dan terverifikasi yang boleh di-deploy | AB75: Personel DevSecOps | AC75: 46387 | AD75: 46102 | AE75: Belum turun — Trivy yang sudah ada hanya memberi visibilitas (tahu ada kerentanan), tapi tidak mencegah image rentan naik production. Tanpa gatekeeper, temuan Trivy bisa diabaikan | AL75: =Q75 -> 4 | AM75: 3 | AN75: =AL75*AM75 -> 12 | AO75: =_xlfn.IFNA(VLOOKUP(AN75,Parameter!$D$53:$E$77,2),"") -> SEDANG | AP75: New - Open
A76: IT | B76: =ROW()-ROW($B$14) -> 62 | C76: Implementasi masking data hanya pada layer database tanpa perlindungan komprehensif pada log aplikasi, parameter URL, respons API, pesan kesalahan, dan buku besar transaksi mengakibatkan eksposur data sensitif pada saluran tidak terenkripsi dan sistem agregasi log. | D76: Database Core System | E76: Information | F76: Strategis | G76: External | H76: Risiko | N76: Semua (C - I - A) | Q76: 1 | R76: 1 | S76: =Q76*R76 -> 1 | T76: =_xlfn.IFNA(VLOOKUP(S76,Parameter!$D$53:$E$77,2),"") -> RENDAH | V76: - | W76: - | X76: - | Y76: Data Management | Z76: IT Security Analyst | AA76: - | AB76: - | AC76: 46387 | AD76: 46102 | AE76: - | AL76: =Q76 -> 1 | AM76: =R76 -> 1 | AN76: =AL76*AM76 -> 1 | AO76: =_xlfn.IFNA(VLOOKUP(AN76,Parameter!$D$53:$E$77,2),"") -> RENDAH | AP76: New - Open
A77: IT | B77: =ROW()-ROW($B$14) -> 63 | C77: Eksekusi kueri analitik yang tidak dioptimalkan (pemindaian tabel penuh, penggabungan tanpa indeks, agregasi berat) secara langsung terhadap basis data transaksi online produksi tanpa optimasi kueri, throttling sumber daya, atau pemisahan ke basis data analitik mengakibatkan penurunan performa sistem pemrosesan transaksi online. | D77: Database Core System | E77: Information | F77: Strategis | G77: External | H77: Risiko | N77: Semua (C - I - A) | Q77: 1 | R77: 1 | S77: =Q77*R77 -> 1 | T77: =_xlfn.IFNA(VLOOKUP(S77,Parameter!$D$53:$E$77,2),"") -> RENDAH | V77: - | W77: - | X77: - | Y77: Data Management | AA77: - | AB77: - | AC77: 46387 | AD77: 46102 | AE77: - | AL77: =Q77 -> 1 | AM77: =R77 -> 1 | AN77: =AL77*AM77 -> 1 | AO77: =_xlfn.IFNA(VLOOKUP(AN77,Parameter!$D$53:$E$77,2),"") -> RENDAH | AP77: New - Open
A78: IT | B78: =ROW()-ROW($B$14) -> 64 | C78: Perbedaan konfigurasi (configuration drift) antara basis data primer dan replika/infrastruktur pemulihan bencana disebabkan oleh prosedur pembaruan yang tidak terkoordinasi menghasilkan jeda replikasi yang tidak diketahui, perbedaan fitur yang tidak terdokumentasi, dan potensi inkonsistensi data yang ditemukan selama acara failover. | D78: Database Core System | E78: Information | F78: Strategis | G78: External | H78: Risiko | N78: Semua (C - I - A) | Q78: 1 | R78: 1 | S78: =Q78*R78 -> 1 | T78: =_xlfn.IFNA(VLOOKUP(S78,Parameter!$D$53:$E$77,2),"") -> RENDAH | V78: - | W78: - | X78: - | Y78: Data Management | AA78: - | AB78: - | AC78: 46387 | AD78: 46102 | AE78: - | AL78: =Q78 -> 1 | AM78: =R78 -> 1 | AN78: =AL78*AM78 -> 1 | AO78: =_xlfn.IFNA(VLOOKUP(AN78,Parameter!$D$53:$E$77,2),"") -> RENDAH | AP78: New - Open
A79: IT | B79: =ROW()-ROW($B$14) -> 65 | C79: Ketiadaan klasifikasi data eksplisit dan spesifikasi persyaratan enkripsi pada tingkat kolom basis data, dipadukan dengan kekurangan validasi QA terhadap implementasi enkripsi saat istirahat (encryption at rest) mengakibatkan penyimpanan data sensitif tanpa enkripsi pada basis data. | D79: Database Core System | E79: Information | F79: Strategis | G79: External | H79: Risiko | N79: Semua (C - I - A) | Q79: 1 | R79: 1 | S79: =Q79*R79 -> 1 | T79: =_xlfn.IFNA(VLOOKUP(S79,Parameter!$D$53:$E$77,2),"") -> RENDAH | V79: - | W79: - | X79: - | Y79: Quality Assurance | AA79: - | AB79: - | AC79: 46387 | AD79: 46102 | AE79: - | AL79: =Q79 -> 1 | AM79: =R79 -> 1 | AN79: =AL79*AM79 -> 1 | AO79: =_xlfn.IFNA(VLOOKUP(AN79,Parameter!$D$53:$E$77,2),"") -> RENDAH | AP79: New - Open
A80: IT | B80: =ROW()-ROW($B$14) -> 66 | C80: Informasi infrastruktur basis data yang diungkapkan atau mudah disimpulkan (produk basis data, port pendengaran, metode autentikasi, lokasi jaringan) memungkinkan ancaman siber melakukan upaya koneksi basis data langsung yang ditargetkan menggunakan pemecahan kata sandi kredensial atau eksploitasi kredensial default. | D80: Database Management Tools | E80: Information | F80: Operasional | G80: Internal | H80: Risiko | Q80: 1 | R80: 1 | S80: =Q80*R80 -> 1 | T80: =_xlfn.IFNA(VLOOKUP(S80,Parameter!$D$53:$E$77,2),"") -> RENDAH | AC80: 46387 | AD80: 46102 | AL80: =Q80 -> 1 | AM80: =R80 -> 1 | AN80: =AL80*AM80 -> 1 | AO80: =_xlfn.IFNA(VLOOKUP(AN80,Parameter!$D$53:$E$77,2),"") -> RENDAH | AP80: New - Open
A81: IT | B81: =ROW()-ROW($B$14) -> 67 | C81: Infrastruktur penyimpanan cadangan dengan postur keamanan yang lebih rendah dibandingkan sistem produksi (enkripsi tidak memadai, kontrol akses permisif, akses tanpa pemantauan) memungkinkan ancaman siber menargetkan cadangan untuk injeksi malware atau pengracunan, memungkinkan kompromi persisten melalui proses pemulihan. | D81: Database Non Core System | E81: Information | F81: Operasional | G81: Internal | H81: Risiko | Q81: 1 | R81: 1 | S81: =Q81*R81 -> 1 | T81: =_xlfn.IFNA(VLOOKUP(S81,Parameter!$D$53:$E$77,2),"") -> RENDAH | AC81: 46387 | AD81: 46102 | AL81: =Q81 -> 1 | AM81: =R81 -> 1 | AN81: =AL81*AM81 -> 1 | AO81: =_xlfn.IFNA(VLOOKUP(AN81,Parameter!$D$53:$E$77,2),"") -> RENDAH | AP81: New - Open
A82: IT | B82: =ROW()-ROW($B$14) -> 68 | C82: Prosedur pemulihan bencana dan lokasi infrastruktur pemulihan yang dipublikasikan atau mudah ditemukan memungkinkan ancaman siber merencanakan waktu serangan terhadap proses pemulihan ketika sistem beroperasi dalam keadaan terdegradasi dengan efektivitas kontrol keamanan yang berkurang. | D82: Database Non Core System | E82: Information | F82: Operasional | G82: Internal | H82: Risiko | Q82: 1 | R82: 1 | S82: =Q82*R82 -> 1 | T82: =_xlfn.IFNA(VLOOKUP(S82,Parameter!$D$53:$E$77,2),"") -> RENDAH | AC82: 46387 | AD82: 46102 | AL82: =Q82 -> 1 | AM82: =R82 -> 1 | AN82: =AL82*AM82 -> 1 | AO82: =_xlfn.IFNA(VLOOKUP(AN82,Parameter!$D$53:$E$77,2),"") -> RENDAH | AP82: New - Open
A83: IT | B83: =ROW()-ROW($B$14) -> 69 | C83: Pengungkapan string koneksi basis data atau informasi endpoint (hardcoded dalam kode sumber, terlihat dalam log, terekspos melalui pesan kesalahan API) memungkinkan ancaman siber membuat koneksi basis data langsung, melewati kontrol keamanan layer aplikasi dan mekanisme autentikasi. | D83: Dokumen Arsitektur Data | E83: Information | F83: Operasional | G83: Internal | H83: Risiko | Q83: 1 | R83: 1 | S83: =Q83*R83 -> 1 | T83: =_xlfn.IFNA(VLOOKUP(S83,Parameter!$D$53:$E$77,2),"") -> RENDAH | AC83: 46387 | AD83: 46102 | AL83: =Q83 -> 1 | AM83: =R83 -> 1 | AN83: =AL83*AM83 -> 1 | AO83: =_xlfn.IFNA(VLOOKUP(AN83,Parameter!$D$53:$E$77,2),"") -> RENDAH | AP83: New - Open
A84: IT | B84: =ROW()-ROW($B$14) -> 70 | C84: Pemahaman lengkap terhadap arsitektur data (desain skema, hubungan tabel, lokasi data, lokasi cadangan, tujuan pengarsipan) memungkinkan ancaman siber merancang strategi eksfiltrasi data yang efisien, memprioritaskan data bernilai tinggi terhadap waktu ekstraksi terbatas, dan mengidentifikasi cadangan untuk kompromi. | D84: Dokumen Arsitektur Data | E84: Information | F84: Operasional | G84: Internal | H84: Risiko | Q84: 1 | R84: 1 | S84: =Q84*R84 -> 1 | T84: =_xlfn.IFNA(VLOOKUP(S84,Parameter!$D$53:$E$77,2),"") -> RENDAH | AC84: 46387 | AD84: 46102 | AL84: =Q84 -> 1 | AM84: =R84 -> 1 | AN84: =AL84*AM84 -> 1 | AO84: =_xlfn.IFNA(VLOOKUP(AN84,Parameter!$D$53:$E$77,2),"") -> RENDAH | AP84: New - Open
A85: IT | B85: =ROW()-ROW($B$14) -> 71 | C85: Standar pengerasan basis data yang dipublikasikan dan baseline konfigurasi yang diketahui memungkinkan ancaman siber mengidentifikasi sistem yang tidak mematuhi standar, komponen yang sudah usang tanpa patch, atau deviasi kontrol keamanan terhadap baseline standar. | D85: Dokumen Baseline Hardening | E85: Information | F85: Operasional | G85: Internal | H85: Risiko | Q85: 1 | R85: 1 | S85: =Q85*R85 -> 1 | T85: =_xlfn.IFNA(VLOOKUP(S85,Parameter!$D$53:$E$77,2),"") -> RENDAH | AC85: 46387 | AD85: 46102 | AL85: =Q85 -> 1 | AM85: =R85 -> 1 | AN85: =AL85*AM85 -> 1 | AO85: =_xlfn.IFNA(VLOOKUP(AN85,Parameter!$D$53:$E$77,2),"") -> RENDAH | AP85: New - Open
A86: IT | B86: =ROW()-ROW($B$14) -> 72 | C86: Pengungkapan dokumentasi rencana kontinuitas bisnis dan pemulihan bencana terhadap lokasi infrastruktur cadangan, detail situs pemulihan, dan prosedur failover memungkinkan ancaman siber merencanakan serangan komprehensif terhadap sistem primer dan cadangan untuk dampak bisnis maksimal. | D86: Dokumen BCDRP Plan & Scenario | E86: Information | F86: Operasional | G86: Internal | H86: Risiko | Q86: 1 | R86: 1 | S86: =Q86*R86 -> 1 | T86: =_xlfn.IFNA(VLOOKUP(S86,Parameter!$D$53:$E$77,2),"") -> RENDAH | AC86: 46387 | AD86: 46102 | AL86: =Q86 -> 1 | AM86: =R86 -> 1 | AN86: =AL86*AM86 -> 1 | AO86: =_xlfn.IFNA(VLOOKUP(AN86,Parameter!$D$53:$E$77,2),"") -> RENDAH | AP86: New - Open
A87: IT | B87: =ROW()-ROW($B$14) -> 73 | C87: Eksploitasi endpoint API integrasi pihak ketiga yang terbuka tanpa autentikasi memadai berpotensi mengakibatkan akses tidak terotorisasi, kebocoran data, dan penyalahgunaan layanan — akibat tidak adanya persyaratan autentikasi kuat dalam BRD dan tidak diverifikasinya keamanan endpoint dalam proses QA | D87: Dokumen BRD, FSD, & User Story | E87: Information | F87: Operasional | G87: External | H87: Risiko | I87: BA tidak mendefinisikan standar autentikasi dan keamanan sebagai persyaratan wajib dalam integrasi API pihak ketiga; gap knowledge BA dan QA terkait standar keamanan API seperti OAuth2, API key management, dan token validation; QA tidak memiliki skenario pengujian untuk memverifikasi apakah endpoint terbuka secara publik tanpa autentikasi | J87: Endpoint API terbuka tanpa autentikasi yang memadai dan dapat diakses publik; potensi eksploitasi berupa pencurian data, penyalahgunaan layanan, dan injeksi data palsu melalui endpoint yang tidak terproteksi; potensi pelanggaran kepatuhan regulasi akibat data nasabah terekspos melalui API yang tidak aman; kerugian finansial dan reputasi akibat insiden yang bersumber dari endpoint tidak terproteksi | K87: Eksploitasi endpoint API publik tanpa autentikasi oleh pihak tidak berwenang; pencurian data melalui API yang tidak terproteksi; serangan injection melalui endpoint yang terbuka; penyalahgunaan layanan melalui akses API tanpa kontrol autentikasi | L87: Tidak ada standar autentikasi API yang terdefinisi dalam requirement; endpoint API tidak diuji keamanannya sebelum diloloskan ke production; tidak ada kebijakan minimum security standard untuk integrasi API pihak ketiga; gap knowledge BA dan QA terkait keamanan API | M87: Belum terdapat pengendalian formal yang diterapkan. Persyaratan autentikasi dan keamanan pada integrasi API dengan pihak ketiga belum didefinisikan sebagai komponen wajib dalam proses requirement gathering, dan pengujian keamanan endpoint API belum diintegrasikan sebagai skenario pengujian wajib dalam proses Quality Assurance | N87: Semua (C - I - A) | O87: 8.1 – Perencanaan dan pengendalian operasional; 7.2 – Kompetensi | P87: A.8.24 – Penggunaan kriptografi; A.8.25 – Siklus hidup pengembangan yang aman; A.8.26 – Persyaratan keamanan aplikasi; A.5.19 – Keamanan informasi dalam hubungan pemasok | Q87: 4 | R87: 5 | S87: =Q87*R87 -> 20 | T87: =_xlfn.IFNA(VLOOKUP(S87,Parameter!$D$53:$E$77,2),"") -> TINGGI | U87: Rendah — perusahaan tidak bersedia membiarkan endpoint API integrasi pihak ketiga beroperasi tanpa autentikasi yang memadai, mengingat dampaknya langsung pada kerahasiaan data nasabah, integritas sistem, dan pemenuhan kewajiban keamanan regulasi | V87: Sedang — perusahaan masih dapat beroperasi selama nilai risiko residual ≤ 9; jika residual masih >9, wajib eskalasi ke manajemen. Sebagai syarat minimum toleransi, organisasi wajib memastikan telah tersedia: (1) standar minimum autentikasi API yang terdokumentasi dan terintegrasi sebagai komponen wajib BRD untuk setiap integrasi pihak ketiga, (2) skenario pengujian keamanan endpoint API yang terdokumentasi dalam standar test case QA, dan (3) security review retroaktif telah dilaksanakan terhadap seluruh endpoint API yang sudah berjalan di production | W87: Lakukan audit segera terhadap seluruh endpoint API production untuk mengidentifikasi yang terbuka tanpa autentikasi; blokir sementara endpoint yang tidak terproteksi hingga mekanisme autentikasi diimplementasikan; koordinasikan dengan vendor pihak ketiga untuk penerapan autentikasi yang memadai; dokumentasikan temuan sebagai dasar remediation plan | X87: Integrasikan standar autentikasi API sebagai komponen wajib dalam BRD untuk setiap integrasi pihak ketiga; tambahkan skenario pengujian keamanan endpoint ke dalam standar test case QA; selenggarakan pelatihan keamanan API untuk BA dan QA | Y87: Business Analyst | AA87: - Definisikan dan integrasikan standar minimum autentikasi API ke dalam BRD — buat standar yang mewajibkan penggunaan mekanisme autentikasi kuat seperti OAuth2, API key management, atau token-based authentication untuk setiap integrasi API pihak ketiga; jadikan sebagai komponen wajib yang harus terdefinisi sebelum BRD dapat disetujui - Tambahkan skenario pengujian keamanan endpoint ke dalam standar test case QA — definisikan skenario wajib yang memverifikasi bahwa tidak ada endpoint yang dapat diakses publik tanpa autentikasi yang memadai, mencakup pengujian akses tanpa token, token tidak valid, dan token kadaluarsa - Lakukan security review retroaktif terhadap seluruh endpoint API production — identifikasi endpoint yang terbuka tanpa autentikasi memadai, blokir sementara yang berisiko tinggi, dan koordinasikan dengan vendor pihak ketiga untuk implementasi autentikasi sesuai standar yang ditetapkan - Selenggarakan pelatihan keamanan API untuk BA dan QA — program pelatihan mencakup standar keamanan API (OWASP API Security Top 10), teknik mendefinisikan autentikasi requirement yang kuat, dan metode pengujian keamanan endpoint yang komprehensif | AB87: Personel Business Analyst berkoordinasi dengan Personel Quality Assurance dan Personel Security Analyst | AC87: 46387 | AD87: 46102 | AE87: Belum ada pengendalian yang berjalan sama sekali terkait security requirement autentikasi API dan pengujian keamanan endpoint, risiko masih terbuka penuh pada level Tinggi dengan probabilitas sangat tinggi, status New - Open dan menjadi prioritas utama untuk segera didefinisikan standar autentikasi API dan diintegrasikan ke dalam BRD serta standar test case QA | AL87: =Q87 -> 4 | AM87: =R87 -> 5 | AN87: =AL87*AM87 -> 20 | AO87: =_xlfn.IFNA(VLOOKUP(AN87,Parameter!$D$53:$E$77,2),"") -> TINGGI | AP87: New - Open
A88: IT | B88: =ROW()-ROW($B$14) -> 74 | C88: Kerentanan keamanan pada tahap requirement gathering dan pengujian aplikasi berpotensi lolos tanpa terdeteksi dan masuk ke lingkungan produks | D88: Dokumen BRD, FSD, & User Story | E88: Information | F88: Operasional | G88: Internal | H88: Risiko | I88: Standar kualifikasi dan kompetensi personil BA dan QA tidak mencakup aspek keamanan informasi; tidak adanya program pelatihan keamanan dasar seperti OWASP Top 10 dan prinsip Secure Design; proses bisnis yang belum terdefinisi dengan jelas mempersulit identifikasi kebutuhan keamanan sejak tahap awal; keterbatasan personil yang menghalangi alokasi waktu untuk pengembangan kompetensi keamanan | J88: Persyaratan keamanan tidak terdefinisi sejak tahap requirement; kerentanan aplikasi tidak teridentifikasi dalam proses pengujian; celah keamanan lolos ke environment production tanpa terdeteksi; peningkatan biaya remediasi akibat kerentanan yang ditemukan setelah release; potensi eksploitasi kerentanan yang berdampak pada data nasabah | K88: Kerentanan OWASP Top 10 yang tidak teridentifikasi sejak tahap desain; celah keamanan yang lolos dalam proses QA; pengembangan fitur yang secara inheren tidak aman akibat tidak adanya security requirement; eksploitasi celah keamanan pada aplikasi production | L88: Tidak ada standar kompetensi keamanan dalam kualifikasi BA dan QA; tidak ada program pelatihan keamanan yang diselenggarakan; prinsip Secure Design belum diintegrasikan ke dalam proses requirement dan testing; tidak ada security checklist atau security test case dalam proses QA | M88: Belum terdapat pengendalian formal yang diterapkan. Persyaratan kompetensi keamanan informasi belum diintegrasikan ke dalam standar kualifikasi, proses kerja, maupun program pengembangan kompetensi bagi personil Business Analyst dan Quality Assurance | N88: Kerahasiaan [C] + Keutuhan [I] | O88: 7.2 – Kompetensi; 7.3 – Kesadaran; 8.1 – Perencanaan dan pengendalian operasional | P88: A.6.3 – Kesadaran, pendidikan dan pelatihan keamanan informasi; A.8.25 – Siklus hidup pengembangan yang aman; A.8.26 – Persyaratan keamanan aplikasi | Q88: 3 | R88: 5 | S88: =Q88*R88 -> 15 | T88: =_xlfn.IFNA(VLOOKUP(S88,Parameter!$D$53:$E$77,2),"") -> SEDANG-TINGGI | U88: Rendah — perusahaan tidak bersedia membiarkan proses requirement dan pengujian aplikasi berjalan tanpa kompetensi keamanan dasar mengingat celah yang dihasilkan berpotensi langsung berdampak pada keamanan data nasabah dan integritas aplikasi production | V88: Sedang — perusahaan masih dapat beroperasi selama nilai risiko residual ≤ 9; jika residual masih >9, wajib eskalasi ke manajemen untuk alokasi program pelatihan dan integrasi security requirement secara segera | W88: Lakukan security review menyeluruh terhadap requirement dan test case yang sudah berjalan; identifikasi celah keamanan yang berpotensi sudah lolos ke production; jadwalkan penetration testing untuk memvalidasi kondisi keamanan aplikasi yang ada; dokumentasikan temuan sebagai justifikasi urgensi program pelatihan | X88: Integrasikan standar kompetensi keamanan informasi ke dalam kualifikasi dan job description BA dan QA; selenggarakan program pelatihan keamanan dasar mencakup OWASP Top 10 dan prinsip Secure Design; integrasikan security requirement dan security test case ke dalam proses kerja standar | Y88: Business Analyst | Z88: Quality Assurance | AA88: - Integrasikan standar kompetensi keamanan ke dalam job description BA dan QA — tambahkan persyaratan pemahaman keamanan dasar seperti OWASP Top 10 sebagai kompetensi yang diharapkan dalam standar kualifikasi - Selenggarakan pelatihan keamanan dasar untuk BA dan QA — program pelatihan yang mencakup OWASP Top 10, prinsip Secure Design, dan identifikasi security requirement sejak tahap awal pengembangan - Susun security requirement template — buat template standar yang memandu BA dalam mendefinisikan persyaratan keamanan pada setiap fitur atau proses bisnis yang dikembangkan - Implementasi security test case dalam proses QA — integrasikan skenario pengujian keamanan berbasis OWASP Top 10 sebagai bagian wajib dari test case yang disusun oleh QA - Libatkan Security Analyst dalam proses requirement review — pastikan setiap requirement yang melibatkan data sensitif atau fungsi kritis direview oleh Personel Security Analyst sebelum disetujui - Jadwalkan refreshment pelatihan keamanan berkala — selenggarakan update pelatihan minimal tahunan untuk memastikan kompetensi keamanan BA dan QA tetap relevan dengan perkembangan ancaman terkini | AB88: Personel IT Governance berkoordinasi dengan Personel Business Analyst, Personel Quality Assurance, dan Personel Security Analyst | AC88: 46387 | AD88: 46102 | AE88: Belum ada pengendalian yang berjalan sama sekali terkait kompetensi keamanan pada BA dan QA, risiko masih terbuka penuh pada level Tinggi dengan probabilitas sangat tinggi, status New - Open dan menjadi prioritas untuk segera diimplementasikan program pelatihan keamanan dasar dan security checklist dalam proses kerja | AL88: =Q88 -> 3 | AM88: =R88 -> 5 | AN88: =AL88*AM88 -> 15 | AO88: =_xlfn.IFNA(VLOOKUP(AN88,Parameter!$D$53:$E$77,2),"") -> SEDANG-TINGGI | AP88: New - Open
A89: IT | B89: =ROW()-ROW($B$14) -> 75 | C89: Kegagalan validasi fitur secara objektif dan potensi penerimaan deliverable yang tidak memenuhi standar kualitas berpotensi terjadi akibat acceptance criteria yang ditulis menggunakan deskripsi kualitatif tanpa parameter ukur yang terdefinisi, | D89: Dokumen BRD, FSD, & User Story | E89: Information | F89: Operasional | G89: Internal | H89: Risiko | I89: Pengguna belum memahami cara menyusun acceptance criteria yang terukur dan dapat diverifikasi; tidak adanya panduan teknis pengisian acceptance criteria yang terstruktur; BA belum secara konsisten memfasilitasi pengguna dalam mendefinisikan acceptance criteria yang objektif dan berbasis parameter ukur yang jelas | J89: Pemenuhan requirement tidak dapat diverifikasi secara objektif dalam proses pengujian; potensi penerimaan deliverable yang secara fungsional tidak memenuhi kebutuhan bisnis sesungguhnya; dispute antara tim IT dan unit bisnis terkait apakah suatu fitur dinyatakan selesai atau tidak; potensi rework yang memboroskan sumber daya akibat ekspektasi yang tidak terdefinisi sejak awal | K89: Penerimaan fitur yang tidak memenuhi kebutuhan bisnis akibat acceptance criteria yang tidak dapat diukur; dispute berkepanjangan antara IT dan unit bisnis; rework berulang akibat ekspektasi yang berbeda antara developer, QA, dan user; kegagalan UAT yang tidak terstruktur | L89: Panduan pengisian acceptance criteria yang terstruktur belum tersedia; pengguna tidak memiliki pemahaman tentang cara menyusun acceptance criteria yang terukur; BA belum secara konsisten membantu user dalam mendefinisikan parameter ukur yang objektif; tidak ada mekanisme validasi kualitas acceptance criteria sebelum BRD disetujui | M89: Formulir Business Requirement telah mencantumkan kolom acceptance criteria sebagai komponen standar dokumen; namun panduan pengisian yang terstruktur belum tersedia dan pemahaman pengguna mengenai cara penyusunan acceptance criteria yang terukur masih sangat terbatas | N89: Keutuhan [I] + Ketersediaan [A] | O89: 7.5 – Informasi terdokumentasi; 8.1 – Perencanaan dan pengendalian operasional | P89: A.5.37 – Prosedur operasi yang terdokumentasi; A.8.25 – Siklus hidup pengembangan yang aman; A.8.26 – Persyaratan keamanan aplikasi | Q89: 3 | R89: 4 | S89: =Q89*R89 -> 12 | T89: =_xlfn.IFNA(VLOOKUP(S89,Parameter!$D$53:$E$77,2),"") -> SEDANG | U89: Sedang — perusahaan dapat mentolerir acceptance criteria yang belum sempurna dalam jangka pendek selama mekanisme konfirmasi berjalan, namun tidak bersedia membiarkan kondisi ini berlanjut mengingat dampaknya pada kualitas deliverable dan efisiensi sumber daya development | V89: Sedang — perusahaan masih dapat beroperasi selama nilai risiko residual ≤ 6; jika residual masih >6, wajib eskalasi untuk penyusunan panduan acceptance criteria dan penyelenggaraan pelatihan bagi user secara segera | W89: Lakukan review terhadap acceptance criteria pada seluruh project yang sedang berjalan; fasilitasi sesi klarifikasi terstruktur antara BA dan user untuk mendefinisikan ulang acceptance criteria yang ambigu menjadi parameter ukur yang objektif; tunda UAT hingga acceptance criteria diperjelas dan disepakati oleh kedua pihak | X89: Susun panduan teknis pengisian acceptance criteria dengan contoh konkret yang membedakan kriteria kualitatif yang tidak terukur dengan kriteria kuantitatif yang dapat diverifikasi; implementasi mekanisme validasi kualitas acceptance criteria sebelum BRD disetujui; tingkatkan kompetensi BA dalam memfasilitasi definisi acceptance criteria yang terukur | Y89: Business Analyst | AA89: - Susun panduan teknis pengisian acceptance criteria — dokumen panduan yang memberikan contoh konkret perbedaan antara kriteria kualitatif yang tidak terukur dengan kriteria kuantitatif yang dapat diverifikasi, dilengkapi template yang siap pakai - Selenggarakan pelatihan pengisian acceptance criteria bagi user — workshop atau sesi edukasi yang membekali pengguna dengan kemampuan mendefinisikan acceptance criteria yang terukur, spesifik, dan dapat diuji - Integrasikan validasi acceptance criteria ke dalam gate review SDLC — pastikan acceptance criteria yang terukur menjadi syarat wajib yang harus terpenuhi sebelum project dapat melanjutkan ke tahap development - Jadwalkan review kualitas BRD secara berkala — lakukan sampling review terhadap BRD yang dihasilkan untuk memastikan konsistensi kualitas acceptance criteria sesuai standar yang ditetapkan | AB89: Personel Business Analyst berkoordinasi dengan Personel Quality Assurance dan Personel IT Governance | AC89: 46387 | AD89: 46102 | AE89: Form BRD sudah mencantumkan kolom acceptance criteria namun cara pengisian belum dipahami user dan panduan belum tersedia, acceptance criteria yang ambigu masih dominan terjadi, status In Progress dan menjadi prioritas untuk segera disusun panduan teknis dan diselenggarakan pelatihan bagi user | AL89: =Q89 -> 3 | AM89: =R89 -> 4 | AN89: =AL89*AM89 -> 12 | AO89: =_xlfn.IFNA(VLOOKUP(AN89,Parameter!$D$53:$E$77,2),"") -> SEDANG | AP89: New - Open
A90: IT | B90: =ROW()-ROW($B$14) -> 76 | C90: Inkonsistensi data antar fase pengembangan, hilangnya traceability requirement, dan potensi pengembangan fitur yang tidak selaras dengan requirement terkini berpotensi terjadi — akibat fragmentasi tools antar BA, QA, dan Developer yang tidak terintegrasi dan mengandalkan sinkronisasi manual | D90: Dokumen BRD, FSD, & User Story | E90: Information | F90: Operasional | G90: Internal | H90: Risiko | I90: Tidak adanya integrasi teknologi antar tools yang digunakan pada masing-masing fase SDLC; keterbatasan lisensi yang menghambat adopsi platform terintegrasi secara menyeluruh; sinkronisasi data antar fase bergantung sepenuhnya pada inisiatif manual individu tanpa mekanisme otomatis | J90: Perubahan requirement tidak otomatis tercermin di test case dan backlog development; traceability antara BRD, test case, dan implementasi tidak dapat diverifikasi secara real-time; potensi pengembangan fitur berdasarkan versi requirement yang sudah tidak relevan; pemborosan sumber daya akibat rework yang disebabkan inkonsistensi data antar fase | K90: Pengembangan fitur berdasarkan requirement yang sudah kadaluarsa; test case yang tidak mencerminkan requirement terkini; kegagalan audit kualitas akibat tidak dapat diverifikasinya traceability antar dokumen; akumulasi inkonsistensi yang sulit dideteksi hingga tahap UAT atau production | L90: Tidak ada integrasi antar tools yang memungkinkan perubahan di satu fase otomatis terefleksi di fase lain; traceability hanya dapat dilakukan secara manual melalui penelusuran dokumen di SharePoint; tidak ada standar penamaan dan versioning dokumen yang memastikan konsistensi referensi antar tim | M90: Seluruh tools yang digunakan dalam proses pengembangan telah tersedia dan dokumen yang dihasilkan disimpan secara terpusat dalam folder SharePoint sebagai repositori dokumen bersama; namun belum terdapat mekanisme integrasi yang menghubungkan antar tools sehingga sinkronisasi data antar fase masih dilakukan secara manual | N90: Kerahasiaan [C] + Keutuhan [I] | O90: 7.5 – Informasi terdokumentasi; 8.1 – Perencanaan dan pengendalian operasional | P90: A.5.37 – Prosedur operasi yang terdokumentasi; A.8.25 – Siklus hidup pengembangan yang aman | Q90: 3 | R90: 4 | S90: =Q90*R90 -> 12 | T90: =_xlfn.IFNA(VLOOKUP(S90,Parameter!$D$53:$E$77,2),"") -> SEDANG | U90: Sedang — perusahaan dapat mentolerir keterbatasan integrasi tools dalam jangka pendek selama dokumen tersimpan terpusat di SharePoint, namun tidak bersedia membiarkan kondisi fragmentasi berlanjut tanpa standar sinkronisasi yang memastikan konsistensi data antar fase | V90: Sedang — perusahaan masih dapat beroperasi selama nilai risiko residual ≤ 6; jika residual masih >6, wajib eskalasi ke manajemen. Sebagai syarat minimum toleransi, organisasi wajib memastikan telah tersedia: (1) standar penamaan, versioning, dan struktur folder dokumen di SharePoint yang seragam dan dipatuhi seluruh tim, dan (2) prosedur sinkronisasi manual yang terdokumentasi dan wajib dijalankan setiap kali terjadi perubahan requirement yang berdampak pada test case dan backlog development | W90: Lakukan audit konsistensi dokumen pada project yang sedang berjalan untuk mengidentifikasi gap antara requirement, test case, dan backlog development; sinkronisasi manual seluruh dokumen yang teridentifikasi tidak konsisten; komunikasikan temuan kepada seluruh tim untuk tindakan korektif segera | X90: Tetapkan standar penamaan, versioning, dan prosedur sinkronisasi dokumen yang seragam; evaluasi opsi integrasi tools yang tersedia dalam keterbatasan lisensi; optimalkan penggunaan SharePoint sebagai platform kolaborasi yang lebih terstruktur | Y90: Business Analyst | AA90: - Tetapkan standar penamaan, versioning, dan struktur folder dokumen di SharePoint — susun konvensi yang seragam dan mengikat untuk seluruh tim mencakup format nama file, nomor versi, dan hierarki folder per project agar traceability antar dokumen dapat dilakukan secara konsisten - Susun dan sosialisasikan prosedur sinkronisasi manual antar tools — dokumentasikan prosedur wajib yang harus dijalankan setiap kali terjadi perubahan requirement, mencakup langkah pembaruan test case di Excel dan backlog di Jira secara terkoordinasi untuk memastikan konsistensi data antar fase - Evaluasi dan optimalkan integrasi tools dalam keterbatasan lisensi — kaji opsi integrasi yang tersedia seperti pemanfaatan fitur SharePoint Lists sebagai pengganti Excel untuk test case, atau eksplorasi plugin Jira yang memungkinkan import dari dokumen Word/Excel tanpa biaya lisensi tambahan - Implementasi requirement traceability matrix berbasis SharePoint — buat template traceability matrix terpusat di SharePoint yang menghubungkan requirement BRD, test case QA, dan backlog Jira secara manual namun terstruktur sebagai jembatan antar tools hingga integrasi teknologi dapat diwujudkan | AB90: Personel Business Analyst berkoordinasi dengan Personel IT Governance | AC90: 46387 | AD90: 46102 | AE90: SharePoint sudah berjalan sebagai repositori terpusat namun tidak ada standar penamaan, versioning, dan prosedur sinkronisasi yang memastikan konsistensi data antar fase, risiko belum mengalami penurunan, status In Progress dan menjadi prioritas untuk segera ditetapkan standar dokumentasi dan prosedur sinkronisasi sebagai kontrol minimum | AL90: =Q90 -> 3 | AM90: =R90 -> 4 | AN90: =AL90*AM90 -> 12 | AO90: =_xlfn.IFNA(VLOOKUP(AN90,Parameter!$D$53:$E$77,2),"") -> SEDANG | AP90: New - Open
A91: IT | B91: =ROW()-ROW($B$14) -> 77 | C91: Cakupan pengujian yang tidak dapat diverifikasi terhadap seluruh requirement akibat tidak adanya pengisian traceability matrix secara konsisten dalam seluruh dokumen BRD | D91: Dokumen BRD, FSD, & User Story | E91: Information | F91: Operasional | G91: Internal | H91: Risiko | I91: Tidak adanya SOP penulisan BRD yang seragam dan mengikat; pengisian traceability matrix tidak diwajibkan secara formal sehingga bergantung pada inisiatif masing-masing personil; tidak ada mekanisme review dan validasi kelengkapan BRD sebelum dokumen disetujui | J91: Cakupan pengujian tidak dapat diverifikasi terhadap seluruh requirement yang terdefinisi; fitur atau skenario yang tidak teruji berpotensi lolos ke environment production; kesulitan investigasi jika terjadi defect di production akibat tidak adanya jejak ketertelusuran requirement; potensi rework dan pemborosan sumber daya development akibat defect yang seharusnya teridentifikasi dalam proses QA | K91: Defect production yang seharusnya dapat dicegah dalam proses QA; ketidakmampuan membuktikan bahwa seluruh requirement telah diuji secara komprehensif; kegagalan audit kualitas pengembangan akibat tidak adanya traceability yang terdokumentasi | L91: SOP penulisan BRD belum seragam dan tidak mengikat; traceability matrix tidak diwajibkan dalam seluruh BRD; tidak ada mekanisme validasi kelengkapan dokumen BRD sebelum disetujui; konsistensi kualitas BRD bergantung pada inisiatif individu bukan standar organisasi | M91: Format Business Requirement Document telah tersedia sebagai panduan penyusunan, namun penerapan traceability matrix belum diwajibkan secara konsisten dalam seluruh dokumen BRD yang dihasilkan, sehingga kelengkapan traceability bergantung pada inisiatif masing-masing personil penyusun | N91: Keutuhan [I] + Ketersediaan [A] | O91: 7.5 – Informasi terdokumentasi; 8.1 – Perencanaan dan pengendalian operasional | P91: A.5.37 – Prosedur operasi yang terdokumentasi; A.8.25 – Siklus hidup pengembangan yang aman; A.8.26 – Persyaratan keamanan aplikasi | Q91: 3 | R91: 3 | S91: =Q91*R91 -> 9 | T91: =_xlfn.IFNA(VLOOKUP(S91,Parameter!$D$53:$E$77,2),"") -> SEDANG-RENDAH | U91: Sedang — perusahaan dapat mentolerir inkonsistensi traceability dalam jangka pendek selama format BRD masih digunakan, namun tidak bersedia membiarkan kondisi ini berlanjut mengingat dampaknya pada kualitas pengujian dan kemampuan audit deliverable pengembangan | V91: Rendah — perusahaan masih dapat beroperasi selama nilai risiko residual ≤ 6; jika residual masih >6, wajib eskalasi untuk standardisasi SOP BRD dan enforcement traceability matrix secara segera | W91: Lakukan review retrospektif terhadap BRD yang sudah ada untuk mengidentifikasi yang belum memiliki traceability matrix; lengkapi traceability matrix pada BRD project yang sedang berjalan sebelum tahap pengujian dimulai; audit test case yang sudah berjalan untuk memastikan seluruh requirement tercakup | X91: Susun dan tetapkan SOP penulisan BRD yang seragam dengan mewajibkan pengisian traceability matrix sebagai komponen mandatory; implementasi mekanisme review dan validasi kelengkapan BRD sebelum dokumen disetujui | Y91: Business Analyst | AA91: - Susun SOP penulisan BRD yang seragam — dokumen standar yang mengatur format, komponen wajib, dan tata cara penulisan BRD yang berlaku untuk seluruh personil BA tanpa pengecualian - Tetapkan traceability matrix sebagai komponen wajib BRD — perbarui template BRD untuk menjadikan traceability matrix sebagai bagian mandatory yang harus diisi sebelum dokumen dapat diajukan untuk persetujuan - Sosialisasi SOP BRD ke seluruh personil BA dan QA — selenggarakan sesi sosialisasi dan workshop penerapan SOP baru untuk memastikan seluruh personil memahami dan mampu menerapkan standar yang ditetapkan - Integrasikan traceability matrix ke dalam proses QA — pastikan QA menggunakan traceability matrix dalam BRD sebagai acuan wajib dalam penyusunan test case untuk setiap project - Pantau kepatuhan pengisian BRD secara berkala — lakukan sampling review terhadap BRD yang dihasilkan untuk memastikan konsistensi penerapan SOP dan kelengkapan traceability matrix | AB91: Personel Business Analyst, berkordinasi dengan SysDur | AC91: 46387 | AD91: 46102 | AE91: Format BRD sudah tersedia namun traceability matrix belum diwajibkan secara konsisten dan SOP penulisan belum seragam, kualitas traceability masih bergantung pada inisiatif individu, status In Progress dan perlu segera dilakukan standardisasi SOP dan enforcement traceability matrix sebagai komponen wajib | AL91: =Q91 -> 3 | AM91: =R91 -> 3 | AN91: =AL91*AM91 -> 9 | AO91: =_xlfn.IFNA(VLOOKUP(AN91,Parameter!$D$53:$E$77,2),"") -> SEDANG-RENDAH | AP91: New - Open
A92: IT | B92: =ROW()-ROW($B$14) -> 78 | C92: Pengembangan fitur yang tidak sesuai kebutuhan bisnis dan hasil pengujian yang tidak dapat dipertanggungjawabkan berpotensi terjadi — akibat tidak adanya dokumentasi proses bisnis menyeluruh sebagai referensi dan kesenjangan pengetahuan pada pengguna yang memahami proses bisnis secara end-to-end | D92: Dokumen BRD, FSD, & User Story | E92: Information | F92: Operasional | G92: Internal | H92: Risiko | I92: Tidak adanya dokumentasi proses bisnis menyeluruh seluruh departemen yang dapat dijadikan referensi standar oleh BA dan QA; kesenjangan pengetahuan pada sisi pengguna terkait proses bisnis end-to-end; ketergantungan pada konfirmasi ad-hoc yang tidak terstruktur sebagai mekanisme klarifikasi requirement | J92: Pengembangan fitur yang tidak sesuai dengan kebutuhan bisnis yang sebenarnya; hasil pengujian yang didasarkan pada asumsi sepihak sehingga tidak dapat dipertanggungjawabkan; potensi rework yang memboroskan sumber daya development; risiko fitur yang dirilis tidak memenuhi ekspektasi operasional bisnis | K92: Fitur yang dirilis tidak sesuai kebutuhan bisnis dan harus di-rework; pengujian yang tidak komprehensif akibat requirement yang ambigu; akumulasi technical debt akibat perubahan requirement yang berulang; penurunan kepercayaan unit bisnis terhadap kualitas deliverable IT | L92: Tidak ada dokumentasi proses bisnis menyeluruh sebagai referensi standar; gap knowledge pada pengguna yang memahami proses bisnis end-to-end; tidak ada mekanisme formal validasi pemahaman requirement antara BA, QA, dan unit bisnis | M92: Setiap inisiasi pengembangan diwajibkan menyiapkan Business Requirement Document dalam format standar yang mencakup uraian manfaat, alur proses, dan asesmen risiko sebagai syarat persetujuan sebelum pengembangan dimulai | N92: Keutuhan [I] + Ketersediaan [A] | O92: 8.1 – Perencanaan dan pengendalian operasional; 7.5 – Informasi terdokumentasi | P92: A.5.37 – Prosedur operasi yang terdokumentasi; A.8.25 – Siklus hidup pengembangan yang aman; A.8.26 – Persyaratan keamanan aplikasi | Q92: 3 | R92: 2 | S92: =Q92*R92 -> 6 | T92: =_xlfn.IFNA(VLOOKUP(S92,Parameter!$D$53:$E$77,2),"") -> SEDANG-RENDAH | U92: Sedang — perusahaan dapat mentolerir risiko ambiguitas requirement dalam batas yang terkendali selama mekanisme konfirmasi dan Business Requirement Document berjalan efektif, namun tidak bersedia membiarkan ketiadaan dokumentasi proses bisnis menyeluruh berlanjut dalam jangka panjang | V92: Rendah — perusahaan masih dapat beroperasi selama nilai risiko residual ≤ 4; jika residual masih >4, wajib eskalasi untuk penyusunan segera dokumentasi proses bisnis menyeluruh | W92: Hentikan sementara pengembangan fitur yang requirement-nya ambigu; lakukan sesi klarifikasi terstruktur dengan unit bisnis yang relevan; dokumentasikan hasil klarifikasi sebagai addendum Business Requirement Document; review ulang test case yang didasarkan pada asumsi sebelum pengujian dilanjutkan | X92: Susun dokumentasi proses bisnis menyeluruh seluruh departemen sebagai referensi standar BA dan QA; implementasi mekanisme validasi pemahaman requirement yang formal; perkuat kompetensi BA dalam teknik elicitasi requirement yang terstruktur | Y92: Business Analyst | AA92: - Susun dokumentasi proses bisnis menyeluruh — buat dokumentasi formal alur proses bisnis end-to-end per departemen yang dapat dijadikan referensi standar oleh BA dan QA dalam setiap inisiasi pengembangan - Implementasi mekanisme sign-off requirement — tetapkan kewajiban persetujuan formal dari perwakilan unit bisnis yang berwenang sebelum requirement dinyatakan final dan pengembangan dimulai - Implementasi requirement traceability matrix — pastikan setiap test case QA dapat ditelusuri kembali ke requirement yang telah dikonfirmasi dan disetujui oleh unit bisnis - Jadwalkan review dan pembaruan dokumentasi proses bisnis — lakukan evaluasi dan pembaruan dokumentasi proses bisnis minimal tahunan atau setiap ada perubahan kebijakan bisnis yang signifikan | AB92: Personel Business Analyst, berkordinasi dengan SysDur | AC92: 46387 | AD92: 46102 | AE92: Business Requirement Document sudah diwajibkan dan berjalan efektif sebagai kontrol utama yang menekan probabilitas kejadian, risiko berada pada level Rendah dan terkendali, namun penyusunan dokumentasi proses bisnis menyeluruh tetap perlu dilanjutkan sebagai penguatan jangka panjang, status In Progress | AL92: =Q92 -> 3 | AM92: =R92 -> 2 | AN92: =AL92*AM92 -> 6 | AO92: =_xlfn.IFNA(VLOOKUP(AN92,Parameter!$D$53:$E$77,2),"") -> SEDANG-RENDAH | AP92: New - Open
A93: IT | B93: =ROW()-ROW($B$14) -> 79 | C93: Postur keamanan reaktif tanpa langganan intelijen ancaman proaktif, pemantauan ancaman spesifik industri, atau analisis tren musuh memungkinkan serangan yang mengejutkan dari kelompok ancaman yang dikenal menargetkan tumpukan teknologi spesifik tanpa peringatan sebelumnya atau persiapan. | D93: Dokumen Cyber Threat Intelligence (CTI) & Feeds | E93: Information | F93: Strategis | G93: External | H93: Risiko | N93: Semua (C - I - A) | Q93: 1 | R93: 1 | S93: =Q93*R93 -> 1 | T93: =_xlfn.IFNA(VLOOKUP(S93,Parameter!$D$53:$E$77,2),"") -> RENDAH | V93: - | W93: - | X93: - | Y93: IT Security Analyst | Z93: DevSecOps | AA93: - | AB93: - | AC93: 46387 | AD93: 46102 | AE93: - | AL93: =Q93 -> 1 | AM93: =R93 -> 1 | AN93: =AL93*AM93 -> 1 | AO93: =_xlfn.IFNA(VLOOKUP(AN93,Parameter!$D$53:$E$77,2),"") -> RENDAH | AP93: New - Open
A94: IT | B94: =ROW()-ROW($B$14) -> 80 | C94: Dokumentasi pemodelan ancaman yang dibuat pada fase awal proyek tanpa pembaruan berkala terhadap perubahan arsitektur (migrasi microservices, adopsi cloud, integrasi baru) menghasilkan model ancaman yang usang, permukaan serangan yang terlewatkan, dan persyaratan keamanan yang tidak lengkap untuk arsitektur baru. | D94: Dokumen Cyber Threat Intelligence (CTI) & Feeds | E94: Information | F94: Strategis | G94: External | H94: Risiko | N94: Semua (C - I - A) | Q94: 1 | R94: 1 | S94: =Q94*R94 -> 1 | T94: =_xlfn.IFNA(VLOOKUP(S94,Parameter!$D$53:$E$77,2),"") -> RENDAH | V94: - | W94: - | X94: - | Y94: IT Security Analyst | AA94: - | AB94: - | AC94: 46387 | AD94: 46102 | AE94: - | AL94: =Q94 -> 1 | AM94: =R94 -> 1 | AN94: =AL94*AM94 -> 1 | AO94: =_xlfn.IFNA(VLOOKUP(AN94,Parameter!$D$53:$E$77,2),"") -> RENDAH | AP94: New - Open
A95: IT | B95: =ROW()-ROW($B$14) -> 81 | C95: Ketidakmampuan mendeteksi dan merespons ancaman siber secara proaktif sebelum terjadi dampak berpotensi memperpanjang waktu eksposur dan kerugian — namun membuka peluang implementasi Cyber Threat Intelligence berbasis AI yang secara otomatis mengagregasi, menganalisis, dan memprioritaskan ancaman relevan bagi industri asuransi, memungkinkan tim keamanan beralih dari postur reaktif menjadi prediktif | D95: Dokumen Cyber Threat Intelligence (CTI) & Feeds | E95: Information | F95: Operasional | G95: Internal | H95: Peluang | Q95: 1 | R95: 1 | S95: =Q95*R95 -> 1 | T95: =_xlfn.IFNA(VLOOKUP(S95,Parameter!$D$53:$E$77,2),"") -> RENDAH | AC95: 46387 | AD95: 46102 | AL95: =Q95 -> 1 | AM95: =R95 -> 1 | AN95: =AL95*AM95 -> 1 | AO95: =_xlfn.IFNA(VLOOKUP(AN95,Parameter!$D$53:$E$77,2),"") -> RENDAH | AP95: New - Open
A96: IT | B96: =ROW()-ROW($B$14) -> 82 | C96: Periode retensi data yang dipublikasikan dan jadwal pembuangan memungkinkan ancaman siber merencanakan waktu pencurian data untuk memanfaatkan jendela kesempatan ketika data masih dapat diakses tetapi sebelum eksekusi penghapusan terjadwal untuk memaksimalkan volume eksfiltrasi. | D96: Dokumen Data Retention & Disposal Rules | E96: Information | F96: Operasional | G96: Internal | H96: Risiko | Q96: 1 | R96: 1 | S96: =Q96*R96 -> 1 | T96: =_xlfn.IFNA(VLOOKUP(S96,Parameter!$D$53:$E$77,2),"") -> RENDAH | AC96: 46387 | AD96: 46102 | AL96: =Q96 -> 1 | AM96: =R96 -> 1 | AN96: =AL96*AM96 -> 1 | AO96: =_xlfn.IFNA(VLOOKUP(AN96,Parameter!$D$53:$E$77,2),"") -> RENDAH | AP96: New - Open
A97: IT | B97: =ROW()-ROW($B$14) -> 83 | C97: Pengungkapan dokumen Penilaian Dampak Privasi Data (DPIA) yang berisi identifikasi kesenjangan kepatuhan, kelemahan keamanan, dan eksposur risiko regulasi memungkinkan ancaman siber atau pesaing menggunakan informasi sebagai leverage untuk pemerasan atau intelijen kompetitif. | D97: Dokumen DPIA | E97: Information | F97: Operasional | G97: Internal | H97: Risiko | Q97: 1 | R97: 1 | S97: =Q97*R97 -> 1 | T97: =_xlfn.IFNA(VLOOKUP(S97,Parameter!$D$53:$E$77,2),"") -> RENDAH | AC97: 46387 | AD97: 46102 | AL97: =Q97 -> 1 | AM97: =R97 -> 1 | AN97: =AL97*AM97 -> 1 | AO97: =_xlfn.IFNA(VLOOKUP(AN97,Parameter!$D$53:$E$77,2),"") -> RENDAH | AP97: New - Open
A98: IT | B98: =ROW()-ROW($B$14) -> 84 | C98: Pemahaman terhadap persyaratan formulir proses bisnis dan alur kerja persetujuan memungkinkan ancaman siber merancang permintaan palsu yang tampak sah untuk social engineer pengguna yang berwenang agar memberikan akses tidak sah atau tindakan sensitif. | D98: Dokumen Form Pengajuan ke IT Department | E98: Information | F98: Operasional | G98: Internal | H98: Risiko | Q98: 1 | R98: 1 | S98: =Q98*R98 -> 1 | T98: =_xlfn.IFNA(VLOOKUP(S98,Parameter!$D$53:$E$77,2),"") -> RENDAH | AC98: 46387 | AD98: 46102 | AL98: =Q98 -> 1 | AM98: =R98 -> 1 | AN98: =AL98*AM98 -> 1 | AO98: =_xlfn.IFNA(VLOOKUP(AN98,Parameter!$D$53:$E$77,2),"") -> RENDAH | AP98: New - Open
A99: IT | B99: =ROW()-ROW($B$14) -> 85 | C99: Hasil latihan respons insiden yang terekspos mengungkapkan kesenjangan kemampuan tim, ekspektasi waktu respons, dan bottleneck yang diidentifikasi memungkinkan ancaman siber merancang skenario serangan yang secara spesifik memanfaatkan kelemahan yang diidentifikasi untuk memaksimalkan waktu hunian. | D99: Dokumen Hasil Incident Simulation | E99: Information | F99: Operasional | G99: Internal | H99: Risiko | Q99: 1 | R99: 1 | S99: =Q99*R99 -> 1 | T99: =_xlfn.IFNA(VLOOKUP(S99,Parameter!$D$53:$E$77,2),"") -> RENDAH | AC99: 46387 | AD99: 46102 | AL99: =Q99 -> 1 | AM99: =R99 -> 1 | AN99: =AL99*AM99 -> 1 | AO99: =_xlfn.IFNA(VLOOKUP(AN99,Parameter!$D$53:$E$77,2),"") -> RENDAH | AP99: New - Open
A100: IT | B100: =ROW()-ROW($B$14) -> 86 | C100: Dokumentasi panduan respons insiden dan playbook yang merujuk pada alat usang, server yang dihentikan, atau staf yang telah keluar menghasilkan prosedur respons insiden yang tidak fungsional ketika insiden keamanan aktual terjadi, menyebabkan penundaan respons dan kebingungan operasional. | D100: Dokumen Incident Response Plan (IRP) & Forensic Playbooks | E100: Information | F100: Strategis | G100: External | H100: Risiko | N100: Semua (C - I - A) | Q100: 1 | R100: 1 | S100: =Q100*R100 -> 1 | T100: =_xlfn.IFNA(VLOOKUP(S100,Parameter!$D$53:$E$77,2),"") -> RENDAH | V100: - | W100: - | X100: - | Y100: IT Security Analyst | AA100: - | AB100: - | AC100: 46387 | AD100: 46102 | AE100: - | AL100: =Q100 -> 1 | AM100: =R100 -> 1 | AN100: =AL100*AM100 -> 1 | AO100: =_xlfn.IFNA(VLOOKUP(AN100,Parameter!$D$53:$E$77,2),"") -> RENDAH | AP100: New - Open
A101: IT | B101: =ROW()-ROW($B$14) -> 87 | C101: Keberadaan dokumentasi rencana respons insiden dan rencana kontinuitas bisnis tanpa simulasi eksekusi aktual atau latihan meja (tabletop exercise) menghasilkan efektivitas prosedur yang tidak tervalidasi, personel yang tidak terlatih, dan koordinasi yang kacau ketika insiden keamanan nyata terjadi. | D101: Dokumen Incident Response Plan (IRP) & Forensic Playbooks | E101: Information | F101: Strategis | G101: External | H101: Risiko | N101: Semua (C - I - A) | Q101: 1 | R101: 1 | S101: =Q101*R101 -> 1 | T101: =_xlfn.IFNA(VLOOKUP(S101,Parameter!$D$53:$E$77,2),"") -> RENDAH | V101: - | W101: - | X101: - | Y101: IT Security Analyst | AA101: - | AB101: - | AC101: 46387 | AD101: 46102 | AE101: - | AL101: =Q101 -> 1 | AM101: =R101 -> 1 | AN101: =AL101*AM101 -> 1 | AO101: =_xlfn.IFNA(VLOOKUP(AN101,Parameter!$D$53:$E$77,2),"") -> RENDAH | AP101: New - Open
A102: IT | B102: =ROW()-ROW($B$14) -> 88 | C102: Degradasi kapabilitas keamanan IT secara bertahap berpotensi terjadi akibat akumulasi gap tools kadaluarsa dan keterbatasan personil ahli — akibat tidak terpenuhinya seluruh kebutuhan anggaran keamanan IT secara konsisten karena mekanisme persetujuan berbasis prioritas tanpa kerangka justifikasi risiko yang memadai | D102: Dokumen IT Budget | E102: Information | F102: Strategis | G102: Internal | H102: Risiko | I102: Mekanisme persetujuan anggaran berbasis prioritas yang tidak selalu mengakomodasi seluruh kebutuhan keamanan IT; tidak adanya kerangka justifikasi investasi keamanan berbasis risiko yang dapat meyakinkan pengambil keputusan; persepsi IT Security sebagai cost center yang tidak menghasilkan nilai bisnis langsung; tidak adanya mekanisme eskalasi formal ketika anggaran keamanan yang disetujui di bawah kebutuhan minimum | J102: Akumulasi tools keamanan yang kadaluarsa dan tidak mendapat pembaruan; keterbatasan personil ahli keamanan yang berdampak pada kapabilitas deteksi dan respons insiden; peningkatan eksposur risiko keamanan yang tidak tertangani akibat gap kapasitas; potensi pelanggaran kepatuhan regulasi akibat tidak terpenuhinya standar minimum keamanan | K102: Eksploitasi celah keamanan yang tidak tertangani akibat tools kadaluarsa; insiden keamanan yang tidak terdeteksi akibat understaffed tim keamanan; kegagalan audit regulasi akibat tidak terpenuhinya standar minimum investasi keamanan; degradasi postur keamanan organisasi yang bersifat gradual dan sulit terdeteksi | L102: Tidak ada kerangka justifikasi investasi keamanan berbasis risiko yang terdokumentasi; anggaran keamanan bersaing dengan kebutuhan operasional lain tanpa mekanisme proteksi minimum; tidak ada threshold minimum anggaran keamanan yang ditetapkan sebagai kebijakan organisasi | M102: Proses pengajuan anggaran IT telah dilaksanakan secara terstruktur di awal tahun dengan monitoring realisasi bulanan; setiap inisiatif strategis IT telah dialignkan dengan justifikasi investasi dan eksplorasi alternatif open-source sebagai opsi efisiensi biaya; namun persetujuan anggaran dilakukan berdasarkan skala prioritas sehingga tidak seluruh kebutuhan keamanan IT dapat terpenuhi dalam satu siklus anggaran | N102: Semua (C - I - A) | O102: 5.1 – Kepemimpinan dan komitmen; 7.1 – Sumber daya; 6.2 – Tujuan keamanan informasi | P102: A.5.1 – Kebijakan keamanan informasi; A.5.4 – Tanggung jawab manajemen; A.6.3 – Kesadaran, pendidikan dan pelatihan keamanan informasi | Q102: 4 | R102: 3 | S102: =Q102*R102 -> 12 | T102: =_xlfn.IFNA(VLOOKUP(S102,Parameter!$D$53:$E$77,2),"") -> SEDANG | U102: Rendah — perusahaan tidak bersedia membiarkan kapabilitas keamanan IT terdegradasi akibat gap anggaran yang tidak terkelola, mengingat dampak kumulatifnya pada postur keamanan organisasi, pemenuhan kewajiban regulasi, dan keberlangsungan operasional bisnis | V102: Sedang — perusahaan masih dapat beroperasi selama nilai risiko residual ≤ 9; jika residual masih >9, wajib eskalasi ke manajemen senior. Sebagai syarat minimum toleransi, organisasi wajib memastikan telah tersedia: (1) kerangka justifikasi investasi keamanan berbasis risiko yang terdokumentasi dan digunakan dalam setiap pengajuan anggaran, dan (2) mekanisme eskalasi formal yang terdefinisi ketika anggaran keamanan yang disetujui berada di bawah threshold kebutuhan minimum | W102: Lakukan inventarisasi segera terhadap tools keamanan yang kadaluarsa dan gap personil yang sudah terjadi; susun remediation plan darurat berbasis prioritas risiko; ajukan anggaran tambahan dengan justifikasi berbasis dampak insiden yang berpotensi terjadi; eskalasi kondisi kepada manajemen senior sebagai dasar pengambilan keputusan | X102: Susun kerangka justifikasi investasi keamanan berbasis risiko untuk mendukung pengajuan anggaran; tetapkan threshold minimum anggaran keamanan sebagai kebijakan organisasi; implementasi mekanisme eskalasi formal ketika anggaran yang disetujui di bawah kebutuhan minimum | Y102: Chief Technology & Information Officer | AA102: - Susun kerangka justifikasi investasi keamanan berbasis risiko — buat dokumen yang mengkuantifikasi potensi kerugian finansial, reputasi, dan kepatuhan regulasi jika kebutuhan keamanan tidak terpenuhi; gunakan sebagai materi pendukung wajib dalam setiap pengajuan anggaran keamanan IT kepada manajemen senior dan Direksi - Tetapkan threshold minimum anggaran keamanan dan mekanisme eskalasi formal — definisikan batas minimum anggaran keamanan IT sebagai kebijakan organisasi; tetapkan prosedur eskalasi formal kepada manajemen senior jika anggaran yang disetujui berada di bawah threshold minimum, agar gap dapat ditindaklanjuti sebelum berdampak pada kapabilitas keamanan - Lakukan inventarisasi tools kadaluarsa dan gap personil keamanan — identifikasi seluruh tools keamanan yang sudah melewati batas dukungan vendor dan personil yang dibutuhkan namun belum tersedia; susun roadmap pemenuhan bertahap berdasarkan prioritas risiko sebagai dasar pengajuan anggaran berikutnya - Bangun narasi IT Security sebagai investasi strategis — susun materi komunikasi yang menjelaskan nilai bisnis investasi keamanan kepada Direksi dalam bahasa bisnis (ROI keamanan, cost of breach, perbandingan biaya pencegahan vs pemulihan); integrasikan ke dalam forum pelaporan manajemen secara berkala | AB102: CTIO | AC102: 46387 | AD102: 46102 | AE102: Pengajuan anggaran terstruktur, monitoring bulanan, dan alignmen strategic plan sudah berjalan sebagai kontrol yang memadai, namun tidak adanya kerangka justifikasi berbasis risiko dan mekanisme eskalasi formal membuat kebutuhan minimum keamanan rentan tidak terpenuhi, risiko belum mengalami penurunan signifikan, status In Progress dan menjadi prioritas untuk segera disusun kerangka justifikasi berbasis risiko sebelum siklus pengajuan anggaran berikutnya | AL102: =Q102 -> 4 | AM102: =R102 -> 3 | AN102: =AL102*AM102 -> 12 | AO102: =_xlfn.IFNA(VLOOKUP(AN102,Parameter!$D$53:$E$77,2),"") -> SEDANG | AP102: New - Open
...

Sheet REF
A1: Jenis Aset | C1: CIA | E1: Kategori Aset | G1: Jenis Risiko | I1: Risiko/Peluang | K1: Internal / Eksternal | M1: Status | O1: Personil
A2: API Endpoint | C2: Kerahasiaan [C] | E2: Information | G2: Strategis | I2: Risiko | K2: Internal | M2: New - Open | O2: Business Analyst
A3: API Spec Documentation | C3: Keutuhan [I] | E3: Software | G3: Operasional | I3: Peluang | K3: External | M3: In Progress | O3: Chief Technology & Information Officer
A4: Aplikasi Core System | C4: Ketersediaan [A] | E4: Intangible | G4: Kredit | M4: Closed | O4: Data Analytics
A5: Aplikasi Identity and Access Management (IAM) & PAM | C5: Kerahasiaan [C] + Keutuhan [I] | E5: People | G5: Pasar | O5: Data Management
A6: Aplikasi Mobile | C6: Kerahasiaan [C] + Ketersediaan [A] | E6: Hardware | G6: Likuiditas | O6: DevSecOps
A7: Aplikasi Ticketing | C7: Keutuhan [I] + Ketersediaan [A] | G7: Hukum | O7: Digital Application Development
A8: Aplikasi Ticketing | C8: Semua (C - I - A) | G8: Kepatuhan | O8: Digital Strategy
A9: Aplikasi Web | G9: Likuiditas | O9: IT Application Production Support
A10: Arsitektur Aplikasi | G10: Reputasi | O10: IT Core Development
A11: Automation Testing | G11: Asuransi | O11: IT Governance
A12: Core System | O12: IT Infra - Network
A13: Dasboard Business Intelligence | O13: IT Infra - Sysadmin
A14: Dashboard Monitoring Tool | O14: IT Infrastructure (Head)
A15: Data Backup & Restore Point | O15: IT Infrastructure Technical Support
A16: Data Center | O16: IT Security Analyst
A17: Data Dummy | O17: IT Vendor/Supplier Management
A18: Data Internal Perusahaan | O18: Quality Assurance
A19: Data list environment (Container Images)
A20: Database Core System
A21: Database Management Tools
A22: Database Non Core System
A23: Development Tools
A24: Dokumen Arsitektur Data
A25: Dokumen Baseline Hardening
A26: Dokumen BCDRP Plan & Scenario
A27: Dokumen BRD, FSD, & User Story
A28: Dokumen Cyber Threat Intelligence (CTI) & Feeds
A29: Dokumen Data Retention & Disposal Rules
A30: Dokumen DPIA
... A100: Vulnerability Scanner

Sheet Asset Owner
A1: No | B1: Nama Bagian | C1: Aset | D1: Kategori Aset
A2: 1 | B2: Digital Application Development | C2: Source Code Application | D2: Information
A3: 2 | B3: Digital Application Development | C3: Development Tools | D3: Software
A4: 3 | B4: Digital Application Development | C4: Hak Cipta / Kekayaan Intelektual (IP) Aplikasi | D4: Intangible
A5: 4 | B5: Digital Application Development | C5: Tim Programmer / Developer (In-house) | D5: People
A6: 5 | B6: Digital Application Development | C6: API Spec Documentation | D6: Information
A7: 6 | B7: Business Analyst | C7: Dokumen BRD, FSD, & User Story | D7: Information
A8: 7 | B8: Business Analyst | C8: Pemetaan Proses Bisnis (Business Process Mapping) | D8: Information
A9: 8 | B9: Business Analyst | C9: Personel Business Analyst | D9: People
A10: 9 | B10: Business Analyst | C10: Matriks Persyaratan Fungsional & Non-Fungsional | D10: Information
A11: 10 | B11: Quality Assurance | C11: Test Case / Skenario Uji | D11: Information
A12: 11 | B12: Quality Assurance | C12: Data Dummy | D12: Information
A13: 12 | B13: Quality Assurance | C13: Automation Testing | D13: Software
... A89: 88 | B89: IT Security | C89: Modul Security Awareness & Hasil Incident Simulation | D89: Information

Sheet Parameter
A2: TINGKAT PROBABILITAS
A3: Nilai | B3: Level | C3: Probabilitas | D3: Risiko IT 1 | E3: Risiko IT 2 | F3: Risiko IT 3 | G3: Risiko IT 4 | H3: Risiko IT 5
A4: 1 | B4: Rendah | C4: Hampir Tidak Pernah Terjadi/Sangat Jarang
A5: 2 | B5: Sedang-Rendah | C5: Kemungkinan Terjadi Ada Tetapi Kecil/Jarang
A6: 3 | B6: Sedang | C6: Mungkin Saja Terjadi/Mungkin
A7: 4 | B7: Sedang-Tinggi | C7: Kemungkinan Besar Jarang Terjadi/Sering
A8: 5 | B8: Tinggi | C8: Hampir Selalu Terjadi/Sangat Sering
A10: TINGKAT DAMPAK | J10: PELUANG
A11: Nilai | B11: Level | C11: Dampak | J11: Pengembangan Produk/Layanan Baru | K11: Penambahan Pelanggan | L11: Peningkatan Produktivitas | M11: Pengembangan Teknologi Baru | N11: Penghematan Biaya
C12: Deskripsi | D12: Bisnis | E12: Finansial | F12: Operasional (Produk atau Pelayanan) | G12: Merusak Reputasi | H12: Perundangan, Peraturan dan Kepatuhan
A13: 1 | B13: Rendah | C13: Dampaknya Sangat Kecil | D13: Sangat kecil, tidak ada | E13: Sangat kecil, tidak ada | F13: Sangat kecil, tidak ada | G13: Sangat kecil, tidak ada citra negatif yang mengakibatkan penurunan kepercayaan | H13: Sangat kecil, tidak ada sanksi yang dikenakan ke perusahaan | J13: Sangat kecil, tidak ada | K13: Sangat kecil, tidak ada | L13: Sangat kecil, tidak ada | M13: Sangat kecil, tidak ada | N13: Sangat kecil, tidak ada
A14: 2 | B14: Sedang-Rendah | C14: Dampaknya Kecil/Minor | D14: Tidak mengganggu proses bisnis namun terdapat sedikit keluhan | E14: Sedikit kerugian atau biaya yang harus dikeluarkan berkisar < Rp 50.000.000,00 | F14: Masih bisa ditoleransi, mengakibatkan penundaan aktivitas (operasional tidak dapat dijalankan) maksimum 2 Jam | G14: Terdapat citra negatif, namun masih bisa ditoleransi oleh perusahaan | H14: Risiko kecil ketika tidak terpenuhi, seperti sanksi berupa teguran tertulis karena sebagian kecil regulasi sudah terdokumentasi, tetapi belum diterapkan secara konsisten | J14: Cukup sulit pengembangan produk atau jasa baru | K14: Cukup sulit penambahan baru | L14: Sedikit menambah produktifitas, 0-5% | M14: Sedikit dapat mengembangkan teknologi, 0-5% | N14: Sedikit menguntungkan, potensi keuntungan 0-5%
A15: 3 | B15: Sedang | C15: Dampaknya Sedang/Moderate | D15: Hanya beberapa proses bisnis tidak berjalan, namun terdapat keluhan secara formal | E15: Menghabiskan cukup biaya atau kerugian yang harus dikeluarkan berkisar Rp 50.000.000,00 - Rp 100.000.000,00 | F15: Cukup berpengaruh terhadap mutu produk atau layanan, mengakibatkan penundaan aktivitas (operasional tidak dapat dijalankan) maksimum 12 Jam | G15: Terdapat citra negatif yang cukup berpengaruh terhadap reputasi perusahaan sehingga mempengaruhi kinerja atau kebijakan | H15: Cukup berbahaya, potensi Ilegal operasional, terdapat sanksi berupa teguran tertulis karena masih banyak regulasi yang belum diterapkan | J15: Cukup mudah untuk pengembangan produk atau jasa baru | K15: Cukup mudah untuk penambahan pelanggan baru | L15: Cukup menambah produktivitas, 5-15% | M15: Cukup untk dapat dengan mudah mengembangkan , 5-15% | N15: Cukup menguntungkan, potensi keuntungan 5-15%
A16: 4 | B16: Sedang-Tinggi | C16: Dampaknya Besar/Major | D16: Sebagian proses bisnis tidak berjalan dengan adanya keluhan yang perlu dieskalasi dan berpotensi menyebar | E16: Banyak menghabiskan biaya atau kerugian yang berkisar Rp 100.000.000,00 - Rp 500.000.000,00 | F16: Potensi bahaya terhadap mutu produk/layanan, mengakibatkan penundaan aktivitas (operasional tidak dapat dijalankan) maksimum 24 Jam | G16: Potensi bahaya berupa pemberitaan negatif yang berpengaruh terhadap reputasi perusahaan | H16: Ilegal operasional pada berbagai area, terdapat sanksi berupa pemanggilan dari pihak yang berwenang terkait pelanggaran regulasi yang berlaku | J16: Sangat mudah pengembangan produk atau jasa baru | K16: Sangat mudah | L16: Peningkatan produktivitas baik, sekitar 15-30% | M16: Pengembangan teknologi realtif baik, sekitar 15-30% | N16: Sangat menguntungkan, potensi keuntungan 15-30%
A17: 5 | B17: Tinggi | C17: Dampaknya Sangat Besar/Catasthropic | D17: Proses bisnis tidak berjalan total dengan adanya potensi pemutusan hubungan kerja sama atau bisnis | E17: Membutuhkan biaya sangat besar atau kerugian yang berkisar > Rp 500.000.000,00 | F17: Merusak mutu produk atau layanan, mengakibatkan penundaan aktivitas (operasional tidak dapat dijalankan) lebih dari 1 hari | G17: Merusak reputasi dengan diikutinya kehilangan kepercayaan dari pihak berkepentingan | H17: Ilegal operasional potensi dihukum berat, terdapat sanksi penutupan perusahaan akibat melanggar regulasi yang berlaku | J17: Mampu mengembangkan beberapa produk atau jasa baru | K17: Pasti Mampu menambah pelanggan baru | L17: Mampu menambah produktivitas denga sangat baik, diatas 30% | M17: Mampu dalam pengembangan teknologi dengan sangat baik, diatas 30% | N17: Sangat menguntungkan, diatas 30%
A23: Tabel Matriks Risiko | D23: PROBABILITAS | J23: Tabel Matrik Risiko | M23: PROBABILITAS
D24: 1 | E24: 2 | F24: 3 | G24: 4 | H24: 5 | M24: 1 | N24: 2 | O24: 3 | P24: 4 | Q24: 5
D25: Rendah | E25: Sedang-Rendah | F25: Sedang | G25: Sedang-Tinggi | H25: Tinggi | M25: Rendah | N25: Sedang-Rendah | O25: Sedang | P25: Sedang-Tinggi | Q25: Tinggi
A26: DAMPAK | B26: 5 | C26: Tinggi | D26: 5 | E26: 10 | F26: 15 | G26: 20 | H26: 25 | J26: DAMPAK | K26: 5 | L26: Tinggi | M26: Sedang-Rendah | N26: Sedang | O26: Sedang-Tinggi | P26: Tinggi | Q26: Tinggi
B27: 4 | C27: Sedang-Tinggi | D27: 4 | E27: 8 | F27: 12 | G27: 16 | H27: 20 | K27: 4 | L27: Sedang-Tinggi | M27: Sedang-Rendah | N27: Sedang-Rendah | O27: Sedang | P27: Sedang-Tinggi | Q27: Tinggi
B28: 3 | C28: Sedang | D28: 3 | E28: 6 | F28: 9 | G28: 12 | H28: 15 | K28: 3 | L28: Sedang | M28: Rendah | N28: Sedang-Rendah | O28: Sedang-Rendah | P28: Sedang | Q28: Sedang-Tinggi
B29: 2 | C29: Sedang-Rendah | D29: 2 | E29: 4 | F29: 6 | G29: 8 | H29: 10 | K29: 2 | L29: Sedang-Rendah | M29: Rendah | N29: Rendah | O29: Sedang-Rendah | P29: Sedang-Rendah | Q29: Sedang
B30: 1 | C30: Rendah | D30: 1 | E30: 2 | F30: 3 | G30: 4 | H30: 5 | K30: 1 | L30: Rendah | M30: Rendah | N30: Rendah | O30: Rendah | P30: Sedang-Rendah | Q30: Sedang-Rendah
A33: Tabel Matriks Resiko | D33: PROBABILITAS
D34: 1 | E34: 2 | F34: 3 | G34: 4 | H34: 5
D35: Rendah | E35: Sedang Rendah | F35: Sedang Tinggi | G35: Tinggi | H35: Sangat Tinggi
A36: DAMPAK | B36: 5 | C36: Sangat Tinggi | D36: =B36*D34 -> 5 | E36: =B36*$E$24 -> 10 | F36: =B36*$F$24 -> 15 | G36: =B36*$G$24 -> 20 | H36: =B36*$H$24 -> 25
B37: 4 | C37: Tinggi | D37: =B37*$D$24 -> 4 | E37: =B37*$E$24 -> 8 | F37: =B37*$F$24 -> 12 | G37: =B37*$G$24 -> 16 | H37: =B37*$H$24 -> 20
B38: 3 | C38: Sedang | D38: =B38*$D$24 -> 3 | E38: =B38*$E$24 -> 6 | F38: =B38*$F$24 -> 9 | G38: =B38*$G$24 -> 12 | H38: =B38*$H$24 -> 15
B39: 2 | C39: Sedang Rendah | D39: =B39*$D$24 -> 2 | E39: =B39*$E$24 -> 4 | F39: =B39*$F$24 -> 6 | G39: =B39*$G$24 -> 8 | H39: =B39*$H$24 -> 10
B40: 1 | C40: Rendah | D40: =B40*$D$24 -> 1 | E40: =B40*$E$24 -> 2 | F40: =B40*$F$24 -> 3 | G40: =B40*$G$24 -> 4 | H40: =B40*$H$24 -> 5
C43: NILAI RISIKO POJK
C45: Indikator Risiko | D45: Nilai POJK 10
C46: RENDAH : | D46: 0 < NR ≤ 1
C47: SEDANG-RENDAH : | D47: 1 < NR ≤ 2
C48: SEDANG : | D48: 2 < NR ≤ 3
C49: SEDANG-TINGGI : | D49: 3 < NR ≤ 4
C50: TINGGI : | D50: 4 < NR ≤ 5
C51: Nilai Risiko Inheren
C52: NILAI RISIKO | D52: TINGKAT RISIKO
C53: 1x1 | D53: 1 | E53: RENDAH
C54: 1x2 | D54: 2 | E54: RENDAH
C55: 1x3 | D55: 3 | E55: RENDAH
C56: 2x1 | D56: 2 | E56: RENDAH
C57: 2x2 | D57: 4 | E57: RENDAH
C58: 3x1 | D58: 3 | E58: RENDAH
C59: 1x4 | D59: 4 | E59: SEDANG-RENDAH
C60: 1x5 | D60: 5 | E60: SEDANG-RENDAH
C61: 2x3 | D61: 6 | E61: SEDANG-RENDAH
C62: 2x4 | D62: 8 | E62: SEDANG-RENDAH
C63: 3x2 | D63: 6 | E63: SEDANG-RENDAH
C64: 3x3 | D64: 9 | E64: SEDANG-RENDAH
... C77: 5x4 | D77: 20 | E77: TINGGI

Sheet Panduan
A1: PANDUAN PENGISIAN | F1: Risiko
F2: Identifikasi | L2: Analisis | T2: Rencana Tindak Lanjut
F3: Kode/No | H3: Penjabaran Risiko/Peluang | I3: Kategori Risiko | J3: Nama Aset | K3: Kategori Aset | L3: Penyebab dan Akibat | N3: Pengendalian Saat Ini | O3: Kode (R/P) | P3: Tingkat Dampak | Q3: Tingkat Probabilitas | R3: Nilai Risiko | S3: Tingkat Risiko | T3: Rencana Penanganan Risiko | Y3: Analisis Risiko | AC3: Status | AD3: Sign off
L4: Penyebab | M4: Akibat | T4: Aktivitas | U4: PIC | V4: Target Waktu | W4: Rencana Reviu | X4: Hasil | Y4: Dampak | Z4: Probabilitas | AA4: Nilai Risiko Baru | AB4: Tingkat Risiko
F5: √ | G5: √ | H5: √ | I5: √ | J5: √ | K5: √ | L5: √ | M5: √ | N5: √ | O5: √ | P5: √ | Q5: √ | R5: √ | S5: √ | AA5: =Y5*Z5 -> 0
F6: Peluang
A7: RISK REGISTER | F7: Identifikasi | L7: Analisis | T7: Rencana Tindak Lanjut
F8: Kode/No | H8: Penjabaran Risiko/Peluang | I8: Kategori Risiko | J8: Nama Aset | K8: Kategori Aset | L8: Penyebab dan Akibat | N8: Pengendalian Saat Ini | O8: Kode (R/P) | P8: Tingkat Dampak | Q8: Tingkat Probabilitas | R8: Nilai Risiko | S8: Tingkat Risiko | T8: Rencana Penanganan Risiko | Y8: Analisis Risiko | AC8: Status | AD8: Sign off
A9: Revisi | C9: 0 | L9: Penyebab | M9: Akibat | T9: Aktivitas | U9: PIC | V9: Target Waktu | W9: Rencana Reviu | X9: Hasil | Y9: Dampak | Z9: Probabilitas | AA9: Nilai Risiko Baru | AB9: Tingkat Risiko
A10: Halaman | C10: 1 / 1 | F10: √ | G10: √ | H10: √ | I10: X | J10: √ | K10: √ | L10: √ | M10: √ | N10: √ | O10: √ | P10: √ | Q10: √ | R10: √ | S10: √ | AA10: =Y10*Z10 -> 0
A11: No | B11: Bagian | C11: Kolom | D11: Keterangan
A12: 1 | B12: Identifikasi | C12: Kode | D12: Diisi dengan 3 huruf awal nama Divisi/Departemen atau Diisi dengan 3 huruf awal setiap kata Divisi/Departemen yang lebih dari satu kata
C13: No | D13: Diisi dengan nomor urut risiko Divisi/Departemen
C14: Penjabaran Risiko/Peluang | D14: Risiko : Diisi dengan risiko yang mungkin terjadi atau sudah pernah terjadi di dalam Divisi/Departemen sebagai akibat dari suatu proses kerja. Peluang : Diisi dengan peluang yang mungkin terjadi sebagai akibat dari penggunaan aset dalam suatu proses kerja.
C15: Kategori Risiko | D15: Diisi dengan memilih 1 (satu) dari 9 (sembilan) kategori risiko di bawah ini: - Strategis - Operasional - Asuransi - Kredit - Pasar - Likuiditas - Hukum - Kepatuhan - Reputasi
C16: Nama Aset | D16: Sebutkan nama aset yang digunakan dalam suatu proses untuk mendukung bisnis/operasional perusahaan. Aset yang dicatat yang mengandung informasi/pendukung penyimpanan atau pengelolaan suatu informasi.
C17: Kategori Aset | D17: Diisi dengan memilih 1 (satu) dari 5 (lima) kategori aset di bawah ini: - Hardware - Software - Intangible - Dokumen/Informasi - People
B18: Analisis | C18: Penyebab | D18: Diisi dengan penyebab yang mungkin atau sudah pernah timbul dari risiko yang ada.
C19: Akibat | D19: Diisi dengan akibat yang mungkin atau sudah pernah timbul dari risiko yang ada.
C20: Pengendalian Saat Ini | D20: Diisi dengan tindakan yang dapat dilakukan oleh Divisi/Departemen terkait pada saat itu dalam mengatasi risiko yang timbul.
C21: Kode (R/P) | D21: Dipilih antara R (Risiko) atau P (Peluang) sesuai kolom penjabaran Risiko/Peluang yang diisi sebelumnya.
C22: Tingkat Dampak (D) | D22: Diisi dengan dampak yang mungkin atau sudah pernah timbul dari risiko yang ada berdasarkan parameter. *salah satu kondisi yang sesuai parameter dampak akan diperhitungkan menjadi nilai/tingkat dampak (Dapat dilihat pada Parameter)
C23: Tingkat Probabilitas (P) | D23: Diisi dengan tingkat frekuensi terjadi atau kemungkinan terjadinya risiko. (Dapat dilihat pada Parameter)
C24: Nilai Risiko | D24: Nilai risiko inheren (bawaan) yang muncul dan dirasakan oleh Divisi/Departemen. Dihitung dengan rumus: = D x P
C25: Tingkat Risiko | D25: Diisi dengan kriteria hasil risiko yang terjadi dari perhitungan DxP. (Dapat dilihat pada Parameter)
A26: 3 | B26: Rencana Tindak Lanjut (Khusus Nilai Risiko Yang Melewati Risk Appetite) | C26: Rencana Penanganan Risiko - Aktivitas | D26: Diisi dengan tindak lanjut yang direkomendasikan oleh fungsi Risk Management guna mengatasi risiko yang teridentifikasi. *Sesuai dengan Kebijakan dan Strategi Manajemen Risiko Perusahaan, untuk setiap Risiko memiliki Risk Appetite Tingkat 2 (Dua)
C27: Rencana Penanganan Risiko - PIC | D27: Diisi dengan penanggung jawab dari Divisi/Departemen terkait dalam melaksanakan tindak lanjut yang sudah ditentukan.
C28: Rencana Penanganan Risiko - Target Waktu | D28: Diisi dengan tanggal penyelesaian tindak lanjut dalam mengatasi risiko.
C29: Rencana Penanganan Risiko - Rencana Reviu | D29: Diisi dengan tanggal penilaian efektifitas tindak lanjut dalam mengatasi risiko.
C30: Rencana Penanganan Risiko - Hasil | D30: Bukti dari implementasi tindak lanjut yang dilaksanakan.
C31: Analisis Risiko - Dampak | D31: Tingkat keparahan yang dirasakan perusahaan/organisasi jika risiko terkait timbul.
C32: Analisis Risiko - Probabilitas | D32: Tingkat frekuensi terjadi atau kemungkinan terjadinya risiko.
C33: Analisis Risiko - Nilai Risiko Baru | D33: Nilai baru mengenai tingkat risiko yang muncul dan dirasakan oleh perusahaan/organisasi setelah ditindak lanjuti. Dihitung dengan rumus: = D x P
C34: Status (CLOSE/OPEN) | D34: Diisi dengan status pemantauan risiko yang ditindak lanjuti, apakah sudah teratasi atau belum.
C35: Sign off by | D35: Jika sudah teratasi dan status CLOSE, maka di tanda tangani oleh evaluator/reviewer
C36: Sign off date | D36: Diisi dengan tanggal sign off dilakukan.
