Workbook

Sheet (1) Informasi Unit Kerja
A1: Ringkasan Singkat Departemen Terkait Business Continuity
A3: Nama Departemen/Divisi | B3: : | C3: Product Management and Segmentation
A4: Deskripsi Tugas Pokok dan Fungsi | B4: : | C4: Product Management and segmentation terdiri dari 2 Department yaitu: 1. Product Development: bertanggung jawab merancang, mengembangkan, dan mengelola produk asuransi agar sesuai kebutuhan pasar, menguntungkan secara finansial, patuh regulasi, dan berkelanjutan. Fungsi utamanya mencakup product design, pricing bersama aktuaria, pengelolaan siklus hidup produk, koordinasi lintas fungsi, serta monitoring performa produk (profitabilitas, klaim, dan persistency. 2. Product Marketing: berfungsi sebagai penghubung strategis antara produk, brand, dan pasar. Dept ini memastikan setiap produk memiliki USP yang mudah dipahami, dan konsisten dengan positioning perusahaan, sekaligus menjaga reputasi dan citra korporasi. Tanggung jawab utamanya mencakup go-to-market strategy, messaging & storytelling produk, komunikasi internal dan eksternal, serta pengelolaan brand dan reputasi perusahaan. Kinerja fungsi ini berdampak langsung pada efektivitas penjualan, kepercayaan publik, dan kekuatan brand jangka panjang.
A5: Jumlah Karyawan | B5: : | C5: 9 orang
A6: Nama Pimpinan Departemen/Divisi | B6: : | C6: Ainsley Santoso
A7: Nama Koordinator Business Continuity | B7: : | C7: Ganjar Kurniawan, Muhamad Rolas Jayasaputra
A8: Tanggal Terakhir Update | B8: : | C8: 46174

Sheet Rekap
A3: Count of Prioritas (1 …5) (Diisi oleh Tim BCP)
A4: Row Labels | B4: Prioritas (High) | C4: Rendah (Low) | D4: Sangat Prioritas (Very High) | E4: Sedang (Medium) | F4: Sedang Rendah (Moderate to Low) | G4: Grand Total
A5: Accounting | B5: 1 | E5: 2 | F5: 13 | G5: 16
A6: Act Pricing | B6: 1 | E6: 2 | F6: 2 | G6: 5
A7: Act Valuation | E7: 1 | F7: 2 | G7: 3
A8: Bank Partnership AJK | D8: 2 | E8: 3 | G8: 5
A9: Business Support | D9: 2 | E9: 4 | G9: 6
A10: Claim | B10: 2 | E10: 4 | G10: 6
A11: Corporate Collection | B11: 4 | G11: 4
A12: Customer Analytics & Insight | F12: 3 | G12: 3
A13: Customer Engagement | F13: 3 | G13: 3
A14: CX Institutional | B14: 1 | E14: 1 | G14: 2
A15: EB | B15: 1 | E15: 1 | G15: 2
A16: Finance | C16: 1 | D16: 2 | E16: 1 | F16: 1 | G16: 5
A17: HCGA | D17: 5 | E17: 3 | F17: 2 | G17: 10
A18: Internal Audit | C18: 2 | E18: 1 | F18: 2 | G18: 5
A19: Investment | F19: 5 | G19: 5
A20: IT | B20: 6 | D20: 12 | G20: 18
A21: L & C | B21: 1 | D21: 2 | E21: 4 | F21: 1 | G21: 8
A22: Non Banking Partnership | B22: 3 | E22: 1 | G22: 4
A23: POS Partnership | B23: 7 | G23: 7
A24: Prodev | B24: 2 | E24: 2 | F24: 4 | G24: 8
A25: Provider | E25: 1 | G25: 1
A26: Reasuransi | C26: 3 | F26: 1 | G26: 4
A27: UW & NBA Institusional | B27: 6 | G27: 6
A28: Grand Total | B28: 35 | C28: 6 | D28: 25 | E28: 31 | F28: 39 | G28: 136

Sheet (2) Bisnis Proses System
B1: Keterkaitan Bisnis Proses dengan Sistem Informasi
G3: Aspek Dampak
A4: Divisi | B4: No. | C4: Bisnis Proses Kritikal | D4: Penjelasan Singkat Bisnis Proses Kritikal | E4: Prioritas (1 …5) (Diisi oleh Tim BCP) | F4: Scoring | G4: Finansial | H4: Waktu | I4: Operasional | J4: Reputasi | K4: Kepatuhan | L4: Manual Proses Saat Sistem Informasi Terganggu | M4: Minimum Resource Required | N4: Apa yang harus dilakukan jika sampai tenggang waktu tersebut, bisnis proses ini belum bisa tersedia
A5: Prodev | B5: 1 | C5: Produk Pricing dan Repricing | D5: Penetapan dan penyesuaian premi | E5: =(VLOOKUP(F5,Formula!$C$6:$D$26,2,FALSE)) -> Sedang Rendah (Moderate to Low) | F5: =G5+H5+I5+J5+K5 -> 10 | G5: 2 | H5: 2 | I5: 2 | J5: 2 | K5: 2 | L5: Excel Pricing template dan manual approval | M5: PM, ACT, RM | N5: Freeze penjualan produk terkait
A6: Prodev | B6: 2 | C6: Product Approval & Governance | D6: Persetujuan internal dan perubahannya | E6: =(VLOOKUP(F6,Formula!$C$6:$D$26,2,FALSE)) -> Sedang (Medium) | F6: =G6+H6+I6+J6+K6 -> 11 | G6: 2 | H6: 3 | I6: 2 | J6: 2 | K6: 2 | L6: Hardcopy sign off approval | M6: PM, ACT, INV, L&C, OPS | N6: Eskalasi ke management
A7: Prodev | B7: 3 | C7: Product Filing ke OJK | D7: Pelaporan/Persetujuan produk melalui sistem elektronik OJK | E7: =(VLOOKUP(F7,Formula!$C$6:$D$26,2,FALSE)) -> Sedang Rendah (Moderate to Low) | F7: =G7+H7+I7+J7+K7 -> 10 | G7: 2 | H7: 2 | I7: 3 | J7: 2 | K7: 1 | L7: Excel manual dokumen tracking | M7: PM, ACT, INV, OPS | N7: Mengirimkan dokumen secara offline ke OJK dan konfirmasi ke PIC OJK terkait
A8: Prodev | B8: 4 | C8: Produk Launch rediness | D8: Kesiapan produk sebelum go live (proses UAT) | E8: =(VLOOKUP(F8,Formula!$C$6:$D$26,2,FALSE)) -> Sedang Rendah (Moderate to Low) | F8: =G8+H8+I8+J8+K8 -> 10 | G8: 2 | H8: 2 | I8: 2 | J8: 2 | K8: 2 | L8: Manual checklist dan meeting kordinasi | M8: PM, ACT, IT, OPS, INV, FIN, ACC | N8: Eskalasi ke management untuk menunda peluncuran produk
A9: Prodev | B9: 5 | C9: Product Enhancement | D9: Penyesuaian manfaat & Fitur Produk | E9: =(VLOOKUP(F9,Formula!$C$6:$D$26,2,FALSE)) -> Sedang (Medium) | F9: =G9+H9+I9+J9+K9 -> 15 | G9: 3 | H9: 3 | I9: 3 | J9: 3 | K9: 3 | L9: Proposal Manual + Offline Simulation (Excel) | M9: PM, ACT, OPS | N9: Tunda enhancement, Freeze penjualan produk terkait/penjualan secara terbatas
A10: Prodev | B10: 6 | C10: Sales Illustration & Manfaat | D10: Ilustrasi manfaat dan simulasi premi | E10: =(VLOOKUP(F10,Formula!$C$6:$D$26,2,FALSE)) -> Sedang Rendah (Moderate to Low) | F10: =G10+H10+I10+J10+K10 -> 10 | G10: 2 | H10: 2 | I10: 2 | J10: 2 | K10: 2 | L10: Proposal Manual + Offline Simulation (Excel) | M10: PM, ACT, OPS | N10: Gunakan Excel Illustration, dan print secara manual
A11: Prodev | B11: 7 | C11: Produk Communication internal | D11: Sosialisasi internal dan external user | E11: =(VLOOKUP(F11,Formula!$C$6:$D$26,2,FALSE)) -> Prioritas (High) | F11: =G11+H11+I11+J11+K11 -> 17 | G11: 3 | H11: 3 | I11: 3 | J11: 3 | K11: 5 | L11: Mengunakan WA Group/Blast | M11: PM, Ops | N11: Email blast/Offline Training/Online training mengunakan 3rd party (Zoom, Gmet, WA Group Etc)
A12: Prodev | B12: 8 | C12: Lisence Sofware dan Aset Kreatif | D12: Subscription account dan annual fee untuk mengunakan layanan ini | E12: =(VLOOKUP(F12,Formula!$C$6:$D$26,2,FALSE)) -> Prioritas (High) | F12: =G12+H12+I12+J12+K12 -> 17 | G12: 3 | H12: 2 | I12: 3 | J12: 4 | K12: 5 | L12: Mengunakan Adobe Creative Suites | M12: PM | N12: Desain secara manual mengunakan Adobe Creative Series
A13: Accounting | B13: 1 | C13: Permintaan Dana - eBass | D13: Permintaan Dana (Payment Request, Supplier Invoice, Purchase Request) | E13: =(VLOOKUP(F13,Formula!$C$6:$D$26,2,FALSE)) -> Sedang (Medium) | F13: =G13+H13+I13+J13+K13 -> 12 | G13: 1 | H13: 3 | I13: 4 | J13: 3 | K13: 1 | L13: Pembayaran Manual terkait Permintaan Dana (Payment Request, Supplier Invoice, Purchase Request) | M13: 2 orang | N13: Koordinasi dengan Intenal Information Technologi, Satelkom terkait Permintaan Dana (Payment Request, Supplier Invoice, Purchase Request)
A14: Accounting | B14: 2 | C14: Upload dari Sistem EJC - eBass | D14: Upload dari Sistem EJC untuk Transaksi Individu Precential dan Transaksi Group Insurance | E14: =(VLOOKUP(F14,Formula!$C$6:$D$26,2,FALSE)) -> Sedang Rendah (Moderate to Low) | F14: =G14+H14+I14+J14+K14 -> 9 | G14: 1 | H14: 2 | I14: 2 | J14: 3 | K14: 1 | L14: Koordinasi dengan Intenal Information Technologi, Satelkom terkait Upload dari Sistem EJC untuk Transaksi Individu Precential dan Transaksi Group Insurance | M14: 2 orang | N14: Koordinasi dengan Intenal Information Technologi, Satelkom terkait Upload dari Sistem EJC untuk Transaksi Individu Precential dan Transaksi Group Insurance
A15: Accounting | B15: 3 | C15: Proses Laporan Keuangan - eBass | D15: Proses Penjurnalan dan Proses Laporan keuangan | E15: =(VLOOKUP(F15,Formula!$C$6:$D$26,2,FALSE)) -> Sedang Rendah (Moderate to Low) | F15: =G15+H15+I15+J15+K15 -> 9 | G15: 1 | H15: 2 | I15: 2 | J15: 3 | K15: 1 | L15: Koordinasi dengan Intenal Information Technologi, Satelkom terkait Proses Penjurnalan dan Proses Laporan keuangan | M15: 2 orang | N15: Koordinasi dengan Intenal Information Technologi, Satelkom terkait Proses Penjurnalan dan Proses Laporan keuangan
A16: Accounting | B16: 4 | C16: Input Kurs Akhir Bulan - eBass | D16: Input Kurs Akhir Bulan di eBass untuk Proses Laporan Keuangan | E16: =(VLOOKUP(F16,Formula!$C$6:$D$26,2,FALSE)) -> Sedang Rendah (Moderate to Low) | F16: =G16+H16+I16+J16+K16 -> 9 | G16: 1 | H16: 2 | I16: 2 | J16: 3 | K16: 1 | L16: Koordinasi dengan Intenal Information Technologi, Satelkom terkait Input Kurs Akhir Bulan di eBass untuk Proses Laporan Keuangan | M16: 1 orang | N16: Koordinasi dengan Intenal Information Technologi, Satelkom terkait Input Kurs Akhir Bulan di eBass untuk Proses Laporan Keuangan
... A34: Business Support | B34: 6 | C34: Vendor & Event Management | D34: Pengelolaan vendor program, event dan perjalanann insentif | E34: =(VLOOKUP(F34,Formula!$C$6:$D$26,2,FALSE)) -> Sedang (Medium) | F34: =G34+H34+I34+J34+K34 -> 15 | G34: 3 | H34: 4 | I34: 3 | J34: 4 | K34: 1 | L34: Koordinasi vendor melalui email/telepon Pengelolaan kontrak dan invoice secara manual Pencatatan kegiatan event offline | M34: Tim Business Services Dokumen kontrak vendor Akses komunikasi vendor | N34: Menunda atau menjadwalkan ulang event Negosiasi ulang dengan vendor Menyampaikan informasi perubahan kepada peserta
A35: POS Partnership | B35: 1 | C35: Pembayaran uang pensiun, resign, meninggal, tahapan, informasi saldo. | D35: Melakukan koordinasi dengan PIC perusahaan pengajuan surat pembayaran uang pensiun, resign, meninggal, tahapan, informasi saldo peserta dengan Finance dan Accounting Unit Link. | E35: =(VLOOKUP(F35,Formula!$C$6:$D$26,2,FALSE)) -> Prioritas (High) | F35: =G35+H35+I35+J35+K35 -> 20 | G35: 4 | H35: 4 | I35: 4 | J35: 4 | K35: 4 | M35: Email in-out by web dan 2 (dua) user | N35: (1) Permintaan data back up dari IT atas informasi tagihan kewajiban perusahaan update terakhir format excell. (2) Membuat perintah bayar ke Finance secara manual (word)
A36: POS Partnership | B36: =B35+1 -> 2 | C36: Pendaftaran kepesertaan | D36: Menerima pengajuan kepesertaan baik polis baru, penambahan, pengurangan peserta dari PIC perusahaan melalui surat/email dan memastikan pengajuan telah lengkap pengisian pada form pendaftaran untuk diproses lebih lanjut ke bagian New Business Administration (NBA) | E36: =(VLOOKUP(F36,Formula!$C$6:$D$26,2,FALSE)) -> Prioritas (High) | F36: =G36+H36+I36+J36+K36 -> 20 | G36: 4 | H36: 4 | I36: 4 | J36: 4 | K36: 4 | M36: Email in-out by web dan 2 (dua) user | N36: (1) Penarikan data peserta melalui data back up di IT untuk memastikan apakah peserta masih terdaftar atau tidak, (2) Pendaftaran peserta belum dapat diberikan
A37: POS Partnership | B37: =B36+1 -> 3 | C37: Penanganan penyelesaian pertanyaan/keluhan melalui email dan telepon baik dari PIC perusahaan, team marketing dan peserta | D37: Memberikan penjelasan atas pertanyaan, keluhan baik melalui email dan telepon dari PIC perusahaan, team Marketing, maupun peserta mengenai pengajuan pembayaran pensiun, resign, meninggal, tahapan, informasi saldo. | E37: =(VLOOKUP(F37,Formula!$C$6:$D$26,2,FALSE)) -> Prioritas (High) | F37: =G37+H37+I37+J37+K37 -> 20 | G37: 4 | H37: 4 | I37: 4 | J37: 4 | K37: 4 | M37: Email in-out by web dan 2 (dua) user | N37: (1) Melakukan pencatatan atas komplain yag diterima dalam format excell dan melakukan penelurusan atas data peserta (2) Penarikan data peserta melalui data back up di IT
A38: POS Partnership | B38: 4 | C38: Penanganan pengajuan klaim AJK & Retail | D38: Menerima pengajuan klaim, pengajuan refund dari nasabah baik secara hard copy maupun softcopy untuk meneruskan ke bagian terkait agar diproses lebih lanjut apabila dokumen yang diajukan telah sesuai persyaratan dan melakukan follow up apabila dokumen yang diajukan tidak memenuhi persyaratan | E38: =(VLOOKUP(F38,Formula!$C$6:$D$26,2,FALSE)) -> Prioritas (High) | F38: =G38+H38+I38+J38+K38 -> 20 | G38: 4 | H38: 4 | I38: 4 | J38: 4 | K38: 4 | M38: Email in-out by web dan 2 (dua) user | N38: (1) Penarikan data peserta melalui data back up di IT, (2) Meverifikasi dokumen yang telah diteriam dan memberikan informasi pengajuan klaim tersebut ke team Klaim melalui email
A39: POS Partnership | B39: 5 | C39: Pengiriman notifikasi email dan penyelesaian pertanyaan / keluhan dari nasabah | D39: 1. Pengiriman notifkasi klaim yang diajukan baik notifikasi klaim lengkap maupun notifikasi klaim pending apabila terdapat pengajuan dari nasabah melalui email blast 2. Pengajuan notifikasi refund atas pengajuan refund asuransi jiwa kredit baik notifikasi refund lengkap, refund pending apablla terdapat pengajuan dari nasabah melalui email blast 3. Pengiriman notifikasi klaim tolak, bayar atau investigasi apabila klaim telah dilakukan analisa oleh bagian klaim dengan menggunakan melalui email blast 4. Pengiriman notifikasi refund bayar, refund dengan nominal dibawah ketentuan dengan menggunakan email blast | E39: =(VLOOKUP(F39,Formula!$C$6:$D$26,2,FALSE)) -> Prioritas (High) | F39: =G39+H39+I39+J39+K39 -> 20 | G39: 4 | H39: 4 | I39: 4 | J39: 4 | K39: 4 | M39: Email in-out by web dan 2 (dua) user | N39: Melakukan pengiriman notifikasi email secara manual kepada peserta mengacu pada keputusan klaim
A40: POS Partnership | B40: 6 | C40: Pembuatan surat tolakan dan informasi klaim terpending karena investigasi | D40: Pembuatan surat informasi klaim tidak disantun serta informasi klaim terpending karena investigasi ke nasabah , setelah dokumen klaim dilakukan analisa oleh bagian klaim | E40: =(VLOOKUP(F40,Formula!$C$6:$D$26,2,FALSE)) -> Prioritas (High) | F40: =G40+H40+I40+J40+K40 -> 20 | G40: 4 | H40: 4 | I40: 4 | J40: 4 | K40: 4 | M40: Email in-out by web dan 2 (dua) user | N40: (1) Melakukan pembuatan surat penolakan dan klaim pending secara manual dengan mengacu pada berkas klaim yang telah diterima dan dasar penolakan yang diinfokan oleh team Klaim (2) Penarikan data back up dariIT untuk update data peserta baik AJK dan Retail
A41: POS Partnership | B41: 7 | C41: Perhitungan Tabel penurunan klaim AJK | D41: Menghitung tabel penurunan apabila terdapat pengajuan klaim AJK yang akan digunakan oleh bagian klaim sebagai acuan perhitungan pembayaran klaim | E41: =(VLOOKUP(F41,Formula!$C$6:$D$26,2,FALSE)) -> Prioritas (High) | F41: =G41+H41+I41+J41+K41 -> 20 | G41: 4 | H41: 4 | I41: 4 | J41: 4 | K41: 4 | M41: Email in-out by web dan 2 (dua) user | N41: (1) Membuat tabel penurunan peserta berdasarkan tabel penurunan secara keseluruhan format excell (2)Penarikan data back up dari IT untuk update data peserta baik AJK dan Retail
A42: Corporate Collection | B42: 1 | C42: Informasi tagihan premi atau provider | D42: Melakukan active phone call ke Nasabah untuk proses penagihan, mengirimkan softcopy tagihan terbaru via email kepada Nasabah yang menunggak. | E42: =(VLOOKUP(F42,Formula!$C$6:$D$26,2,FALSE)) -> Prioritas (High) | F42: =G42+H42+I42+J42+K42 -> 20 | G42: 4 | H42: 4 | I42: 4 | J42: 4 | K42: 4 | M42: Email in-out by web dan 2 (dua) user | N42: Mengajukan permintaan data back up dari IT atas informasi tagihan kewajiban perusahaan update terakhir format excell
A43: Corporate Collection | B43: =B42+1 -> 2 | C43: Informasi pembayaran ke Finance | D43: Pembayaran dari nasabah yang sudah sesuai dengan perincian Debit/ Credit Note diinformasikan ke Finance Account Receivable Departemen melalui email agar dapat segera dibukukan / diinput pelunasannya | E43: =(VLOOKUP(F43,Formula!$C$6:$D$26,2,FALSE)) -> Prioritas (High) | F43: =G43+H43+I43+J43+K43 -> 20 | G43: 4 | H43: 4 | I43: 4 | J43: 4 | K43: 4 | M43: Email in-out by web dan 2 (dua) user | N43: Menyampaikan informasi pembayaran ke Finance melalui email Equity dan WA
A44: Corporate Collection | B44: =B43+1 -> 3 | C44: Rekonsiliasi tagihan dengan nasabah | D44: Jika terjadi ketidaksesuaian antara pembayaran dan data Tagihan dan Kewajiban, maka Staff Group Collection melakukan rekonsiliasi melalui pertemuan dengan nasabah, telpon atau email. Pertemuan tersebut dapat dilakukan di PT Equity Life Indonesia atau di tempat nasabah | E44: =(VLOOKUP(F44,Formula!$C$6:$D$26,2,FALSE)) -> Prioritas (High) | F44: =G44+H44+I44+J44+K44 -> 20 | G44: 4 | H44: 4 | I44: 4 | J44: 4 | K44: 4 | M44: Email in-out by web dan 2 (dua) user | N44: Mengajukan permintaan data back up dari IT atas informasi tagihan kewajiban perusahaan update terakhir format excell
A45: Corporate Collection | B45: =B44+1 -> 4 | C45: Buka Pending | D45: Memberikan rekomendasi atas cara bayar tagihan premi dan provider | E45: =(VLOOKUP(F45,Formula!$C$6:$D$26,2,FALSE)) -> Prioritas (High) | F45: =G45+H45+I45+J45+K45 -> 20 | G45: 4 | H45: 4 | I45: 4 | J45: 4 | K45: 4 | M45: Email in-out by web dan 2 (dua) user | N45: Konfirmasi ke pihak ke-3 (team penjaminan) untuk dapat melakukan penalangan full cover terlebih dahulu atas setiap penjaminan yang ada
A46: Non Banking Partnership | B46: 1 | C46: Pendaftaran peserta AJK | D46: Penerimaan data peserta AJK dari partner untuk diproses registrasi kepesertaan ke sistem ELI | E46: =(VLOOKUP(F46,Formula!$C$6:$D$26,2,FALSE)) -> Prioritas (High) | F46: =G46+H46+I46+J46+K46 -> 17 | G46: 5 | H46: 4 | I46: 4 | J46: 2 | K46: 2 | L46: Menampung data kepesertaan manual melalui email untuk kemudian diupload setelah sistem sudah bisa diakses kembali | M46: UW NBA 1 orang dan SBU NBI 1 orang : Menampung sementara data pendaftaran kepesertaan dari partner melalui Email untuk file nya bisa disimpan lalu kemudian bisa di upload ke sistem AJK ELI. | N46: Menginformasikan ke partner untuk bisa mengirimkan ulang file pendaftaran peserta secara manual.
A47: Non Banking Partnership | B47: 2 | C47: Pembelian produk asuransi melalui microsite | D47: Kesiapan dan ketersediaan akses microsite agar calon nasabah bisa melakukan pembelian asuransi | E47: =(VLOOKUP(F47,Formula!$C$6:$D$26,2,FALSE)) -> Sangat Prioritas (Very High) | F47: =G47+H47+I47+J47+K47 -> 21 | G47: 5 | H47: 4 | I47: 5 | J47: 5 | K47: 2 | L47: Tidak ada | M47: Tidak ada karena proses pembelian asuransi melalui microsite ini customer harus melakukan pengisian data pribadi, ahli waris, dan pembayaran secara mandiri melalui microsite. | N47: Menginformasikan ke partner untuk tidak menawarkan produk asuransi Microsite sebelum sistem bisa diakses kembali
A48: Non Banking Partnership | B48: 3 | C48: Proses rekonsiliasi | D48: Proses penarikan jumlah data peserta asuransi untuk disesuaikan dengan jumlah yang ada di partner untuk dilakukan rekonsiliasi | E48: =(VLOOKUP(F48,Formula!$C$6:$D$26,2,FALSE)) -> Sedang (Medium) | F48: =G48+H48+I48+J48+K48 -> 15 | G48: 5 | H48: 4 | I48: 2 | J48: 2 | K48: 2 | L48: Tidak ada | M48: Tidak ada karena data rekap kepesertaan untuk melalui rekon hanya tersedia di sistem AJK untuk melakukan rekonsiliasi. | N48: Menginformasikan ke partner perihal terterlambatan yang terjadi untuk melakukan proses rekonsiliasi
A49: Non Banking Partnership | B49: 4 | C49: Proses Pengajuan Claim | D49: Menerima dan memproses pengajuan claim dari nasabah Non Banking | E49: =(VLOOKUP(F49,Formula!$C$6:$D$26,2,FALSE)) -> Prioritas (High) | F49: =G49+H49+I49+J49+K49 -> 18 | G49: 1 | H49: 4 | I49: 5 | J49: 5 | K49: 3 | L49: Menampung data pengajuan klaim manual melalui email untuk kemudian di daftarkan ke sistem setelah sudah bisa diakses | M49: CS 1 orang& SBU NBI 1 orang: Menampung sementara data pendaftaran kepesertaan dari partner melalui Email dan melakukan listing manual dengan Excel untuk bisa di tampung dan di tracking hingga sistem portal klaim Retail ELI bisa di proses. | N49: Menginformasikan ke partner bahwa terjadi kendala dalam proses registrasi pengajuan claim dan ada potensi keterlambatan SLA Claim
A50: Bank Partnership AJK | B50: 1 | C50: Pendaftaran peserta AJK (Harian) | D50: Penerimaan data peserta AJK dari partner untuk diproses registrasi kepesertaan ke sistem ELI | E50: =(VLOOKUP(F50,Formula!$C$6:$D$26,2,FALSE)) -> Sangat Prioritas (Very High) | F50: =G50+H50+I50+J50+K50 -> 23 | G50: 5 | H50: 5 | I50: 5 | J50: 5 | K50: 3
A51: Bank Partnership AJK | B51: 2 | C51: Proses Penanganan Keluhan (Harian) | D51: Proses menerima, menanggapi dan mengangani keluhan Partner atas produk dan proses asuransi | E51: =(VLOOKUP(F51,Formula!$C$6:$D$26,2,FALSE)) -> Sedang (Medium) | F51: =G51+H51+I51+J51+K51 -> 15 | G51: 3 | H51: 3 | I51: 3 | J51: 3 | K51: 3
A52: Bank Partnership AJK | B52: 3 | C52: Proses Pengajuan Claim dan Refund Premi (Harian) | D52: Menerima dan memproses pengajuan claim, dan Refund Premi (karena pelunasan dipercepat) dari Bank Partner | E52: =(VLOOKUP(F52,Formula!$C$6:$D$26,2,FALSE)) -> Sangat Prioritas (Very High) | F52: =G52+H52+I52+J52+K52 -> 23 | G52: 5 | H52: 5 | I52: 5 | J52: 5 | K52: 3
A53: Bank Partnership AJK | B53: 4 | C53: Proses perhitungan Fee Base Income Partner AJK (bulanan) | D53: Perhitungan FBI bulanan Bank Partner | E53: =(VLOOKUP(F53,Formula!$C$6:$D$26,2,FALSE)) -> Sedang (Medium) | F53: =G53+H53+I53+J53+K53 -> 15 | G53: 3 | H53: 3 | I53: 3 | J53: 3 | K53: 3
A54: Bank Partnership AJK | B54: 5 | C54: Proses rekonsiliasi (Bulanan) | D54: Proses penarikan jumlah data peserta asuransi untuk disesuaikan dengan jumlah yang ada di partner untuk dilakukan rekonsiliasi | E54: =(VLOOKUP(F54,Formula!$C$6:$D$26,2,FALSE)) -> Sedang (Medium) | F54: =G54+H54+I54+J54+K54 -> 15 | G54: 3 | H54: 3 | I54: 3 | J54: 3 | K54: 3
A55: Claim | B55: 1 | C55: Data upload harian klaim dari TPA (Admedika) | D55: Data klaim peserta yang telah diproses akan di upload ke core system. Proses upload data yang tidak berjalan menyebabkan tim klaim tidak dapat memproses / melanjutkan proses perhitungan hingga pembayarannya | E55: =(VLOOKUP(F55,Formula!$C$6:$D$26,2,FALSE)) -> Prioritas (High) | F55: =G55+H55+I55+J55+K55 -> 17 | G55: 4 | H55: 3 | I55: 5 | J55: 3 | K55: 2 | L55: Saat ini belum bisa dilakukan manual proses untuk sistem group karena dapat menyebabkan perbedaan data dengan yang ada di TPA | M55: - 11 tim klaim - Tim IT | N55: Perhitungan klaim dapat dismulasikan dahulu di UAT environment jika memungkinkan sehingga bisa dihitung secara manual (dengan kondisi kendala sudah terlalu lama belum terselesaikan)
A56: Claim | B56: 2 | C56: Pemrosesan hingga pembayaran klaim harian menggunakan core system PL | D56: Klaim diinput atau di upload ke core system selanjutnya akan di proses perhitungan oleh sistem sesuai dengan manfaat atau santunannya lalu di buatkan perintah pembayarannya | E56: =(VLOOKUP(F56,Formula!$C$6:$D$26,2,FALSE)) -> Sedang (Medium) | F56: =G56+H56+I56+J56+K56 -> 14 | G56: 4 | H56: 3 | I56: 3 | J56: 2 | K56: 2 | L56: - Melakukan analisa klaim dahulu hingga bisa diinput di dalam sistem core jika sistem tidak dapat diakses - Jika sistem bisa diakses namun terdapat error saat melakukan pemrosesan klaimnya maka dilakukan manual proses dahulu dan membuat rekap atas klaim-klaim yang diproses manual agar saat sistem sudah berjalan lancar, tidak terjadi proses double payment | M56: - 3 tim klaim - Tim IT | N56: Membagi beban kerja berdasarkan urgensi untuk meminimalkan dampak reputasi. Misal : 1. Klaim dengan jumlah besar dan yang sedang dalam proses sebelum sistem down / error didahulukan 2. Klaim yang masuk saat sistem down / error dikelompokkan menjadi satu 3. Klaim yang membutuhkan waktu proses investigasi di proses belakangan.
A57: Claim | B57: 3 | C57: Pemrosesan hingga pembayaran klaim harian menggunakan core system AJK | D57: Klaim diinput atau di upload ke core system selanjutnya akan di proses perhitungan oleh sistem sesuai dengan manfaat atau santunannya lalu di buatkan perintah pembayarannya | E57: =(VLOOKUP(F57,Formula!$C$6:$D$26,2,FALSE)) -> Sedang (Medium) | F57: =G57+H57+I57+J57+K57 -> 14 | G57: 3 | H57: 3 | I57: 3 | J57: 3 | K57: 2 | L57: - Manual proses. - Membuat rekap atas klaim-klaim yang diproses manual agar saat sistem dapat beroperasi kembali, tidak terjadi proses double payment | M57: - 4 tim klaim - Tim IT | N57: Membagi beban kerja berdasarkan urgensi untuk meminimalkan dampak reputasi. Misal : 1. Klaim dengan jumlah besar dan yang sedang dalam proses sebelum sistem down / error didahulukan 2. Klaim yang masuk saat sistem down / error dikelompokkan menjadi satu 3. Klaim yang membutuhkan waktu proses investigasi di proses belakangan.
A58: Claim | B58: 4 | C58: Pemrosesan hingga pembayaran klaim harian menggunakan core system Group Insurance | D58: Klaim diinput atau di upload ke core system selanjutnya akan di proses perhitungan oleh sistem sesuai dengan manfaat atau santunannya lalu di buatkan perintah pembayarannya | E58: =(VLOOKUP(F58,Formula!$C$6:$D$26,2,FALSE)) -> Prioritas (High) | F58: =G58+H58+I58+J58+K58 -> 17 | G58: 4 | H58: 3 | I58: 5 | J58: 3 | K58: 2 | L58: Saat ini belum bisa dilakukan manual proses untuk sistem group karena dapat menyebabkan perbedaan data dengan yang ada di TPA | M58: - 11 tim klaim - Tim IT | N58: Perhitungan klaim dapat dismulasikan dahulu di UAT environment jika memungkinkan sehingga bisa dihitung secara manual (dengan kondisi kendala sudah terlalu lama belum terselesaikan)
A59: Claim | B59: 5 | C59: Pengajuan klaim harian melalui Web Portal | D59: Pengajuan klaim khususnya Polis yang menggunakan Web Portal yang terkoneksi secara API dengan TPA (AAA) | E59: =(VLOOKUP(F59,Formula!$C$6:$D$26,2,FALSE)) -> Sedang (Medium) | F59: =G59+H59+I59+J59+K59 -> 12 | G59: 3 | H59: 3 | I59: 3 | J59: 2 | K59: 1 | L59: Nasabah dapat mengirimkan pengajuan klaim via email atau hardcopy | N59: Nasabah dapat mengirimkan pengajuan klaim via email atau hardcopy
A60: Claim | B60: 6 | C60: Pengajuan klaim harian melalui Mobile Apps | D60: Klaim yang diajukan secara digital (E Claim Submission) akan masuk ke file SFTP dan selanjutnya dikirim ke TPA untuk di proses | E60: =(VLOOKUP(F60,Formula!$C$6:$D$26,2,FALSE)) -> Sedang (Medium) | F60: =G60+H60+I60+J60+K60 -> 11 | G60: 2 | H60: 3 | I60: 3 | J60: 2 | K60: 1 | L60: Nasabah dapat mengirimkan pengajuan klaim via email atau hardcopy | N60: Nasabah dapat mengirimkan pengajuan klaim via email atau hardcopy
A61: HCGA | B61: 1 | C61: Bulanan | D61: Proses pembayaran upah bagi Karyawan | E61: =(VLOOKUP(F61,Formula!$C$6:$D$26,2,FALSE)) -> Sangat Prioritas (Very High) | F61: =G61+H61+I61+J61+K61 -> 23 | G61: 5 | H61: 5 | I61: 5 | J61: 5 | K61: 3 | L61: - | M61: 2
A62: HCGA | B62: 2 | C62: Bulanan | D62: Pembayaran BPJS Ketenagakerjaan Karyawan | E62: =(VLOOKUP(F62,Formula!$C$6:$D$26,2,FALSE)) -> Sangat Prioritas (Very High) | F62: =G62+H62+I62+J62+K62 -> 23 | G62: 5 | H62: 5 | I62: 5 | J62: 5 | K62: 3 | L62: HC input diaplikasi dan download tagihan di sistem kemudian ke finance utk pembayaran | M62: 2
A63: HCGA | B63: 3 | C63: Bulanan | D63: Pembayaran BPJS Kesehatan Karyawan | E63: =(VLOOKUP(F63,Formula!$C$6:$D$26,2,FALSE)) -> Sangat Prioritas (Very High) | F63: =G63+H63+I63+J63+K63 -> 23 | G63: 5 | H63: 5 | I63: 5 | J63: 5 | K63: 3 | L63: HC download billing invoice dari edabu (sistem bpjs) kemudian ke finance utk pembayaran | M63: 2
A64: HCGA | B64: 4 | C64: Bulanan | D64: Pembayaran Pajak Penghasilan Karyawan | E64: =(VLOOKUP(F64,Formula!$C$6:$D$26,2,FALSE)) -> Sangat Prioritas (Very High) | F64: =G64+H64+I64+J64+K64 -> 23 | G64: 5 | H64: 5 | I64: 5 | J64: 5 | K64: 3 | M64: 2
A65: HCGA | B65: 5 | C65: Bulanan | D65: Pelaporan Pajak Penghasilan Karyawan | E65: =(VLOOKUP(F65,Formula!$C$6:$D$26,2,FALSE)) -> Sangat Prioritas (Very High) | F65: =G65+H65+I65+J65+K65 -> 23 | G65: 5 | H65: 5 | I65: 5 | J65: 5 | K65: 3 | M65: 2
A66: HCGA | B66: 6 | C66: Bulanan | D66: Pembayaran Listrik, Air dan Internet | E66: =(VLOOKUP(F66,Formula!$C$6:$D$26,2,FALSE)) -> Sedang (Medium) | F66: =G66+H66+I66+J66+K66 -> 11 | G66: 2 | H66: 2 | I66: 3 | J66: 2 | K66: 2 | M66: 1 | N66: Melakukan pembayaran langsung lewat internet
A67: HCGA | B67: 7 | C67: Bulanan | D67: Pembayaran IPL | E67: =(VLOOKUP(F67,Formula!$C$6:$D$26,2,FALSE)) -> Sedang (Medium) | F67: =G67+H67+I67+J67+K67 -> 11 | G67: 2 | H67: 2 | I67: 3 | J67: 2 | K67: 2 | M67: 1 | N67: Melakukan pembayaran langsung lewat internet
A68: HCGA | B68: 8 | C68: Bulanan | D68: Pembayaran Maintenance Lift - Raden Saleh | E68: =(VLOOKUP(F68,Formula!$C$6:$D$26,2,FALSE)) -> Sedang Rendah (Moderate to Low) | F68: =G68+H68+I68+J68+K68 -> 10 | G68: 2 | H68: 2 | I68: 2 | J68: 2 | K68: 2 | M68: 1
A69: HCGA | B69: 9 | C69: Bulanan | D69: Pembayaran ekspedisi - tergantung invoice | E69: =(VLOOKUP(F69,Formula!$C$6:$D$26,2,FALSE)) -> Sedang (Medium) | F69: =G69+H69+I69+J69+K69 -> 12 | G69: 2 | H69: 2 | I69: 3 | J69: 3 | K69: 2 | M69: 1
A70: HCGA | B70: 10 | C70: Tergantung Kebutuhan | D70: Pemesaran tiket dan akomodasi perjalanan dinas | E70: =(VLOOKUP(F70,Formula!$C$6:$D$26,2,FALSE)) -> Sedang Rendah (Moderate to Low) | F70: =G70+H70+I70+J70+K70 -> 10 | G70: 2 | H70: 2 | I70: 2 | J70: 2 | K70: 2 | M70: 1
A71: Finance | B71: 1 | C71: Proses Pembayaran melalui Internet Banking | D71: Proses pembayaran kepada Nasabah dan atau pihak ketiga harus tetap dapat dijalankan | E71: =(VLOOKUP(F71,Formula!$C$6:$D$26,2,FALSE)) -> Sangat Prioritas (Very High) | F71: =G71+H71+I71+J71+K71 -> 21 | G71: 4 | H71: 5 | I71: 4 | J71: 5 | K71: 3 | L71: - Menginformasikan kepada Dept terkait bahwa pembayaran terhambat, - Membuat Cek/BG ke Bank, - Menggunakan tethering internet HP untuk koneksi internet banking | M71: - 4 orang - Sistem PrecentiaLIfe (PL), E-Bas, EJC, Group Insurance, Internet Banking | N71: - Menginformasikan kepada Dept terkait bahwa pembayaran terhambat, - Membuat Cek/BG ke Bank, - Menggunakan tethering internet HP untuk koneksi internet banking
A72: Finance | B72: 2 | C72: Proses Auto Debet | D72: Proses auto debet premi asuransi individu harus tetap dapat berjalan agar premi dapat tetap tertagih sesuai jadwal pendebetan | E72: =(VLOOKUP(F72,Formula!$C$6:$D$26,2,FALSE)) -> Sangat Prioritas (Very High) | F72: =G72+H72+I72+J72+K72 -> 21 | G72: 5 | H72: 4 | I72: 4 | J72: 5 | K72: 3 | L72: - Menginformasikan kepada Dept terkait dan Bank Partner bahwa proses auto debet terlambat | M72: - 4 orang - Sistem PrecentiaLIfe (PL),Internet Banking, Email, Bank Partner | N72: - Menginformasikan kepada Dept terkait dan Bank Partner bahwa proses auto debet terlambat
A73: Finance | B73: 3 | C73: Proses CP Batch Peneriman Premi Individu | D73: Proses triger cut off penentuan tanggal valuta unit link tidak dapat dilakukan dan proses subscription ke Bank Kustodian terhambat | E73: =(VLOOKUP(F73,Formula!$C$6:$D$26,2,FALSE)) -> Sedang Rendah (Moderate to Low) | F73: =G73+H73+I73+J73+K73 -> 10 | G73: 2 | H73: 2 | I73: 2 | J73: 1 | K73: 3 | L73: - Melakukan koordinasi dengan Bank Kustodian bahwa proses subscription terlambat | M73: - 4 orang - Sistem PrecentiaLIfe (PL), Email, Bank Partner | N73: - Melakukan koordinasi dengan Bank Kustodian bahwa proses subscription terlambat
A74: Finance | B74: 4 | C74: Penerimaan Premi Virtual Account (Online/API) | D74: Pembukuan penerimaan premi virtual account terhambat | E74: =(VLOOKUP(F74,Formula!$C$6:$D$26,2,FALSE)) -> Sedang (Medium) | F74: =G74+H74+I74+J74+K74 -> 11 | G74: 2 | H74: 2 | I74: 2 | J74: 2 | K74: 3 | L74: - Melakukan koordinasi dengan IT terkait data transaksi virtual account | M74: - 2 orang - Sistem PrecentiaLIfe (PL), PL Satelite, DB Payment, Bank Partner | N74: - Melakukan koordinasi dengan IT terkait data transaksi virtual account
A75: Finance | B75: 5 | C75: Proses Rekonsiliasi Bank | D75: Proses Rekonsiliasi Bank (Penerimaan dan Pengeluaran) | E75: =(VLOOKUP(F75,Formula!$C$6:$D$26,2,FALSE)) -> Rendah (Low) | F75: =G75+H75+I75+J75+K75 -> 5 | G75: 1 | H75: 1 | I75: 1 | J75: 1 | K75: 1 | L75: - Melakukan koordinasi dengan Accounting terkait data rekonsiliasi bank | M75: - 4 orang | N75: - Melakukan koordinasi dengan Accounting terkait data rekonsiliasi bank
A76: UW & NBA Institusional | B76: 1 | C76: Pengaktifan Polis EB, AJK & Retail Insurance | D76: Proses pengaktifan polis EB, AJK & Retail Insurance pada Sistem | E76: =(VLOOKUP(F76,Formula!$C$6:$D$26,2,FALSE)) -> Prioritas (High) | F76: =G76+H76+I76+J76+K76 -> 16 | G76: 4 | H76: 1 | I76: 4 | J76: 5 | K76: 2 | L76: Merekap JO Order yang masuk agar pengaktifan apabila sistem sudah berjalan tidak terlewat | M76: Jumlah SDM: 1 Jumlah Sistem: 2 Jumlah Vendor: 2 | N76: Menginformasikan kepada marketing & CS agar disampaikan kepada pihak Perusahaan dan koordinasi dengan CS untuk dilakukan penjaminan manual apabila nasabah masuk Rumah Sakit (nasabah EB)
A77: UW & NBA Institusional | B77: 2 | C77: Pembuatan Polis EB, AJK & Retail Insurance | D77: Memproses pembuatan dokumen hardcopy Polis EB, AJK & Retail Insurance secara manual Note : untuk polis EB masih menggunakan sistem group insurance untuk mencetak produk polis yang dilampirkan pada dokumen hardcopy polis | E77: =(VLOOKUP(F77,Formula!$C$6:$D$26,2,FALSE)) -> Prioritas (High) | F77: =G77+H77+I77+J77+K77 -> 16 | G77: 4 | H77: 1 | I77: 4 | J77: 5 | K77: 2 | L77: Memproses draft polis terlebih dahulu dan lampiran akan disertakan ketika sistem sudah berjalan | M77: Jumlah SDM: 1 Jumlah Sistem: 2 Jumlah Vendor: - | N77: Menginformasikan kepada marketing & CS agar disampaikan kepada pihak Perusahaan dikarenakan adanya keterlambatan pengiriman hardcopy polis
A78: UW & NBA Institusional | B78: 3 | C78: Pendaftaran, penambahan & perubahan peserta EB, AJK & Retail Insurance | D78: Memproses pendaftaran, penambahan & perubahan peserta EB, AJK & Retail Insurance | E78: =(VLOOKUP(F78,Formula!$C$6:$D$26,2,FALSE)) -> Prioritas (High) | F78: =G78+H78+I78+J78+K78 -> 16 | G78: 4 | H78: 1 | I78: 4 | J78: 5 | K78: 2 | L78: Merekap penambahan, perubahan dan pengurangan agar tidak terlewat ketika proses pada sistem apabila sudah berjalan | M78: Jumlah SDM: 2 Jumlah Sistem: 2 Jumlah Vendor: 3 | N78: Menginformasikan kepada marketing & CS agar disampaikan kepada pihak Perusahaan dan koordinasi dengan CS untuk dilakukan penjaminan manual apabila nasabah masuk Rumah Sakit (nasabah EB)
A79: UW & NBA Institusional | B79: 4 | C79: Penerbitan Debit Note/Credit Note EB, AJK & Retail Insurance | D79: Memproses penerbitan Debit Note/Credit Note EB, AJK & Retail Insurance yang kemudian akan di email kepada PIC Perusahaan | E79: =(VLOOKUP(F79,Formula!$C$6:$D$26,2,FALSE)) -> Prioritas (High) | F79: =G79+H79+I79+J79+K79 -> 16 | G79: 4 | H79: 1 | I79: 4 | J79: 5 | K79: 2 | L79: Merekap penambahan, perubahan dan pengurangan peserta yang belum diterbitkan debit/credit note | M79: Jumlah SDM: 2 Jumlah Sistem: 2 Jumlah Vendor: 3 | N79: Apabila sistem tidak berjalan dalam jangka waktu yang lama, maka perhitungan premi akan dilakukan secara manual menggunakan excel kemudian akan dibuatkan debit/credit note secara manual untuk dikirimkan kepada nasabah
A80: UW & NBA Institusional | B80: 5 | C80: Pengiriman Plan Import & Enrollment Peserta kepada pihak TPA | D80: Memproses import plan & enrollment peserta EB kepada TPA | E80: =(VLOOKUP(F80,Formula!$C$6:$D$26,2,FALSE)) -> Prioritas (High) | F80: =G80+H80+I80+J80+K80 -> 16 | G80: 4 | H80: 1 | I80: 4 | J80: 5 | K80: 2 | L80: Menginformasikan kepada pihak TPA untuk dapat memproses manual New Business maupun renewal | M80: Jumlah SDM: 2 Jumlah Sistem: 2 Jumlah Vendor: 3 | N80: Menginformasikan kepada pihak TPA, agar dapat proses ini dapat dilakukan secara manual agar pelayanan kepada nasabah EB tetap berjalan
A81: UW & NBA Institusional | B81: 6 | C81: Pengiriman Plan Import & Enrollment Peserta kepada pihak Telemedicine | D81: Memproses import plan & enrollment peserta EB kepada telemedicine | E81: =(VLOOKUP(F81,Formula!$C$6:$D$26,2,FALSE)) -> Prioritas (High) | F81: =G81+H81+I81+J81+K81 -> 16 | G81: 4 | H81: 1 | I81: 4 | J81: 5 | K81: 2 | L81: Menginformasikan kepada pihak telemedicine untuk dapat memproses manual New Business maupun renewal | M81: Jumlah SDM: 2 Jumlah Sistem: 2 Jumlah Vendor: 3 | N81: Menginformasikan kepada pihak TPA, agar dapat proses ini dapat dilakukan secara manual agar pelayanan kepada nasabah EB tetap berjalan
A82: Provider | B82: 1 | C82: Input Master Provider di system Group Insurance | D82: User PR akan melakukan registrasi master di system Group Insurance | E82: =(VLOOKUP(F82,Formula!$C$6:$D$26,2,FALSE)) -> Sedang (Medium) | F82: =G82+H82+I82+J82+K82 -> 12 | G82: 2 | H82: 1 | I82: 3 | J82: 3 | K82: 3 | L82: Daftar Provider yang di email setiap bulan | M82: Akses ke email account | N82: Menggunakan daftar provider manual
A83: Act Pricing | B83: 1 | C83: Maintenance Parameter Product (Sewaktu-waktu) | D83: Melakukan Input dan Upload parameter produk individu sesuai spesifikasi produk | E83: =(VLOOKUP(F83,Formula!$C$6:$D$26,2,FALSE)) -> Prioritas (High) | F83: =G83+H83+I83+J83+K83 -> 17 | G83: 2 | H83: 2 | I83: 5 | J83: 5 | K83: 3 | L83: Melanjutkan kembali proses maintenance parameter product | M83: 1 | N83: Tidak ada manual proses
A84: Act Pricing | B84: 2 | C84: Analisa Rasio Klaim Asuransi Kumpulan (Harian) | D84: Melakukan penarikan data premi dan klaim produk asuransi kumpulan | E84: =(VLOOKUP(F84,Formula!$C$6:$D$26,2,FALSE)) -> Sedang (Medium) | F84: =G84+H84+I84+J84+K84 -> 13 | G84: 2 | H84: 1 | I84: 3 | J84: 5 | K84: 2 | L84: Melanjutkan proses penarikan data rasio klaim | M84: 1 | N84: Tidak ada manual proses
A85: Act Pricing | B85: 3 | C85: Perhitungan Rasio Klaim dan Profit Sharing Produk AJK (Sewaktu-waktu) | D85: Melakukan penarikan database yang dibutuhkan dari sistem AJK | E85: =(VLOOKUP(F85,Formula!$C$6:$D$26,2,FALSE)) -> Sedang (Medium) | F85: =G85+H85+I85+J85+K85 -> 13 | G85: 2 | H85: 2 | I85: 3 | J85: 4 | K85: 2 | L85: Melanjutkan kembali proses perhitungan rasio klaim dan profit sharing | M85: 1 | N85: Menginformasikan kepada bagian terkait adanya kendala yang menghambat proses pekerjaan dan melakukan koordinasi dengan bagian terkait
A86: Act Pricing | B86: 4 | C86: Perhitungan Teknis Perubahan Polis (Sewaktu-waktu) | D86: Melakukan pengecekan data Polis Individu | E86: =(VLOOKUP(F86,Formula!$C$6:$D$26,2,FALSE)) -> Sedang Rendah (Moderate to Low) | F86: =G86+H86+I86+J86+K86 -> 10 | G86: 1 | H86: 2 | I86: 2 | J86: 3 | K86: 2 | L86: Melanjutkan kembali proses perhitungan perubahan polis | M86: 1 | N86: Menginformasikan kepada bagian terkait adanya kendala yang menghambat proses pekerjaan dan melakukan koordinasi dengan bagian terkait
A87: Act Pricing | B87: 5 | C87: Proses Approval Discount Contact Person (DCP) (Sewaktu-waktu) | D87: Melakukan approval Discount Contact Person pada sistem yang sudah diinput oleh bagian admin support | E87: =(VLOOKUP(F87,Formula!$C$6:$D$26,2,FALSE)) -> Sedang Rendah (Moderate to Low) | F87: =G87+H87+I87+J87+K87 -> 8 | G87: 1 | H87: 1 | I87: 2 | J87: 2 | K87: 2 | L87: Melanjutkan kembali proses approval (DCP) | M87: 1 | N87: Menginformasikan kepada bagian terkait adanya kendala yang menghambat proses pekerjaan dan melakukan koordinasi dengan bagian terkait
A88: Act Valuation | B88: 1 | C88: Proses data untuk keperluan laporan keuangan regular ke OJK (cadangan, laporan operasional, laporan aktuaris, laporan rencana bisnis, laporan IFRS 17, data polis, laporan VONB, dll) | D88: Pembuatan laporan untuk dikirim ke OJK sesuai dengan batas waktu yang telah ditentukan. | E88: =(VLOOKUP(F88,Formula!$C$6:$D$26,2,FALSE)) -> Sedang (Medium) | F88: =G88+H88+I88+J88+K88 -> 13 | G88: 3 | H88: 3 | I88: 2 | J88: 2 | K88: 3 | L88: Tidak ada proses manual | M88: 5 | N88: Segera menginformasikan kepada bagian terkait atas kendala di pihak ke-3 tersebut yang berdampak pada keterlambatan proses perhitungan laporan ke OJK
A89: Act Valuation | B89: 2 | C89: Proses data untuk keperluan laporan internal (expense loading, VoNB, EV) | D89: Pembuatan laporan untuk keperluan internal dan management. | E89: =(VLOOKUP(F89,Formula!$C$6:$D$26,2,FALSE)) -> Sedang Rendah (Moderate to Low) | F89: =G89+H89+I89+J89+K89 -> 9 | G89: 3 | H89: 3 | I89: 1 | J89: 1 | K89: 1 | L89: Tidak ada proses manual | M89: 5 | N89: Segera menginformasikan kepada bagian terkait atas kendala di pihak ke-3 tersebut yang berdampak pada keterlambatan proses perhitungan laporan internal
A90: Act Valuation | B90: 3 | C90: Proses experience study (tingkat mortalita, tingkat polis lapse, loss ratio, biaya) | D90: Untuk menentukan asumsi aktuaria yang digunakan untuk menghitung cadangan dan proyeksi laporan keuangan | E90: =(VLOOKUP(F90,Formula!$C$6:$D$26,2,FALSE)) -> Sedang Rendah (Moderate to Low) | F90: =G90+H90+I90+J90+K90 -> 9 | G90: 3 | H90: 3 | I90: 1 | J90: 1 | K90: 1 | L90: Tidak ada proses manual | M90: 3 | N90: Segera menginformasikan kepada bagian terkait atas kendala di pihak ke-3 tersebut yang berdampak pada keterlambatan proses perhitungan experience study
A91: Reasuransi | B91: 1 | C91: Melakukan analisis risiko terhadap portofolio asuransi perusahaan dan menentukan kebutuhan reasuransi. Ini melibatkan identifikasi risiko-risiko tertentu, penilaian potensi kerugian, dan menentukan sejauh mana risiko tersebut dapat ditransfer ke reasuransi. | D91: melakukan reviu terhadap atas risiko yang akan direasuransikan, nilai retensi, TC , Rate,dll | E91: =(VLOOKUP(F91,Formula!$C$6:$D$26,2,FALSE)) -> Rendah (Low) | F91: =G91+H91+I91+J91+K91 -> 5 | G91: 1 | H91: 1 | I91: 1 | J91: 1 | K91: 1 | L91: Memang saat ini masih manual , jadi tidak ada impact ke BAU yg sekarang berjalan (Manual) | M91: Personel yg mumpuni dalam pengolahan data besar (Spread Sheet minimal) | N91: Akan dilakukan secara manual , maka dibutuhkan sistem kecil dibantu IT untuk penyediaan data yg bisa digunakan untuk analisa risiko.
A92: Reasuransi | B92: 2 | C92: Bertanggung jawab untuk bernegosiasi dengan perusahaan reasuransi terkait premi, syarat-syarat kontrak, batas retensi (retention limits), dan ketentuan lainnya dalam kontrak reasuransi. Tujuannya adalah untuk memastikan bahwa perusahaan asuransi mendapatkan perlindungan yang sesuai dengan kebutuhan. | D92: Negosiasi dengan perusahaan reasuransi terkait risiko yang akan ditransfer | E92: =(VLOOKUP(F92,Formula!$C$6:$D$26,2,FALSE)) -> Rendah (Low) | F92: =G92+H92+I92+J92+K92 -> 5 | G92: 1 | H92: 1 | I92: 1 | J92: 1 | K92: 1 | L92: Memang saat ini masih manual , jadi tidak ada impact ke BAU yg sekarang berjalan (Manual) | M92: Personel yg mumpuni dalam pengolahan data besar (Spread Sheet minimal) | N92: Akan dilakukan secara manual , maka dibutuhkan sistem kecil dibantu IT untuk penyediaan data yg bisa digunakan untuk analisa risiko.
A93: Reasuransi | B93: 3 | C93: Melakukan manajemen portofolio reasuransi perusahaan, termasuk mengelola kontrak reasuransi yang ada, meninjau dan menilai kinerja reasuransi, serta membuat keputusan terkait perubahan yang diperlukan. | D93: Reviu terhadap kontrak/treaty yang sudah berjalan | E93: =(VLOOKUP(F93,Formula!$C$6:$D$26,2,FALSE)) -> Rendah (Low) | F93: =G93+H93+I93+J93+K93 -> 5 | G93: 1 | H93: 1 | I93: 1 | J93: 1 | K93: 1 | L93: Review berkala berbasis checklist dan KPI. | M93: Dokumentasi perjanjian reasuransi di bagian legal. | N93: Centralized database kontrak reasuransi.
A94: Reasuransi | B94: 4 | C94: Patuhi regulasi asuransi dan reasuransi yang berlaku di wilayah Indonesia. Ini mencakup pelaporan yang diperlukan kepada regulator. | D94: Laporan reasuransi ke regulator (OJK) | E94: =(VLOOKUP(F94,Formula!$C$6:$D$26,2,FALSE)) -> Sedang Rendah (Moderate to Low) | F94: =G94+H94+I94+J94+K94 -> 10 | G94: 2 | H94: 2 | I94: 2 | J94: 2 | K94: 2 | L94: Review berkala berbasis checklist dan KPI. | M94: Centralized compliance checklist & kalender pelaporan. | N94: Four-eyes review sebelum pelaporan.
A95: CX Institutional | B95: 1 | C95: Pendaftaran kepesertaan | D95: Menerima pengajuan kepesertaan baik penambahan, pengurangan, perubahan plan dari PIC perusahaan melalui email dan memastikan pengajuan telah lengkap pengisian pada form pendaftaran untuk diproses lebih lanjut ke bagian New Business Administration (NBA) | E95: =(VLOOKUP(F95,Formula!$C$6:$D$26,2,FALSE)) -> Sedang (Medium) | F95: =G95+H95+I95+J95+K95 -> 13 | G95: 2 | H95: 3 | I95: 3 | J95: 3 | K95: 2 | L95: 1. Menerima permintaan penambahan/pengurangan peserta melalui email. 2. Memverifikasi data berdasarkan dokumen yang dikirim PIC. 3. Mengirimkan permintaan penambahan/pengurangan peserta ke Membership Via email atau hard copy. 4. Memberikan konfirmasi penerimaan kepada PIC melalui email. 5. Data akan di-input kembali setelah sistem pulih | M95: 1. Dua SDM staf administrasi kepesertaan. 2. Akses email aktif 3. Template Excel untuk pendaftaran peserta 4. Master data kepesertaan (backup EOD) 5. Akses Komunikasi via telepon/WA internal | N95: 1. Menginformasikan ke PIC Perusahaan mengenai keterlambatan proses. 2. Prioritaskan peserta yang butuh urgent penjaminan dan pengajuan klaim. 3. Koordinasi dengan departement terkait dilanjutkan sampai sistem pulih 4. Memberikan estimasi waktu pemulihan dan update berkala
A96: CX Institutional | B96: 2 | C96: Penanganan penyelesaian pertanyaan/keluhan melalui email dan telepon baik dari PIC perusahaan, team marketing dan peserta | D96: Memberikan penjelasan, informasi, report atas pertanyaan, keluhan, permintaan yang diterima melalui email dan telepon dari PIC perusahaan, team Marketing, maupun peserta mengenai pengajuan klaim, benefit asuransi, telemedicine, kepesertaan, dan permintaan report dari Marketing | E96: =(VLOOKUP(F96,Formula!$C$6:$D$26,2,FALSE)) -> Prioritas (High) | F96: =G96+H96+I96+J96+K96 -> 17 | G96: 2 | H96: 4 | I96: 3 | J96: 4 | K96: 4 | L96: 1. Mencatat setiap keluhan/pertanyaan pada Form Komplain Manual (Excel). 2. Memberikan jawaban berdasarkan data offline yang tersedia (master data EOD) 3. Memberikan update status kepada PIC/Marketing secara berkala melalui email/telpon | M96: 1. Dua SDM Customer Survice 2. File master data kepesertaan offline 3. Pencatatan komplain manual (Excel/Google Sheet) 4. Akses informasi benefit (table manfaat offline) | N96: 1. Mengirimkan pemberitahuan resmi kepada PIC/Marketing tentang keterlambatan respons 2. Menyampaikan informasi kebutuhan apa saja yang diperlukan secara offline untuk service ke nasabah 3. Menangani keluhan kategori urgent terlebih dahulu 4. Melakukan eskalasi ke atasan apabila ada keluhan yang membutuhkan penyelesain ke atasan. Memberikan update berkala sampai layanan normal
A97: EB | B97: 1 | C97: Proses penjualan produk dan pengiriman proposal penawaran melalui email dan atau telp | D97: Menawarkan asuransi kepada calon nasabah dan nasabah yang akan renewal melalui email dan atau telp kondisi pada saat server down | E97: =(VLOOKUP(F97,Formula!$C$6:$D$26,2,FALSE)) -> Prioritas (High) | F97: =G97+H97+I97+J97+K97 -> 18 | G97: 5 | H97: 5 | I97: 3 | J97: 3 | K97: 2 | L97: Komunikasi via email pribadi atau telepon by handphone | M97: Email | N97: Konfirmasi dan komunikasi via email pribadi atau telepon by handphone ke PIC perusahaan
A98: EB | B98: 2 | C98: Persetujuan pemberian referral fee | D98: Untuk produksi New Business dan Renewal Business yang ada referral fee kepada PIC Perusahaan (Contact Person) dan Agent ELI mapun Agent Non ELI perlu dilakukan persetujuan pada sistem group insurance | E98: =(VLOOKUP(F98,Formula!$C$6:$D$26,2,FALSE)) -> Sedang (Medium) | F98: =G98+H98+I98+J98+K98 -> 13 | G98: 2 | H98: 5 | I98: 2 | J98: 2 | K98: 2 | L98: Tidak bisa manual proses, sehingga harus menunggu sistem group insurance kembali beroperasi | M98: Sistem Group Insurance | N98: Konfirmasi kepada penerima referral fee bahwa telah terjadi gangguan pada sistem sehingga adanya pending untuk pembayaran referral fee
A99: Customer Engagement | B99: 1 | C99: Pengiriman campaign | D99: Mengirimkan pesan kepada nasabah melalui WA, email atau web portal | E99: =(VLOOKUP(F99,Formula!$C$6:$D$26,2,FALSE)) -> Sedang Rendah (Moderate to Low) | F99: =G99+H99+I99+J99+K99 -> 6 | G99: 1 | H99: 1 | I99: 1 | J99: 2 | K99: 1 | L99: Menghubungi IT dan vendor untuk koordinasi agar pengiriman dapat dijalankan menggunakan sistem secepatnya. | M99: 1 Engagement Programming dan 1 IT | N99: Membatalkan pengiriman campaign yang udah direncanakan.
A100: Customer Engagement | B100: 2 | C100: Penyelenggaraan online event | D100: Menyelenggarakan webinar mengenai kesehatan, financial planning untuk nasabah segmen tertentu | E100: =(VLOOKUP(F100,Formula!$C$6:$D$26,2,FALSE)) -> Sedang Rendah (Moderate to Low) | F100: =G100+H100+I100+J100+K100 -> 6 | G100: 1 | H100: 1 | I100: 1 | J100: 2 | K100: 1 | L100: Menghubungi IT apabila ada kendala jaringan agar media online tetap dapat berjalan. | M100: 1 Engagement Programming dan 1 IT | N100: Menggunakan jaringan internet back up dari IT.
A101: Customer Engagement | B101: 3 | C101: Pengajuan transaksi melalui web portal nasabah | D101: Nasabah dapat mengajukan transaksi tertentu seperti pengkinian data, top up tunggal, ubah ahli waris melalui web portal nasabah (My eLife) | E101: =(VLOOKUP(F101,Formula!$C$6:$D$26,2,FALSE)) -> Sedang Rendah (Moderate to Low) | F101: =G101+H101+I101+J101+K101 -> 7 | G101: 1 | H101: 1 | I101: 2 | J101: 2 | K101: 1 | L101: Pengajuan dilakukan secara manual. | M101: 1 Contact Center, 1 CX POS dan 1 IT | N101: Nasabah diarahkan untuk melakukan pengajuan transaksi secara manual melalui sarana lainnya seperti menghubungi Contact Center atau datang ke kantor pemasaran terdekat.
A102: Internal Audit | B102: 1 | C102: Internal Kontrol | D102: 1) Melakukan verifikasi transaksi harian yang diajukan oleh nasabah dan diproses oleh Branch Services pada aplikasi EDITS 2) Melakukan verifikasi kesesuaian informasi pada aplikasi EDITS dengan informasi yang diinput pada aplikasi E-BASE (PL) oleh Individual Customer Solution 3) Hasil verifikasi audit dokumen diproses pada aplikasi EDITS dengan menambahkan audit proses dan audit status Frekuensi: Harian | E102: =(VLOOKUP(F102,Formula!$C$6:$D$26,2,FALSE)) -> Sedang (Medium) | F102: =G102+H102+I102+J102+K102 -> 11 | G102: 1 | H102: 2 | I102: 3 | J102: 2 | K102: 3 | L102: Verifikasi dapat dilakukan dengan pengecekan dokumen pengajuan transaksi harian (pada Kantor Pemasaran yang menjadi objek pemeriksaan oleh Internal Kontrol) sesuai mekanisme yang diterapkan oleh Branch Services dan Individual Customer Solution | M102: SDM: 1 personil Sistem: E-DITS dan PL Network: Email dan VPN Hardware: Laptop | N102: - Proses verifikasi dilakukan secara manual, dokumen yang dikirimkan oleh Branch Service kepada Individual Customer Solution diteruskan kepada Internal Kontrol - Request database nasabah kepada Divisi IT Operation untuk verifikasi data nasabah - Request rekaman telefon konfirmasi oleh Individual Customer Solution kepada nasabah kepada Divisi IT Operation
... A140: IT | B140: 18 | C140: Ad-hoc Data Analysis | D140: Analisis data untuk mendukung kebutuhan bisnis dan pengambilan keputusan manajemen | E140: =(VLOOKUP(F140,Formula!$C$6:$D$26,2,FALSE)) -> Prioritas (High) | F140: =G140+H140+I140+J140+K140 -> 20 | G140: 4 | H140: 4 | I140: 4 | J140: 4 | K140: 4 | L140: Analisis ditunda atau menggunakan data historis terbatas dengan penyesuaian ruang lingkup analisis | M140: Dataset historis, analis data | N140: Penyesuaian scope analisis dan komunikasi resmi ke stakeholder terkait keterbatasan data
A141: Agency | B141: 1 | C141: Rekrutmen agen | D141: Proses perekrutan agen baru, seleksi administrasi, wawancara | E141: =(VLOOKUP(F141,Formula!$C$6:$D$26,2,FALSE)) -> Rendah (Low) | F141: =G141+H141+I141+J141+K141 -> 5 | G141: 1 | H141: 1 | I141: 1 | J141: 1 | K141: 1 | L141: Ceklist manual dan cross-check dokumen pendukung
A142: Agency | B142: 2 | C142: Aktivitas Penjualan Polis | D142: Proses pemasaran, penawaran produk, pengisian SPAJ dan kelengkapan dokumen calon nasabah | E142: =(VLOOKUP(F142,Formula!$C$6:$D$26,2,FALSE)) -> Sedang Rendah (Moderate to Low) | F142: =G142+H142+I142+J142+K142 -> 10 | G142: 2 | H142: 2 | I142: 2 | J142: 2 | K142: 2 | L142: SPAJ diserahkan ke Underwriting secara scan dan informasi by email
A143: Agency | B143: 3 | C143: Validasi dan Submission SPAJ | D143: Pemeriksaan kelengkapan dan keakuratan SPAJ sebelum dikirim ke Underwriting | E143: =(VLOOKUP(F143,Formula!$C$6:$D$26,2,FALSE)) -> Sedang Rendah (Moderate to Low) | F143: =G143+H143+I143+J143+K143 -> 10 | G143: 2 | H143: 2 | I143: 2 | J143: 2 | K143: 2 | L143: Ceklist manual dan cross-check dokumen pendukung
A144: Agency | B144: 4 | C144: Penanganan Keluhan Nasabah terkait Agen | D144: Proses investigasi dan penyelesaian komplain nasabah | E144: =(VLOOKUP(F144,Formula!$C$6:$D$26,2,FALSE)) -> Sedang Rendah (Moderate to Low) | F144: =G144+H144+I144+J144+K144 -> 10 | G144: 2 | H144: 2 | I144: 2 | J144: 2 | K144: 2 | L144: Keluhan diterima via email dan dicatat pada register manual
A145: Agency | B145: 5 | C145: Lisensi & Registrasi Agen (AAJI/OJK) | D145: Pengurusan lisensi, registrasi dan status keagenan sesuai regulasi | E145: =(VLOOKUP(F145,Formula!$C$6:$D$26,2,FALSE)) -> Sedang (Medium) | F145: =G145+H145+I145+J145+K145 -> 15 | G145: 3 | H145: 3 | I145: 3 | J145: 3 | K145: 3
A146: Agency | B146: 6 | C146: Pelatihan & Sertifikasi Agen | D146: Pelatihan Produk, etika, kepatuhan dan pengetahuan regulasi | E146: =(VLOOKUP(F146,Formula!$C$6:$D$26,2,FALSE)) -> Sedang Rendah (Moderate to Low) | F146: =G146+H146+I146+J146+K146 -> 10 | G146: 2 | H146: 2 | I146: 2 | J146: 2 | K146: 2
A147: Agency | B147: 7 | C147: Komisi Agen | D147: Perhitungan, pencatatan dan pembayaran komisi agen | E147: =(VLOOKUP(F147,Formula!$C$6:$D$26,2,FALSE)) -> Rendah (Low) | F147: =G147+H147+I147+J147+K147 -> 5 | G147: 1 | H147: 1 | I147: 1 | J147: 1 | K147: 1
A148: Agency | B148: 8 | C148: Validasi kinerja Agen dan Kepatuhan | D148: Pemantauan target penjualan, persistency, dan kepatuhan agen | E148: =(VLOOKUP(F148,Formula!$C$6:$D$26,2,FALSE)) -> Sedang Rendah (Moderate to Low) | F148: =G148+H148+I148+J148+K148 -> 10 | G148: 2 | H148: 2 | I148: 2 | J148: 2 | K148: 2
A149: Agency | B149: 9 | C149: Terminasi dan Disiplin Agen | D149: Pemberhentian agen yang melanggar aturan atau non aktif sesuai ketentuan | E149: =(VLOOKUP(F149,Formula!$C$6:$D$26,2,FALSE)) -> Sedang Rendah (Moderate to Low) | F149: =G149+H149+I149+J149+K149 -> 10 | G149: 2 | H149: 2 | I149: 2 | J149: 2 | K149: 2
A150: Sysdur | C150: Set Up Akses

Sheet Penilaian
A1: Keterkaitan Bisnis Proses dengan Sistem Informasi
A3: No. | B3: Bisnis Proses Kritikal | C3: Penjelasan Singkat Bisnis Proses Kritikal | D3: Prioritas (1 …5) (Diisi oleh Tim BCP) | E3: Aspek Dampak | L3: Manual Proses Saat Sistem Informasi Terganggu | M3: Minimum Resource Required | N3: Apa yang harus dilakukan jika sampai tenggang waktu tersebut, bisnis proses ini belum bisa tersedia
E4: Finansial | F4: Waktu | G4: Operasional | H4: Reputasi | I4: Kepatuhan
A5: 1 | B5: Produk Pricing dan Repricing | C5: Penetapan dan penyesuaian premi | E5: 2 | F5: 2 | G5: 2 | H5: 2 | I5: 2 | J5: =SUM(E5:I5) -> 10 | L5: Excel Pricing template dan manual approval | M5: PM, ACT, RM | N5: Freeze penjualan produk terkait
A6: 2 | B6: Product Approval & Governance | C6: Persetujuan internal dan perubahannya | E6: 2 | F6: 3 | G6: 2 | H6: 2 | I6: 2 | J6: =SUM(E6:I6) -> 11 | L6: Hardcopy sign off approval | M6: PM, ACT, INV, L&C, OPS | N6: Eskalasi ke management
A7: 3 | B7: Product Filing ke OJK | C7: Pelaporan/Persetujuan produk melalui sistem elektronik OJK | E7: 2 | F7: 2 | G7: 3 | H7: 2 | I7: 1 | J7: =SUM(E7:I7) -> 10 | L7: Excel manual dokumen tracking | M7: PM, ACT, INV, OPS | N7: Mengirimkan dokumen secara offline ke OJK dan konfirmasi ke PIC OJK terkait
A8: 4 | B8: Produk Launch rediness | C8: Kesiapan produk sebelum go live (proses UAT) | E8: 2 | F8: 2 | G8: 2 | H8: 2 | I8: 2 | J8: =SUM(E8:I8) -> 10 | L8: Manual checklist dan meeting kordinasi | M8: PM, ACT, IT, OPS, INV, FIN, ACC | N8: Eskalasi ke management untuk menunda peluncuran produk
A9: 5 | B9: Product Enhancement | C9: Penyesuaian manfaat & Fitur Produk | E9: 3 | F9: 3 | G9: 3 | H9: 3 | I9: 3 | J9: =SUM(E9:I9) -> 15 | L9: Proposal Manual + Offline Simulation (Excel) | M9: PM, ACT, OPS | N9: Tunda enhancement, Freeze penjualan produk terkait/penjualan secara terbatas
A10: 6 | B10: Sales Illustration & Manfaat | C10: Ilustrasi manfaat dan simulasi premi | E10: 2 | F10: 2 | G10: 2 | H10: 2 | I10: 2 | J10: =SUM(E10:I10) -> 10 | L10: Proposal Manual + Offline Simulation (Excel) | M10: PM, ACT, OPS | N10: Gunakan Excel Illustration, dan print secara manual
A11: 7 | B11: Produk Communication internal | C11: Sosialisasi internal dan external user | E11: 3 | F11: 3 | G11: 3 | H11: 3 | I11: 5 | J11: =SUM(E11:I11) -> 17 | L11: Mengunakan WA Group/Blast | M11: PM, Ops | N11: Email blast/Offline Training/Online training mengunakan 3rd party (Zoom, Gmet, WA Group Etc)
A12: 8 | B12: Lisence Sofware dan Aset Kreatif | C12: Subscription account dan annual fee untuk mengunakan layanan ini | E12: 3 | F12: 2 | G12: 3 | H12: 4 | I12: 5 | J12: =SUM(E12:I12) -> 17 | L12: Mengunakan Adobe Creative Suites | M12: PM | N12: Desain secara manual mengunakan Adobe Creative Series
A13: 9
A14: 10

Sheet (3) Keterlibatan Pihak Ketiga
A1: Keterlibatan Pihak Ketiga/Partner
A3: No. | B3: Bisnis Proses Kritikal | C3: Nama Pihak Ketiga atan Partner Terkait | D3: Kontak Informasi No. Telepon Pihak Ketiga | E3: Kontak Informasi Email Pihak Ketiga | F3: Hari Maksimal menginfokan Pihak Ketiga | G3: Apakah proses internal dapat dilakukan oleh Divisi terkait
A4: 1 | B4: Pelaporan produk pada sistem elektronik OJK | C4: OJK | D4: Helpdesk Sistem Informasi OJK Telp. : 021-29600000 ext. 7000 : 021-29600296 (DID) VOIP : 301-7000 | E4: helpdesk@ojk.go.id | G4: Menginformasikan via email atau telp terkait error tersebut untuk dapat segera diperbaiki
A5: 2 | B5: UAT Product dan/atau Proposal Ilustrasi | C5: Bug pada sistem ELI | D5: Dynafront - Lim Shy Huey, Wong Ching Han | E5: shlim@dynafront.com chwong@dynafront.com | G5: Menginformasikan via email atau telp terkait error tersebut untuk dapat segera diperbaiki
A6: 3 | B6: License Software dan Creative Asset | C6: Approval Permintaan Barang (Subscription fee), Adobe Creative Cloud, Canva, Freepik | E6: customercare-chatsupport@adobe.com, info@email-freepik.com, support@canva.com
A7: 4
A8: 5
A9: 6
A10: 7
A11: 8
A12: 9
A13: 10

Sheet Panduan
B4: No | C4: Kolom | D4: Keterangan | F4: *Dampak
B5: 1) | C5: Departemen/Divisi | D5: Diisi dengan Departemen/Divisi dimaksud. | F5: Nilai | G5: Deskripsi | H5: Finansial | I5: Waktu Gangguan | J5: Operasional | K5: Reputasi | L5: Kepatuhan
C6: Deskripsi Tugas Pokok dan Fungsi | D6: Diisi dengan Tugas Pokok dan Fungsi dari Divisi/Departemen dimaksud. | F6: 1 | G6: Sangat Rendah | H6: <Rp10jt (Lost) | I6: <1 Jam | J6: Tidak berdampak terhadap:pemasaran, dan pelayanan kepada nasabah | K6: Tidak berdampak ke nasabah | L6: Tidak terkait kewajiban Regulator
C7: Jumlah Karyawan | D7: Diisi dengan jumlah Karyawan dari Divisi/Departemen dimaksud. | F7: 2 | G7: Rendah | H7: >Rp10-100Jt(Lost) | I7: 1-3 Jam | J7: Sedikit berdampak terhadap:pemasaran, pelayanan dan operasional kepada nasabah | K7: Keluhan terbatas | L7: Keterlambatan administratif ringan
C8: Nama Pimpinan Departemen/Divisi | D8: Diisi dengan nama Pimpinan Divisi/Departemen dimaksud. | F8: 3 | G8: Sedang | H8: >Rp100-500Jt(Lost) | I8: 4-6 Jam | J8: Cukup berdampak terhadap:pemasaran, pelayanan dan operasional kepada nasabah | K8: Keluhan meluas | L8: Potensi teguran regulator
C9: Nama Koordinator Business Continuity | D9: Diisi dengan nama PIC yang ditunjuk dalam pengelolaan administrasi BCP dari Divisi/Departemen dimaksud. | F9: 4 | G9: Tinggi | H9: >Rp500Jt-1Miliar(Lost) | I9: >6-8 Jam | J9: Sangat berdampak terhadap:pemasaran, pelayanan dan operasional kepada nasabah | K9: Pemberitaan Negatif | L9: Pelanggaran ketentuan OJK
C10: Tanggal Terakhir Update | D10: Diisi dengan tanggal dalam melakukan pengisian BIA. | F10: 5 | G10: Sangat Tinggi | H10: >Rp1Miliar(Lost) | I10: >8 Jam | J10: Proses pemasaran, pelayanan dan operasional terhenti di hari insiden | K10: Penurunan kepercayaan signifikan | L10: Sanksi Berat/Pembekuan Kegiatan
B11: 2) | C11: Bisnis Proses Kritikal | D11: Diisi dengan proses yang tetap harus berjalan pada saat terjadinya risiko. Dengan menyertakan keterangan (proses yang dilakukan): Harian; Bulanan; Tahunan; Lainnya...
C12: Penjelasan Singkat Bisnis Proses Kritikal | D12: Diisi dengan penjelasan singkat atas bisnis proses kritikal yang di identifikasi sesuai kategori bisnis proses kritikal.
C13: Prioritas (1 … 5) | D13: Diisi dengan skala prioritas dari bisnis proses kritikal yang telah di identifikasi. 1. Sangat Prioritas (Critical) -> Harus dipulihkan segera 2. Prioritas (High) -> dipulihkan setelah fungsi kritikal 3. Sedang (Medium) -> Bisa ditunda sementara 4. Sedang Rendah (Moderate to Low) -> Tidak memerlukan BCP Khusus 5. Rendah (Low) -> Tidak berdampak secara langsung/tidak langsung
C14: Aspek Dampak* | D14: Diisi dengan pengaruh dampak langsung atas peristiwa yang mengganggu proses bisnis Divisi/Departemen, yaitu (sesuai parameter): Finansial, Waktu, Operasional, Reputasi, Kepatuhan
C15: Manual Proses Saat Sistem Informasi Terganggu | D15: Diisi dengan tindakan yang dapat dilakukan oleh Divisi/Departemen terkait pada saat itu dalam mengatasi risiko yang timbul.
C16: Minimum Resource Required | D16: Diisi dengan: Jumlah SDM atas Proses Critical; Sistem; Vendor (apabila ada). Lainnya:…..
C17: Apa yang harus dilakukan jika sampai tenggang waktu tersebut, bisnis proses ini belum bisa tersedia | D17: Diisi dengan usulan perubahan bisnis proses sementara saat penangangan insiden
B18: 3) | C18: Bisnis Proses Kritikal | D18: Diisi dengan proses yang tetap harus berjalan pada saat terjadinya risiko yang dilakukan oleh Vendor. Dengan menyertakan keterangan (proses yang dilakukan): Harian; Bulanan; Tahunan; Lainnya:....
C19: Nama Pihak Ketiga atau Partner Terkait | D19: Diisi dengan nama Perusahaan (Vendor)
C20: Kontak Informasi No. Telepon Pihak Ketiga | D20: Diisi dengan informasi Perusahaan (Vendor); Telpon, PIC, dst
C21: Kontak Informasi Email Pihak Ketiga | D21: Diisi dengan informasi email Perusahaan (Vendor)
C22: Hari Maksimal menginfokan Pihak Ketiga | D22: Lama waktu dalam penyampaian informasi kepada Perusahaan (Vendor)
C23: Apakah proses dapat dilakukan oleh Divisi terkait | D23: Diisi dengan proses bisnis apakah dapat dilakukan oleh internal Divisi tanpa melalui Vendor

Sheet Formula
B4: Total Impact Score = Finansial + Waktu + Operasional + Reputasi + Kepatuhan
B5: Level | C5: Score | D5: Keterangan
B6: 1 | C6: 25 | D6: Sangat Prioritas (Very High)
C7: 24 | D7: Sangat Prioritas (Very High)
C8: 23 | D8: Sangat Prioritas (Very High)
C9: 22 | D9: Sangat Prioritas (Very High)
C10: 21 | D10: Sangat Prioritas (Very High)
B11: 2 | C11: 20 | D11: Prioritas (High)
C12: 19 | D12: Prioritas (High)
C13: 18 | D13: Prioritas (High)
C14: 17 | D14: Prioritas (High)
C15: 16 | D15: Prioritas (High)
B16: 3 | C16: 15 | D16: Sedang (Medium)
C17: 14 | D17: Sedang (Medium)
C18: 13 | D18: Sedang (Medium)
C19: 12 | D19: Sedang (Medium)
C20: 11 | D20: Sedang (Medium)
B21: 4 | C21: 10 | D21: Sedang Rendah (Moderate to Low)
C22: 9 | D22: Sedang Rendah (Moderate to Low)
C23: 8 | D23: Sedang Rendah (Moderate to Low)
C24: 7 | D24: Sedang Rendah (Moderate to Low)
C25: 6 | D25: Sedang Rendah (Moderate to Low)
B26: 5 | C26: 5 | D26: Rendah (Low)
